{"type": "FeatureCollection", "features": [{"type": "Feature", "id": 3359, "geometry": {"type": "Point", "coordinates": [114.5816240001476, 30.674640000435716]}, "properties": {"OBJECTID": 3359, "poiid": "B0FFI7FD5I", "name": "潘庙广场", "address": "阳逻街潘庙新家园", "type": "风景名胜;公园广场;城市广场|购物服务;综合市场;农副产品市场", "typecode": "110105|060703", "pcode": 420000, "pname": "湖北省", "citycode": 27, "cityname": "武汉市", "adcode": 420117, "adname": "新洲区", "business_a": "阳逻", "location": "114.581624,30.674640", "tel": " ", "fetch_time": "19/1/2025 20:59:21", "大类": "风景名胜", "中类": "公园广场", "小类": "城市广场|购物服务;综合市场;农副产品市场", "wgs84经ti": 114.576552, "wgs84纬ti": 30.677243}}]}