{"type": "FeatureCollection", "features": [{"type": "Feature", "id": 5238, "geometry": {"type": "Point", "coordinates": [114.40534099978743, 30.43399799990783]}, "properties": {"OBJECTID": 5238, "poiid": "B001B0J071", "name": "藏龙岛", "address": "藏龙大道", "type": "风景名胜;公园广场;植物园|风景名胜;风景名胜;风景名胜", "typecode": "110103|110200", "pcode": 420000, "pname": "湖北省", "citycode": 27, "cityname": "武汉市", "adcode": 420115, "adname": "江夏区", "business_a": " ", "location": "114.405341,30.433998", "tel": " ", "fetch_time": "19/1/2025 06:41:12", "大类": "风景名胜", "中类": "公园广场", "小类": "植物园|风景名胜;风景名胜;风景名胜", "wgs84经ti": 114.39981, "wgs84纬ti": 30.436323}}]}