{"type": "FeatureCollection", "features": [{"type": "Feature", "id": 4714, "geometry": {"type": "Point", "coordinates": [114.01937999958739, 30.53522999986467]}, "properties": {"OBJECTID": 4714, "poiid": "B0K60DYMHD", "name": "缤纷水族", "address": "通城大道与连通路交叉口西南320米", "type": "风景名胜;公园广场;水族馆|购物服务;花鸟鱼虫市场;花鸟鱼虫市场", "typecode": "110104|060500", "pcode": 420000, "pname": "湖北省", "citycode": 27, "cityname": "武汉市", "adcode": 420114, "adname": "蔡甸区", "business_a": " ", "location": "114.019380,30.535230", "tel": " ", "fetch_time": "19/1/2025 07:22:04", "大类": "风景名胜", "中类": "公园广场", "小类": "水族馆|购物服务;花鸟鱼虫市场;花鸟鱼虫市场", "wgs84经ti": 114.013733, "wgs84纬ti": 30.537659}}]}