{"type": "FeatureCollection", "features": [{"type": "Feature", "id": 4538, "geometry": {"type": "Point", "coordinates": [114.28020299996854, 30.62944700007904]}, "properties": {"OBJECTID": 4538, "poiid": "B0FFGIGHZB", "name": "捷豹路虎4S店(武汉路泽)", "address": "石桥二路7号1号轻工车间1-5层", "type": "汽车销售;捷豹特约销售;捷豹销售|汽车维修;捷豹特约维修;捷豹维修", "typecode": "021900|032000", "pcode": 420000, "pname": "湖北省", "citycode": 27, "cityname": "武汉市", "adcode": 420102, "adname": "江岸区", "business_a": "后湖", "location": "114.280203,30.629447", "tel": "027-59335888", "fetch_time": "19/1/2025 19:37:50", "大类": "汽车销售", "中类": "捷豹特约销售", "小类": "捷豹销售|汽车维修;捷豹特约维修;捷豹维修", "wgs84经ti": 114.274781, "wgs84纬ti": 30.631878}}]}