{"type": "FeatureCollection", "features": [{"type": "Feature", "id": 39442, "geometry": {"type": "Point", "coordinates": [114.26646100027506, 30.568985999804113]}, "properties": {"OBJECTID": 39442, "poiid": "B0FFFDVTJZ", "name": "SOMERSET(凯德广场店)", "address": "中山大道238号凯德广场F7", "type": "购物服务;商场;普通商场|住宿服务;宾馆酒店;宾馆酒店", "typecode": "060102|100100", "pcode": 420000, "pname": "湖北省", "citycode": 27, "cityname": "武汉市", "adcode": 420104, "adname": "硚口区", "business_a": "荣华", "location": "114.266461,30.568986", "tel": " ", "fetch_time": "19/1/2025 21:25:06", "大类": "购物服务", "中类": "商场", "小类": "普通商场|住宿服务;宾馆酒店;宾馆酒店", "wgs84经ti": 114.26105, "wgs84纬ti": 30.571453}}]}