{"type": "FeatureCollection", "features": [{"type": "Feature", "id": 23089, "geometry": {"type": "Point", "coordinates": [114.33281199967416, 30.537946000107866]}, "properties": {"OBJECTID": 23089, "poiid": "B0FFF33YJG", "name": "天紫广场", "address": "中南路(地铁站)B口步行119米", "type": "购物服务;商场;普通商场|购物服务;专卖店;珠宝首饰工艺品|商务住宅;商务住宅相关;商务住宅相关", "typecode": "060102|061202|120000", "pcode": 420000, "pname": "湖北省", "citycode": 27, "cityname": "武汉市", "adcode": 420106, "adname": "武昌区", "business_a": "中南路/中南", "location": "114.332812,30.537946", "tel": " ", "fetch_time": "19/1/2025 20:53:13", "大类": "购物服务", "中类": "商场", "小类": "普通商场|购物服务;专卖店;珠宝首饰工艺品|商务住宅;商务住宅相关;商务住宅相关", "wgs84经ti": 114.327329, "wgs84纬ti": 30.540324}}, {"type": "Feature", "id": 183205, "geometry": {"type": "Point", "coordinates": [114.33275099955904, 30.537906000061923]}, "properties": {"OBJECTID": 183205, "poiid": "B0FFF33YJG", "name": "天紫广场", "address": "中南路特9号", "type": "购物服务;商场;普通商场|购物服务;专卖店;珠宝首饰工艺品|商务住宅;商务住宅相关;商务住宅相关", "typecode": "060102|061202|120000", "pcode": 420000, "pname": "湖北省", "citycode": 27, "cityname": "武汉市", "adcode": 420106, "adname": "武昌区", "business_a": "中南路/中南", "location": "114.332751,30.537906", "tel": " ", "fetch_time": "19/1/2025 06:50:50", "大类": "购物服务", "中类": "商场", "小类": "普通商场|购物服务;专卖店;珠宝首饰工艺品|商务住宅;商务住宅相关;商务住宅相关", "wgs84经ti": 114.327268, "wgs84纬ti": 30.540285}}]}