{"type": "FeatureCollection", "features": [{"type": "Feature", "id": 29923, "geometry": {"type": "Point", "coordinates": [114.28327400039484, 30.57729599991052]}, "properties": {"OBJECTID": 29923, "poiid": "B0FFFQ88MF", "name": "御美广场", "address": "六渡桥(地铁站)C2口步行299米", "type": "购物服务;商场;普通商场|购物服务;专卖店;专营店", "typecode": "060102|061200", "pcode": 420000, "pname": "湖北省", "citycode": 27, "cityname": "武汉市", "adcode": 420103, "adname": "江汉区", "business_a": "江滩", "location": "114.283274,30.577296", "tel": " ", "fetch_time": "19/1/2025 20:44:09", "大类": "购物服务", "中类": "商场", "小类": "普通商场|购物服务;专卖店;专营店", "wgs84经ti": 114.277855, "wgs84纬ti": 30.579744}}, {"type": "Feature", "id": 30202, "geometry": {"type": "Point", "coordinates": [114.26242600035971, 30.593027999642516]}, "properties": {"OBJECTID": 30202, "poiid": "B0FFK66BA7", "name": "金叶阳光(国烟草王家墩店)", "address": "万松街街道青年路187号兴盛大厦一楼", "type": "购物服务;商场;普通商场|购物服务;专卖店;专营店", "typecode": "060102|061200", "pcode": 420000, "pname": "湖北省", "citycode": 27, "cityname": "武汉市", "adcode": 420103, "adname": "江汉区", "business_a": "建设大道", "location": "114.262426,30.593028", "tel": " ", "fetch_time": "19/1/2025 20:44:37", "大类": "购物服务", "中类": "商场", "小类": "普通商场|购物服务;专卖店;专营店", "wgs84经ti": 114.257012, "wgs84纬ti": 30.595488}}, {"type": "Feature", "id": 182910, "geometry": {"type": "Point", "coordinates": [114.28327400039484, 30.57729599991052]}, "properties": {"OBJECTID": 182910, "poiid": "B0FFFQ88MF", "name": "御美广场", "address": "前进一路与民主二街交叉口北40米", "type": "购物服务;商场;普通商场|购物服务;专卖店;专营店", "typecode": "060102|061200", "pcode": 420000, "pname": "湖北省", "citycode": 27, "cityname": "武汉市", "adcode": 420103, "adname": "江汉区", "business_a": "江滩", "location": "114.283274,30.577296", "tel": " ", "fetch_time": "19/1/2025 06:25:01", "大类": "购物服务", "中类": "商场", "小类": "普通商场|购物服务;专卖店;专营店", "wgs84经ti": 114.277855, "wgs84纬ti": 30.579744}}]}