{"type": "FeatureCollection", "features": [{"type": "Feature", "id": 3073, "geometry": {"type": "Point", "coordinates": [114.15190600016183, 30.476071000276477]}, "properties": {"OBJECTID": 3073, "poiid": "B0FFHAHZUQ", "name": "经发进口商品交易中心", "address": "沌口街办事处经济开发区创业路1楼", "type": "购物服务;商场;普通商场|购物服务;商场;免税品店", "typecode": "060102|060103", "pcode": 420000, "pname": "湖北省", "citycode": 27, "cityname": "武汉市", "adcode": 420114, "adname": "蔡甸区", "business_a": "沌口", "location": "114.151906,30.476071", "tel": " ", "fetch_time": "19/1/2025 21:06:45", "大类": "购物服务", "中类": "商场", "小类": "普通商场|购物服务;商场;免税品店", "wgs84经ti": 114.146279, "wgs84纬ti": 30.478443}}]}