{"type": "FeatureCollection", "features": [{"type": "Feature", "id": 3321, "geometry": {"type": "Point", "coordinates": [114.3489130002348, 30.715912999885063]}, "properties": {"OBJECTID": 3321, "poiid": "B0G3UO47S0", "name": "房东直租", "address": "汉口北大道与滠横路交叉口西南60米", "type": "住宿服务;旅馆招待所;旅馆招待所|生活服务;生活服务场所;生活服务场所", "typecode": "100200|070000", "pcode": 420000, "pname": "湖北省", "citycode": 27, "cityname": "武汉市", "adcode": 420116, "adname": "黄陂区", "business_a": "滠口", "location": "114.348913,30.715913", "tel": " ", "fetch_time": "19/1/2025 20:48:30", "大类": "住宿服务", "中类": "旅馆招待所", "小类": "旅馆招待所|生活服务;生活服务场所;生活服务场所", "wgs84经ti": 114.343389, "wgs84纬ti": 30.718188}}, {"type": "Feature", "id": 3322, "geometry": {"type": "Point", "coordinates": [114.44866999962085, 31.073951000238537]}, "properties": {"OBJECTID": 3322, "poiid": "B0G21Z6ZIT", "name": "绿道驿站", "address": " ", "type": "住宿服务;旅馆招待所;旅馆招待所|生活服务;生活服务场所;生活服务场所", "typecode": "100200|070000", "pcode": 420000, "pname": "湖北省", "citycode": 27, "cityname": "武汉市", "adcode": 420116, "adname": "黄陂区", "business_a": " ", "location": "114.448670,31.073951", "tel": " ", "fetch_time": "19/1/2025 20:48:30", "大类": "住宿服务", "中类": "旅馆招待所", "小类": "旅馆招待所|生活服务;生活服务场所;生活服务场所", "wgs84经ti": 114.443156, "wgs84纬ti": 31.076018}}, {"type": "Feature", "id": 3429, "geometry": {"type": "Point", "coordinates": [114.43451599981358, 30.953706000331692]}, "properties": {"OBJECTID": 3429, "poiid": "B001B17SYK", "name": "阳光驿站", "address": "955医院", "type": "住宿服务;旅馆招待所;旅馆招待所|生活服务;生活服务场所;生活服务场所", "typecode": "100200|070000", "pcode": 420000, "pname": "湖北省", "citycode": 27, "cityname": "武汉市", "adcode": 420116, "adname": "黄陂区", "business_a": " ", "location": "114.434516,30.953706", "tel": " ", "fetch_time": "19/1/2025 20:48:44", "大类": "住宿服务", "中类": "旅馆招待所", "小类": "旅馆招待所|生活服务;生活服务场所;生活服务场所", "wgs84经ti": 114.428979, "wgs84纬ti": 30.955819}}]}