{"type": "FeatureCollection", "features": [{"type": "Feature", "id": 3293, "geometry": {"type": "Point", "coordinates": [114.3696759999475, 30.877280000371798]}, "properties": {"OBJECTID": 3293, "poiid": "B0FFJY7FZP", "name": "时尚住宿(武汉黄陂店)", "address": "向阳大道396号", "type": "住宿服务;旅馆招待所;旅馆招待所|购物服务;便民商店/便利店;便民商店/便利店", "typecode": "100200|060200", "pcode": 420000, "pname": "湖北省", "citycode": 27, "cityname": "武汉市", "adcode": 420116, "adname": "黄陂区", "business_a": "前川", "location": "114.369676,30.877280", "tel": "15072438944", "fetch_time": "19/1/2025 20:48:28", "大类": "住宿服务", "中类": "旅馆招待所", "小类": "旅馆招待所|购物服务;便民商店/便利店;便民商店/便利店", "wgs84经ti": 114.364113, "wgs84纬ti": 30.879436}}]}