{"type": "FeatureCollection", "features": [{"type": "Feature", "id": 518, "geometry": {"type": "Point", "coordinates": [114.20175600033917, 30.59549099990977]}, "properties": {"OBJECTID": 518, "poiid": "B001B0JQVV", "name": "百分百(解放大道)", "address": "解放大道109附66辛家地车站", "type": "体育休闲服务;娱乐场所;KTV|购物服务;服装鞋帽皮具店;服装鞋帽皮具店", "typecode": "080302|061100", "pcode": 420000, "pname": "湖北省", "citycode": 27, "cityname": "武汉市", "adcode": 420104, "adname": "硚口区", "business_a": "古田", "location": "114.201756,30.595491", "tel": " ", "fetch_time": "19/1/2025 21:16:27", "大类": "体育休闲服务", "中类": "娱乐场所", "小类": "KTV|购物服务;服装鞋帽皮具店;服装鞋帽皮具店", "wgs84经ti": 114.196258, "wgs84纬ti": 30.597913}}, {"type": "Feature", "id": 8436, "geometry": {"type": "Point", "coordinates": [114.34877500016614, 30.60723600014137]}, "properties": {"OBJECTID": 8436, "poiid": "B001B16C8P", "name": "郁金香(铁机路)", "address": "铁机路5-105号附近", "type": "体育休闲服务;娱乐场所;KTV|购物服务;服装鞋帽皮具店;服装鞋帽皮具店", "typecode": "080302|061100", "pcode": 420000, "pname": "湖北省", "citycode": 27, "cityname": "武汉市", "adcode": 420106, "adname": "武昌区", "business_a": "杨园", "location": "114.348775,30.607236", "tel": " ", "fetch_time": "19/1/2025 22:40:28", "大类": "体育休闲服务", "中类": "娱乐场所", "小类": "KTV|购物服务;服装鞋帽皮具店;服装鞋帽皮具店", "wgs84经ti": 114.343261, "wgs84纬ti": 30.60956}}, {"type": "Feature", "id": 9843, "geometry": {"type": "Point", "coordinates": [114.3160799996923, 30.621882000154244]}, "properties": {"OBJECTID": 9843, "poiid": "B0FFH7EY4J", "name": "公馆KTV(二七店)", "address": "解放大道2159号东部购物公园C2座3层(中影国际影城)", "type": "体育休闲服务;娱乐场所;KTV|购物服务;服装鞋帽皮具店;服装鞋帽皮具店", "typecode": "080302|061100", "pcode": 420000, "pname": "湖北省", "citycode": 27, "cityname": "武汉市", "adcode": 420102, "adname": "江岸区", "business_a": "二七", "location": "114.316080,30.621882", "tel": "027-82220188", "fetch_time": "19/1/2025 09:08:25", "大类": "体育休闲服务", "中类": "娱乐场所", "小类": "KTV|购物服务;服装鞋帽皮具店;服装鞋帽皮具店", "wgs84经ti": 114.310617, "wgs84纬ti": 30.624261}}, {"type": "Feature", "id": 14129, "geometry": {"type": "Point", "coordinates": [114.34346299981769, 30.523841999908427]}, "properties": {"OBJECTID": 14129, "poiid": "B0FFF5UOKY", "name": "浪漫满屋(街道口南路店)", "address": "石牌岭竹苑小区", "type": "体育休闲服务;娱乐场所;KTV|购物服务;服装鞋帽皮具店;服装鞋帽皮具店", "typecode": "080302|061100", "pcode": 420000, "pname": "湖北省", "citycode": 27, "cityname": "武汉市", "adcode": 420111, "adname": "洪山区", "business_a": "街道口", "location": "114.343463,30.523842", "tel": " ", "fetch_time": "19/1/2025 12:03:55", "大类": "体育休闲服务", "中类": "娱乐场所", "小类": "KTV|购物服务;服装鞋帽皮具店;服装鞋帽皮具店", "wgs84经ti": 114.337964, "wgs84纬ti": 30.526205}}]}