{"type": "FeatureCollection", "features": [{"type": "Feature", "id": 10622, "geometry": {"type": "Point", "coordinates": [114.38983200044652, 30.498069000284204]}, "properties": {"OBJECTID": 10622, "poiid": "B0FFHJDJHD", "name": "飞歌(雄楚1号购物广场)", "address": "雄楚大道888号雄楚1号购物广场3层", "type": "体育休闲服务;娱乐场所;KTV|购物服务;专卖店;专营店", "typecode": "080302|061200", "pcode": 420000, "pname": "湖北省", "citycode": 27, "cityname": "武汉市", "adcode": 420111, "adname": "洪山区", "business_a": "鲁巷", "location": "114.389832,30.498069", "tel": "027-65699999;4000027566", "fetch_time": "19/1/2025 08:58:40", "大类": "体育休闲服务", "中类": "娱乐场所", "小类": "KTV|购物服务;专卖店;专营店", "wgs84经ti": 114.384291, "wgs84纬ti": 30.50038}}]}