{"type": "FeatureCollection", "features": [{"type": "Feature", "id": 8545, "geometry": {"type": "Point", "coordinates": [114.46139500007928, 30.57763700034735]}, "properties": {"OBJECTID": 8545, "poiid": "B0FFFV2MBP", "name": "休闲文化社", "address": "街二村24栋", "type": "体育休闲服务;娱乐场所;娱乐场所|生活服务;生活服务场所;生活服务场所", "typecode": "080300|070000", "pcode": 420000, "pname": "湖北省", "citycode": 27, "cityname": "武汉市", "adcode": 420107, "adname": "青山区", "business_a": "武东", "location": "114.461395,30.577637", "tel": "027-86437169", "fetch_time": "19/1/2025 22:47:37", "大类": "体育休闲服务", "中类": "娱乐场所", "小类": "娱乐场所|生活服务;生活服务场所;生活服务场所", "wgs84经ti": 114.455963, "wgs84纬ti": 30.579994}}]}