{"type": "FeatureCollection", "features": [{"type": "Feature", "id": 12252, "geometry": {"type": "Point", "coordinates": [114.3207300000895, 30.52372299981664]}, "properties": {"OBJECTID": 12252, "poiid": "B0FFLPF32V", "name": "本源养生茶棋牌", "address": "静安路8-附27附近", "type": "体育休闲服务;娱乐场所;棋牌室|餐饮服务;茶艺馆;茶艺馆|购物服务;购物相关场所;购物相关场所", "typecode": "080306|050600|060000", "pcode": 420000, "pname": "湖北省", "citycode": 27, "cityname": "武汉市", "adcode": 420106, "adname": "武昌区", "business_a": "丁字桥", "location": "114.320730,30.523723", "tel": " ", "fetch_time": "19/1/2025 09:23:29", "大类": "体育休闲服务", "中类": "娱乐场所", "小类": "棋牌室|餐饮服务;茶艺馆;茶艺馆|购物服务;购物相关场所;购物相关场所", "wgs84经ti": 114.315268, "wgs84纬ti": 30.526129}}]}