{"type": "FeatureCollection", "features": [{"type": "Feature", "id": 12823, "geometry": {"type": "Point", "coordinates": [114.37572199997044, 30.8776310003704]}, "properties": {"OBJECTID": 12823, "poiid": "B001B1CB1H", "name": "家春秋棋牌简餐", "address": "锦绣道157号", "type": "体育休闲服务;娱乐场所;棋牌室|生活服务;中介机构;中介机构|餐饮服务;休闲餐饮场所;休闲餐饮场所", "typecode": "080306|071600|050400", "pcode": 420000, "pname": "湖北省", "citycode": 27, "cityname": "武汉市", "adcode": 420116, "adname": "黄陂区", "business_a": "前川", "location": "114.375722,30.877631", "tel": " ", "fetch_time": "19/1/2025 09:19:48", "大类": "体育休闲服务", "中类": "娱乐场所", "小类": "棋牌室|生活服务;中介机构;中介机构|餐饮服务;休闲餐饮场所;休闲餐饮场所", "wgs84经ti": 114.370154, "wgs84纬ti": 30.87978}}]}