{"type": "FeatureCollection", "features": [{"type": "Feature", "id": 4806, "geometry": {"type": "Point", "coordinates": [114.19955100027846, 30.58830200023715]}, "properties": {"OBJECTID": 4806, "poiid": "B0HRFC2FMF", "name": "锦程棋牌咖啡茗茶", "address": "古田路68号之92号-98号", "type": "体育休闲服务;娱乐场所;棋牌室|购物服务;家居建材市场;厨卫市场", "typecode": "080306|060604", "pcode": 420000, "pname": "湖北省", "citycode": 27, "cityname": "武汉市", "adcode": 420104, "adname": "硚口区", "business_a": "古田", "location": "114.199551,30.588302", "tel": "15071471641", "fetch_time": "19/1/2025 20:57:39", "大类": "体育休闲服务", "中类": "娱乐场所", "小类": "棋牌室|购物服务;家居建材市场;厨卫市场", "wgs84经ti": 114.194048, "wgs84纬ti": 30.590723}}]}