{"type": "FeatureCollection", "features": [{"type": "Feature", "id": 1967, "geometry": {"type": "Point", "coordinates": [114.08798500040746, 30.328308000313996]}, "properties": {"OBJECTID": 1967, "poiid": "B0FFMEZMEJ", "name": "嘉丽新棋牌住宿免费", "address": "汉南大道与兴二路交叉口北80米", "type": "体育休闲服务;娱乐场所;棋牌室|住宿服务;住宿服务相关;住宿服务相关", "typecode": "080306|100000", "pcode": 420000, "pname": "湖北省", "citycode": 27, "cityname": "武汉市", "adcode": 420113, "adname": "汉南区", "business_a": " ", "location": "114.087985,30.328308", "tel": " ", "fetch_time": "19/1/2025 21:17:17", "大类": "体育休闲服务", "中类": "娱乐场所", "小类": "棋牌室|住宿服务;住宿服务相关;住宿服务相关", "wgs84经ti": 114.082264, "wgs84纬ti": 30.330658}}]}