{"type": "FeatureCollection", "features": [{"type": "Feature", "id": 16294, "geometry": {"type": "Point", "coordinates": [114.31610399989972, 30.63963400040882]}, "properties": {"OBJECTID": 16294, "poiid": "B0FFH42BAD", "name": "欢乐网吧(建设新村路店)", "address": "建设新村路875号附近", "type": "体育休闲服务;娱乐场所;棋牌室|体育休闲服务;娱乐场所;网吧", "typecode": "080306|080308", "pcode": 420000, "pname": "湖北省", "citycode": 27, "cityname": "武汉市", "adcode": 420102, "adname": "江岸区", "business_a": "后湖", "location": "114.316104,30.639634", "tel": " ", "fetch_time": "19/1/2025 12:03:55", "大类": "体育休闲服务", "中类": "娱乐场所", "小类": "棋牌室|体育休闲服务;娱乐场所;网吧", "wgs84经ti": 114.310639, "wgs84纬ti": 30.642005}}]}