{"type": "FeatureCollection", "features": [{"type": "Feature", "id": 5664, "geometry": {"type": "Point", "coordinates": [114.2555810003629, 30.646833999689363]}, "properties": {"OBJECTID": 5664, "poiid": "B001B16GBT", "name": "好运棋牌(将军一路店)", "address": "将军一路81号", "type": "体育休闲服务;娱乐场所;棋牌室|餐饮服务;休闲餐饮场所;休闲餐饮场所|购物服务;购物相关场所;购物相关场所", "typecode": "080306|050400|060000", "pcode": 420000, "pname": "湖北省", "citycode": 27, "cityname": "武汉市", "adcode": 420112, "adname": "东西湖区", "business_a": " ", "location": "114.255581,30.646834", "tel": "15926466737", "fetch_time": "19/1/2025 21:02:09", "大类": "体育休闲服务", "中类": "娱乐场所", "小类": "棋牌室|餐饮服务;休闲餐饮场所;休闲餐饮场所|购物服务;购物相关场所;购物相关场所", "wgs84经ti": 114.250161, "wgs84纬ti": 30.649274}}, {"type": "Feature", "id": 7519, "geometry": {"type": "Point", "coordinates": [114.25366700023199, 30.62848099959848]}, "properties": {"OBJECTID": 7519, "poiid": "B0FFGDXOCF", "name": "畅和", "address": "汉兴街街道常青五路市委党校斜对面", "type": "体育休闲服务;娱乐场所;棋牌室|餐饮服务;休闲餐饮场所;休闲餐饮场所|购物服务;购物相关场所;购物相关场所", "typecode": "080306|050400|060000", "pcode": 420000, "pname": "湖北省", "citycode": 27, "cityname": "武汉市", "adcode": 420103, "adname": "江汉区", "business_a": "常青", "location": "114.253667,30.628481", "tel": "027-65605173", "fetch_time": "19/1/2025 22:08:51", "大类": "体育休闲服务", "中类": "娱乐场所", "小类": "棋牌室|餐饮服务;休闲餐饮场所;休闲餐饮场所|购物服务;购物相关场所;购物相关场所", "wgs84经ti": 114.248248, "wgs84纬ti": 30.630929}}]}