{"type": "FeatureCollection", "features": [{"type": "Feature", "id": 14859, "geometry": {"type": "Point", "coordinates": [114.37133199987193, 30.873738999854993]}, "properties": {"OBJECTID": 14859, "poiid": "B0FFFFMVEE", "name": "伊人居网吧(西寺大道)", "address": "前川街西寺大道1号", "type": "体育休闲服务;娱乐场所;网吧|购物服务;服装鞋帽皮具店;服装鞋帽皮具店", "typecode": "080308|061100", "pcode": 420000, "pname": "湖北省", "citycode": 27, "cityname": "武汉市", "adcode": 420116, "adname": "黄陂区", "business_a": "前川", "location": "114.371332,30.873739", "tel": " ", "fetch_time": "19/1/2025 12:03:55", "大类": "体育休闲服务", "中类": "娱乐场所", "小类": "网吧|购物服务;服装鞋帽皮具店;服装鞋帽皮具店", "wgs84经ti": 114.365768, "wgs84纬ti": 30.875895}}]}