{"type": "FeatureCollection", "features": [{"type": "Feature", "id": 108, "geometry": {"type": "Point", "coordinates": [114.57731600023328, 30.674915999673715]}, "properties": {"OBJECTID": 108, "poiid": "B0FFGCI4GV", "name": "谜团网咖", "address": "阳逻街高潮村新城世家第1幢1单元1-2层1号", "type": "体育休闲服务;娱乐场所;网吧|餐饮服务;咖啡厅;咖啡厅", "typecode": "080308|050500", "pcode": 420000, "pname": "湖北省", "citycode": 27, "cityname": "武汉市", "adcode": 420117, "adname": "新洲区", "business_a": "阳逻", "location": "114.577316,30.674916", "tel": "18986024878;027-89505018", "fetch_time": "19/1/2025 20:56:14", "大类": "体育休闲服务", "中类": "娱乐场所", "小类": "网吧|餐饮服务;咖啡厅;咖啡厅", "wgs84经ti": 114.572239, "wgs84纬ti": 30.677515}}, {"type": "Feature", "id": 22112, "geometry": {"type": "Point", "coordinates": [114.57731600023328, 30.674915999673715]}, "properties": {"OBJECTID": 22112, "poiid": "B0FFGCI4GV", "name": "谜团网咖", "address": "阳逻街高潮村新城世家第1幢1单元1-2层1号", "type": "体育休闲服务;娱乐场所;网吧|餐饮服务;咖啡厅;咖啡厅", "typecode": "080308|050500", "pcode": 420000, "pname": "湖北省", "citycode": 27, "cityname": "武汉市", "adcode": 420117, "adname": "新洲区", "business_a": "阳逻", "location": "114.577316,30.674916", "tel": "027-89505018;18986024878", "fetch_time": "19/1/2025 06:56:11", "大类": "体育休闲服务", "中类": "娱乐场所", "小类": "网吧|餐饮服务;咖啡厅;咖啡厅", "wgs84经ti": 114.572239, "wgs84纬ti": 30.677515}}]}