{"type": "FeatureCollection", "features": [{"type": "Feature", "id": 9451, "geometry": {"type": "Point", "coordinates": [114.4088509997739, 30.459693999578462]}, "properties": {"OBJECTID": 9451, "poiid": "B0FFFGLTI4", "name": "吉普餐厅酒吧", "address": "第五大道万科城市花园", "type": "体育休闲服务;娱乐场所;酒吧|餐饮服务;中餐厅;中餐厅|餐饮服务;休闲餐饮场所;休闲餐饮场所", "typecode": "080304|050100|050400", "pcode": 420000, "pname": "湖北省", "citycode": 27, "cityname": "武汉市", "adcode": 420115, "adname": "江夏区", "business_a": " ", "location": "114.408851,30.459694", "tel": "027-81691066", "fetch_time": "19/1/2025 23:34:49", "大类": "体育休闲服务", "中类": "娱乐场所", "小类": "酒吧|餐饮服务;中餐厅;中餐厅|餐饮服务;休闲餐饮场所;休闲餐饮场所", "wgs84经ti": 114.40332, "wgs84纬ti": 30.462013}}, {"type": "Feature", "id": 21889, "geometry": {"type": "Point", "coordinates": [114.4088650004195, 30.45967999983219]}, "properties": {"OBJECTID": 21889, "poiid": "B0FFFGLTI4", "name": "吉普餐厅酒吧", "address": "梦幻岛正门西100米", "type": "体育休闲服务;娱乐场所;酒吧|餐饮服务;中餐厅;中餐厅|餐饮服务;休闲餐饮场所;休闲餐饮场所", "typecode": "080304|050100|050400", "pcode": 420000, "pname": "湖北省", "citycode": 27, "cityname": "武汉市", "adcode": 420115, "adname": "江夏区", "business_a": " ", "location": "114.408865,30.459680", "tel": " ", "fetch_time": "19/1/2025 06:40:27", "大类": "体育休闲服务", "中类": "娱乐场所", "小类": "酒吧|餐饮服务;中餐厅;中餐厅|餐饮服务;休闲餐饮场所;休闲餐饮场所", "wgs84经ti": 114.403334, "wgs84纬ti": 30.461999}}]}