{"type": "FeatureCollection", "features": [{"type": "Feature", "id": 1496, "geometry": {"type": "Point", "coordinates": [114.04361500023208, 30.47418000030683]}, "properties": {"OBJECTID": 1496, "poiid": "B0FFL0ZGLR", "name": "江淮德沃斯中卡（武汉灿晖汽车销售服务有限公司）", "address": "花园湾一街与九康大道交叉路口往南约80米", "type": "汽车销售;江淮销售;江淮销售", "typecode": "022800", "pcode": 420000, "pname": "湖北省", "citycode": 27, "cityname": "武汉市", "adcode": 420114, "adname": "蔡甸区", "business_a": " ", "location": "114.043615,30.474180", "tel": "18062585882", "fetch_time": "19/1/2025 21:12:29", "大类": "汽车销售", "中类": "江淮销售", "小类": "江淮销售", "wgs84经ti": 114.037919, "wgs84纬ti": 30.476564}}, {"type": "Feature", "id": 1497, "geometry": {"type": "Point", "coordinates": [114.29998700039982, 30.661843000254294]}, "properties": {"OBJECTID": 1497, "poiid": "B001B16H2M", "name": "江淮骏铃(竹叶山店)", "address": "金桥大道特1号竹叶山中环商贸城C31-15-17号", "type": "汽车销售;江淮销售;江淮销售", "typecode": "022800", "pcode": 420000, "pname": "湖北省", "citycode": 27, "cityname": "武汉市", "adcode": 420102, "adname": "江岸区", "business_a": "后湖", "location": "114.299987,30.661843", "tel": " ", "fetch_time": "19/1/2025 21:12:29", "大类": "汽车销售", "中类": "江淮销售", "小类": "江淮销售", "wgs84经ti": 114.294543, "wgs84纬ti": 30.664233}}, {"type": "Feature", "id": 2866, "geometry": {"type": "Point", "coordinates": [114.1984980002826, 30.548702999743682]}, "properties": {"OBJECTID": 2866, "poiid": "B0KAXSCFMZ", "name": "江淮钇为", "address": "隆祥街11号", "type": "汽车销售;江淮销售;江淮销售", "typecode": "022800", "pcode": 420000, "pname": "湖北省", "citycode": 27, "cityname": "武汉市", "adcode": 420105, "adname": "汉阳区", "business_a": "王家湾", "location": "114.198498,30.548703", "tel": "17798209390", "fetch_time": "19/1/2025 04:36:55", "大类": "汽车销售", "中类": "江淮销售", "小类": "江淮销售", "wgs84经ti": 114.192996, "wgs84纬ti": 30.551137}}, {"type": "Feature", "id": 4052, "geometry": {"type": "Point", "coordinates": [114.04361500023208, 30.47418000030683]}, "properties": {"OBJECTID": 4052, "poiid": "B0FFL0ZGLR", "name": "江淮德沃斯中卡(武汉灿晖汽车销售服务有限公司)", "address": "花园湾一街与九康大道交叉口西南120米", "type": "汽车销售;江淮销售;江淮销售", "typecode": "022800", "pcode": 420000, "pname": "湖北省", "citycode": 27, "cityname": "武汉市", "adcode": 420114, "adname": "蔡甸区", "business_a": " ", "location": "114.043615,30.474180", "tel": "18062585882", "fetch_time": "19/1/2025 06:27:15", "大类": "汽车销售", "中类": "江淮销售", "小类": "江淮销售", "wgs84经ti": 114.037919, "wgs84纬ti": 30.476564}}]}