{"type": "FeatureCollection", "features": [{"type": "Feature", "id": 1030, "geometry": {"type": "Point", "coordinates": [114.33799600041516, 30.47135400038684]}, "properties": {"OBJECTID": 1030, "poiid": "B0G3Z1UAP1", "name": "雪佛兰", "address": "狮子山街华中农业大学西门1-1-4号", "type": "汽车销售;通用特约销售;雪佛兰销售|汽车维修;汽车维修;汽车维修", "typecode": "020403|030000", "pcode": 420000, "pname": "湖北省", "citycode": 27, "cityname": "武汉市", "adcode": 420111, "adname": "洪山区", "business_a": " ", "location": "114.337996,30.471354", "tel": "027-87665999", "fetch_time": "19/1/2025 20:44:44", "大类": "汽车销售", "中类": "通用特约销售", "小类": "雪佛兰销售|汽车维修;汽车维修;汽车维修", "wgs84经ti": 114.332511, "wgs84纬ti": 30.473743}}, {"type": "Feature", "id": 3759, "geometry": {"type": "Point", "coordinates": [114.33842799965248, 30.471315000386994]}, "properties": {"OBJECTID": 3759, "poiid": "B0G3Z1UAP1", "name": "武汉恒信天安汽车销售服务有限公司", "address": "珞狮南路狮子山街华中农业大学西门1-1-6号野芷湖大桥旁", "type": "汽车销售;通用特约销售;雪佛兰销售|汽车维修;汽车维修;汽车维修", "typecode": "020403|030000", "pcode": 420000, "pname": "湖北省", "citycode": 27, "cityname": "武汉市", "adcode": 420111, "adname": "洪山区", "business_a": " ", "location": "114.338428,30.471315", "tel": "027-87665999;027-87676907", "fetch_time": "19/1/2025 07:04:25", "大类": "汽车销售", "中类": "通用特约销售", "小类": "雪佛兰销售|汽车维修;汽车维修;汽车维修", "wgs84经ti": 114.332942, "wgs84纬ti": 30.473703}}]}