{"type": "FeatureCollection", "features": [{"type": "Feature", "id": 1559, "geometry": {"type": "Point", "coordinates": [114.30048099979831, 30.662319999768215]}, "properties": {"OBJECTID": 1559, "poiid": "B0FFHLZRD7", "name": "SAIC MOTOR", "address": "中环一路与车二街交叉口东50米", "type": "汽车销售;名爵销售;名爵销售", "typecode": "022700", "pcode": 420000, "pname": "湖北省", "citycode": 27, "cityname": "武汉市", "adcode": 420102, "adname": "江岸区", "business_a": "后湖", "location": "114.300481,30.662320", "tel": " ", "fetch_time": "19/1/2025 21:06:56", "大类": "汽车销售", "中类": "名爵销售", "小类": "名爵销售", "wgs84经ti": 114.295037, "wgs84纬ti": 30.664709}}]}