{"type": "FeatureCollection", "features": [{"type": "Feature", "id": 48497, "geometry": {"type": "Point", "coordinates": [114.29232999982969, 30.57087699977376]}, "properties": {"OBJECTID": 48497, "poiid": "B0FFFFWRQA", "name": "三镇烘焙·制冷", "address": "民权路20号", "type": "餐饮服务;糕饼店;糕饼店|购物服务;专卖店;专营店", "typecode": "050800|061200", "pcode": 420000, "pname": "湖北省", "citycode": 27, "cityname": "武汉市", "adcode": 420103, "adname": "江汉区", "business_a": "民族", "location": "114.292330,30.570877", "tel": "18986247373;18986227373", "fetch_time": "19/1/2025 09:00:55", "大类": "餐饮服务", "中类": "糕饼店", "小类": "糕饼店|购物服务;专卖店;专营店", "wgs84经ti": 114.286903, "wgs84纬ti": 30.573316}}]}