{"type": "FeatureCollection", "features": [{"type": "Feature", "id": 1643, "geometry": {"type": "Point", "coordinates": [114.35224600015283, 30.522274999591616]}, "properties": {"OBJECTID": 1643, "poiid": "B0FFGCE8L4", "name": "湖北省高等学校毕业生就业指导服务中心", "address": "珞狮路122号", "type": "科教文化服务;学校;高等院校|政府机构及社会团体;政府机关;省直辖市级政府及事业单位", "typecode": "141201|130102", "pcode": 420000, "pname": "湖北省", "citycode": 27, "cityname": "武汉市", "adcode": 420111, "adname": "洪山区", "business_a": "珞南", "location": "114.352246,30.522275", "tel": "4009027110", "fetch_time": "19/1/2025 20:57:32", "大类": "科教文化服务", "中类": "学校", "小类": "高等院校|政府机构及社会团体;政府机关;省直辖市级政府及事业单位", "wgs84经ti": 114.346735, "wgs84纬ti": 30.524623}}]}