{"type": "FeatureCollection", "features": [{"type": "Feature", "id": 5881, "geometry": {"type": "Point", "coordinates": [114.2997850000778, 30.53807999999208]}, "properties": {"OBJECTID": 5881, "poiid": "B0FFF67JSC", "name": "读书院", "address": "黄鹤楼街办事处", "type": "商务住宅;住宅区;住宅小区|科教文化服务;科教文化场所;科教文化场所", "typecode": "120302|140000", "pcode": 420000, "pname": "湖北省", "citycode": 27, "cityname": "武汉市", "adcode": 420106, "adname": "武昌区", "business_a": "江滩", "location": "114.299785,30.538080", "tel": " ", "fetch_time": "19/1/2025 21:24:47", "大类": "商务住宅", "中类": "住宅区", "小类": "住宅小区|科教文化服务;科教文化场所;科教文化场所", "wgs84经ti": 114.294352, "wgs84纬ti": 30.540519}}]}