{"type": "FeatureCollection", "features": [{"type": "Feature", "id": 7385, "geometry": {"type": "Point", "coordinates": [114.32376299966279, 30.354473000028975]}, "properties": {"OBJECTID": 7385, "poiid": "B0FFGIGRW1", "name": "江夏碧舫", "address": "纸坊街文化路综合楼1-2层5号(水产局小区南)", "type": "商务住宅;住宅区;住宅小区|购物服务;专卖店;专营店", "typecode": "120302|061200", "pcode": 420000, "pname": "湖北省", "citycode": 27, "cityname": "武汉市", "adcode": 420115, "adname": "江夏区", "business_a": "纸坊", "location": "114.323763,30.354473", "tel": "027-81815988;027-81819588", "fetch_time": "19/1/2025 21:35:19", "大类": "商务住宅", "中类": "住宅区", "小类": "住宅小区|购物服务;专卖店;专营店", "wgs84经ti": 114.318311, "wgs84纬ti": 30.356913}}]}