{"type": "FeatureCollection", "features": [{"type": "Feature", "id": 4399, "geometry": {"type": "Point", "coordinates": [114.55761700012454, 30.45954800004023]}, "properties": {"OBJECTID": 4399, "poiid": "B0FFIEKDDF", "name": "九龙湖社区", "address": "新兴路临27号附近", "type": "商务住宅;住宅区;住宅小区|商务住宅;住宅区;社区中心", "typecode": "120302|120304", "pcode": 420000, "pname": "湖北省", "citycode": 27, "cityname": "武汉市", "adcode": 420115, "adname": "江夏区", "business_a": " ", "location": "114.557617,30.459548", "tel": " ", "fetch_time": "19/1/2025 20:36:56", "大类": "商务住宅", "中类": "住宅区", "小类": "住宅小区|商务住宅;住宅区;社区中心", "wgs84经ti": 114.552522, "wgs84纬ti": 30.462198}}]}