{"type": "FeatureCollection", "features": [{"type": "Feature", "id": 17192, "geometry": {"type": "Point", "coordinates": [114.35749000006354, 30.522996999611905]}, "properties": {"OBJECTID": 17192, "poiid": "B0FFF3UR30", "name": "云英阁", "address": "桂元路76-10号附近", "type": "商务住宅;住宅区;宿舍|科教文化服务;科教文化场所;科教文化场所", "typecode": "120303|140000", "pcode": 420000, "pname": "湖北省", "citycode": 27, "cityname": "武汉市", "adcode": 420111, "adname": "洪山区", "business_a": "陈家湾", "location": "114.357490,30.522997", "tel": " ", "fetch_time": "19/1/2025 12:03:55", "大类": "商务住宅", "中类": "住宅区", "小类": "宿舍|科教文化服务;科教文化场所;科教文化场所", "wgs84经ti": 114.351971, "wgs84纬ti": 30.525336}}]}