{"type": "FeatureCollection", "features": [{"type": "Feature", "id": 639, "geometry": {"type": "Point", "coordinates": [114.25821899970708, 30.41873900040457]}, "properties": {"OBJECTID": 639, "poiid": "B0G3CA520K", "name": "TOYOTA", "address": " ", "type": "汽车销售;丰田特约销售;丰田销售|汽车销售;日产特约销售;日产销售", "typecode": "021000|020700", "pcode": 420000, "pname": "湖北省", "citycode": 27, "cityname": "武汉市", "adcode": 420111, "adname": "洪山区", "business_a": " ", "location": "114.258219,30.418739", "tel": " ", "fetch_time": "19/1/2025 21:03:55", "大类": "汽车销售", "中类": "丰田特约销售", "小类": "丰田销售|汽车销售;日产特约销售;日产销售", "wgs84经ti": 114.25282, "wgs84纬ti": 30.421253}}]}