{"type": "FeatureCollection", "features": [{"type": "Feature", "id": 30163, "geometry": {"type": "Point", "coordinates": [114.21316699955742, 30.515001999642607]}, "properties": {"OBJECTID": 30163, "poiid": "B0FFHMVF7B", "name": "尊宝比萨(汉阳四新店)", "address": "绿地新都会8栋1-2层9号", "type": "餐饮服务;快餐厅;快餐厅|餐饮服务;休闲餐饮场所;休闲餐饮场所", "typecode": "050300|050400", "pcode": 420000, "pname": "湖北省", "citycode": 27, "cityname": "武汉市", "adcode": 420105, "adname": "汉阳区", "business_a": " ", "location": "114.213167,30.515002", "tel": "027-84668917;027-84668916", "fetch_time": "19/1/2025 22:03:36", "大类": "餐饮服务", "中类": "快餐厅", "小类": "快餐厅|餐饮服务;休闲餐饮场所;休闲餐饮场所", "wgs84经ti": 114.207703, "wgs84纬ti": 30.517468}}, {"type": "Feature", "id": 51237, "geometry": {"type": "Point", "coordinates": [114.58202499975403, 30.881641000032175]}, "properties": {"OBJECTID": 51237, "poiid": "B0FFIRZDU5", "name": "此食", "address": "红业超市对面", "type": "餐饮服务;快餐厅;快餐厅|餐饮服务;休闲餐饮场所;休闲餐饮场所", "typecode": "050300|050400", "pcode": 420000, "pname": "湖北省", "citycode": 27, "cityname": "武汉市", "adcode": 420116, "adname": "黄陂区", "business_a": " ", "location": "114.582025,30.881641", "tel": " ", "fetch_time": "19/1/2025 09:19:48", "大类": "餐饮服务", "中类": "快餐厅", "小类": "快餐厅|餐饮服务;休闲餐饮场所;休闲餐饮场所", "wgs84经ti": 114.576936, "wgs84纬ti": 30.884135}}]}