{"type": "FeatureCollection", "features": [{"type": "Feature", "id": 3759, "geometry": {"type": "Point", "coordinates": [114.26978899996243, 30.61039199999084]}, "properties": {"OBJECTID": 3759, "poiid": "B0FFF38BYV", "name": "肯德基(菱角湖餐厅)", "address": "唐家墩路5号菱角湖万达广场一楼", "type": "餐饮服务;快餐厅;肯德基|餐饮服务;甜品店;甜品店", "typecode": "050301|050900", "pcode": 420000, "pname": "湖北省", "citycode": 27, "cityname": "武汉市", "adcode": 420103, "adname": "江汉区", "business_a": "新华", "location": "114.269789,30.610392", "tel": "4009208801;027-85580631;027-85748732", "fetch_time": "19/1/2025 21:05:28", "大类": "餐饮服务", "中类": "快餐厅", "小类": "肯德基|餐饮服务;甜品店;甜品店", "wgs84经ti": 114.264373, "wgs84纬ti": 30.61284}}]}