{"type": "FeatureCollection", "features": [{"type": "Feature", "id": 2238, "geometry": {"type": "Point", "coordinates": [114.18203400006917, 30.496977000288382]}, "properties": {"OBJECTID": 2238, "poiid": "B0FFLGQHUA", "name": "东风", "address": "车城东路7号", "type": "汽车销售;标致雪铁龙特约销售;东风雪铁龙销售|汽车销售;东风特约销售;东风销售", "typecode": "021201|022200", "pcode": 420000, "pname": "湖北省", "citycode": 27, "cityname": "武汉市", "adcode": 420114, "adname": "蔡甸区", "business_a": "沌口", "location": "114.182034,30.496977", "tel": " ", "fetch_time": "19/1/2025 12:03:55", "大类": "汽车销售", "中类": "标致雪铁龙特约销售", "小类": "东风雪铁龙销售|汽车销售;东风特约销售;东风销售", "wgs84经ti": 114.176491, "wgs84纬ti": 30.499398}}]}