{"type": "FeatureCollection", "features": [{"type": "Feature", "id": 780, "geometry": {"type": "Point", "coordinates": [114.20283999996605, 30.547959999654324]}, "properties": {"OBJECTID": 780, "poiid": "B0I67RQ8SV", "name": "东风卓联武汉汉阳汽车服务有限公司", "address": "陶家岭特18号", "type": "汽车销售;标致雪铁龙特约销售;东风雪铁龙销售|汽车服务;汽车服务相关;汽车服务相关", "typecode": "021201|010000", "pcode": 420000, "pname": "湖北省", "citycode": 27, "cityname": "武汉市", "adcode": 420105, "adname": "汉阳区", "business_a": "王家湾", "location": "114.202840,30.547960", "tel": " ", "fetch_time": "19/1/2025 21:22:41", "大类": "汽车销售", "中类": "标致雪铁龙特约销售", "小类": "东风雪铁龙销售|汽车服务;汽车服务相关;汽车服务相关", "wgs84经ti": 114.197349, "wgs84纬ti": 30.550401}}]}