{"type": "FeatureCollection", "features": [{"type": "Feature", "id": 40759, "geometry": {"type": "Point", "coordinates": [114.32053600013637, 30.347774999616604]}, "properties": {"OBJECTID": 40759, "poiid": "B001B16OUC", "name": "伊莎贝尔(古驿道店)", "address": "纸坊街古驿道5号", "type": "生活服务;摄影冲印店;摄影冲印|餐饮服务;糕饼店;糕饼店", "typecode": "071300|050800", "pcode": 420000, "pname": "湖北省", "citycode": 27, "cityname": "武汉市", "adcode": 420115, "adname": "江夏区", "business_a": "纸坊", "location": "114.320536,30.347775", "tel": "18571846320;027-87919019", "fetch_time": "19/1/2025 22:54:11", "大类": "生活服务", "中类": "摄影冲印店", "小类": "摄影冲印|餐饮服务;糕饼店;糕饼店", "wgs84经ti": 114.31509, "wgs84纬ti": 30.350222}}]}