{"type": "FeatureCollection", "features": [{"type": "Feature", "id": 1511, "geometry": {"type": "Point", "coordinates": [114.25423700043723, 30.577153999657412]}, "properties": {"OBJECTID": 1511, "poiid": "B0FFG0Z8JE", "name": "武汉中升聚星汽车销售服务有限公司硚口分公司", "address": "解放大道586号中御广场1层1-2号", "type": "汽车销售;梅赛德斯-奔驰特约销售;梅赛德斯-奔驰销售|汽车维修;梅赛德斯-奔驰卡车维修;梅赛德斯-奔驰卡车维修", "typecode": "020000|036000", "pcode": 420000, "pname": "湖北省", "citycode": 27, "cityname": "武汉市", "adcode": 420104, "adname": "硚口区", "business_a": "崇仁", "location": "114.254237,30.577154", "tel": "027-83359999;4008181188", "fetch_time": "19/1/2025 21:17:48", "大类": "汽车销售", "中类": "梅赛德斯-奔驰特约销售", "小类": "梅赛德斯-奔驰销售|汽车维修;梅赛德斯-奔驰卡车维修;梅赛德斯-奔驰卡车维修", "wgs84经ti": 114.248823, "wgs84纬ti": 30.579623}}, {"type": "Feature", "id": 3326, "geometry": {"type": "Point", "coordinates": [114.25423200020668, 30.57715199956516]}, "properties": {"OBJECTID": 3326, "poiid": "B0FFG0Z8JE", "name": "武汉中升聚星汽车销售服务有限公司硚口分公司", "address": "解放大道578号中御广场1层1-2号", "type": "汽车销售;梅赛德斯-奔驰特约销售;梅赛德斯-奔驰销售|汽车维修;梅赛德斯-奔驰卡车维修;梅赛德斯-奔驰卡车维修", "typecode": "020900|036000", "pcode": 420000, "pname": "湖北省", "citycode": 27, "cityname": "武汉市", "adcode": 420104, "adname": "硚口区", "business_a": "崇仁", "location": "114.254232,30.577152", "tel": "027-83359999;4008181188", "fetch_time": "19/1/2025 06:31:07", "大类": "汽车销售", "中类": "梅赛德斯-奔驰特约销售", "小类": "梅赛德斯-奔驰销售|汽车维修;梅赛德斯-奔驰卡车维修;梅赛德斯-奔驰卡车维修", "wgs84经ti": 114.248818, "wgs84纬ti": 30.579621}}]}