{"type": "FeatureCollection", "features": [{"type": "Feature", "id": 1081, "geometry": {"type": "Point", "coordinates": [114.4119630002923, 30.609734000223966]}, "properties": {"OBJECTID": 1081, "poiid": "B0G077535Q", "name": "武汉腾星汽车销售服务有限公司", "address": "团结大道1919号工业四路地铁C出口前行20米奔驰4S店", "type": "汽车销售;梅赛德斯-奔驰特约销售;梅赛德斯-奔驰销售|汽车维修;汽车维修;汽车维修", "typecode": "020900|030000", "pcode": 420000, "pname": "湖北省", "citycode": 27, "cityname": "武汉市", "adcode": 420111, "adname": "洪山区", "business_a": "冶金", "location": "114.411963,30.609734", "tel": "027-86687666", "fetch_time": "19/1/2025 21:00:26", "大类": "汽车销售", "中类": "梅赛德斯-奔驰特约销售", "小类": "梅赛德斯-奔驰销售|汽车维修;汽车维修;汽车维修", "wgs84经ti": 114.406422, "wgs84纬ti": 30.612005}}, {"type": "Feature", "id": 1189, "geometry": {"type": "Point", "coordinates": [114.43045200035954, 30.429781999739532]}, "properties": {"OBJECTID": 1189, "poiid": "B0G1LD5OU9", "name": "武汉中升之星汽车销售服务有限公司", "address": "藏龙岛凤凰大道16号奔驰4S店", "type": "汽车销售;梅赛德斯-奔驰特约销售;梅赛德斯-奔驰销售|汽车维修;汽车维修;汽车维修", "typecode": "020900|030000", "pcode": 420000, "pname": "湖北省", "citycode": 27, "cityname": "武汉市", "adcode": 420115, "adname": "江夏区", "business_a": "藏龙岛", "location": "114.430452,30.429782", "tel": "027-81935888;027-86696950", "fetch_time": "19/1/2025 21:13:15", "大类": "汽车销售", "中类": "梅赛德斯-奔驰特约销售", "小类": "梅赛德斯-奔驰销售|汽车维修;汽车维修;汽车维修", "wgs84经ti": 114.424953, "wgs84纬ti": 30.432125}}, {"type": "Feature", "id": 1505, "geometry": {"type": "Point", "coordinates": [114.23965499977851, 30.62353399989422]}, "properties": {"OBJECTID": 1505, "poiid": "B0FFGS4VA3", "name": "星威奔驰会馆", "address": "江汉经济开发区", "type": "汽车销售;梅赛德斯-奔驰特约销售;梅赛德斯-奔驰销售|汽车维修;汽车维修;汽车维修", "typecode": "020000|030000", "pcode": 420000, "pname": "湖北省", "citycode": 27, "cityname": "武汉市", "adcode": 420103, "adname": "江汉区", "business_a": "常青", "location": "114.239655,30.623534", "tel": " ", "fetch_time": "19/1/2025 21:17:26", "大类": "汽车销售", "中类": "梅赛德斯-奔驰特约销售", "小类": "梅赛德斯-奔驰销售|汽车维修;汽车维修;汽车维修", "wgs84经ti": 114.234225, "wgs84纬ti": 30.625983}}, {"type": "Feature", "id": 3268, "geometry": {"type": "Point", "coordinates": [114.23965499977851, 30.62353399989422]}, "properties": {"OBJECTID": 3268, "poiid": "B0FFGS4VA3", "name": "星威奔驰会馆", "address": "江汉经济开发区", "type": "汽车销售;梅赛德斯-奔驰特约销售;梅赛德斯-奔驰销售|汽车维修;汽车维修;汽车维修", "typecode": "020000|030000", "pcode": 420000, "pname": "湖北省", "citycode": 27, "cityname": "武汉市", "adcode": 420103, "adname": "江汉区", "business_a": "常青", "location": "114.239655,30.623534", "tel": " ", "fetch_time": "19/1/2025 06:22:27", "大类": "汽车销售", "中类": "梅赛德斯-奔驰特约销售", "小类": "梅赛德斯-奔驰销售|汽车维修;汽车维修;汽车维修", "wgs84经ti": 114.234225, "wgs84纬ti": 30.625983}}]}