{"type": "FeatureCollection", "features": [{"type": "Feature", "id": 102032, "geometry": {"type": "Point", "coordinates": [114.14352200024018, 30.62001100020757]}, "properties": {"OBJECTID": 102032, "poiid": "B001B16LA2", "name": "瑞星莱财务", "address": "四明路32号", "type": "生活服务;事务所;会计师事务所|金融保险服务;财务公司;财务公司", "typecode": "070702|160600", "pcode": 420000, "pname": "湖北省", "citycode": 27, "cityname": "武汉市", "adcode": 420112, "adname": "东西湖区", "business_a": "吴家山", "location": "114.143522,30.620011", "tel": "027-83215225", "fetch_time": "19/1/2025 04:51:43", "大类": "生活服务", "中类": "事务所", "小类": "会计师事务所|金融保险服务;财务公司;财务公司", "wgs84经ti": 114.13786, "wgs84纬ti": 30.62232}}]}