{"type": "FeatureCollection", "features": [{"type": "Feature", "id": 5622, "geometry": {"type": "Point", "coordinates": [114.34426299983761, 30.5583949997295]}, "properties": {"OBJECTID": 5622, "poiid": "B0FFLPIH23", "name": "武汉中央文化区", "address": "水果湖街办事处", "type": "商务住宅;商务住宅相关;商务住宅相关|科教文化服务;科教文化场所;科教文化场所", "typecode": "120000|140000", "pcode": 420000, "pname": "湖北省", "citycode": 27, "cityname": "武汉市", "adcode": 420106, "adname": "武昌区", "business_a": "中北路", "location": "114.344263,30.558395", "tel": " ", "fetch_time": "19/1/2025 21:24:40", "大类": "商务住宅", "中类": "商务住宅相关", "小类": "商务住宅相关|科教文化服务;科教文化场所;科教文化场所", "wgs84经ti": 114.33876, "wgs84纬ti": 30.560745}}]}