{"type": "FeatureCollection", "features": [{"type": "Feature", "id": 183, "geometry": {"type": "Point", "coordinates": [114.36560200003237, 30.87443799971396]}, "properties": {"OBJECTID": 183, "poiid": "B0GRDUIJW2", "name": "黄陂区宏达名车汽车维修中心", "address": "西寺大道与金堂街交叉口西北80米", "type": "汽车维修;大众特约维修;一汽-大众维修", "typecode": "030202", "pcode": 420000, "pname": "湖北省", "citycode": 27, "cityname": "武汉市", "adcode": 420116, "adname": "黄陂区", "business_a": "前川", "location": "114.365602,30.874438", "tel": " ", "fetch_time": "19/1/2025 20:54:03", "大类": "汽车维修", "中类": "大众特约维修", "小类": "一汽-大众维修", "wgs84经ti": 114.360043, "wgs84纬ti": 30.876601}}, {"type": "Feature", "id": 6883, "geometry": {"type": "Point", "coordinates": [114.36560200003237, 30.87443799971396]}, "properties": {"OBJECTID": 6883, "poiid": "B0GRDUIJW2", "name": "黄陂区宏达名车汽车维修中心", "address": "西寺大道与金堂街交叉口西北80米", "type": "汽车维修;大众特约维修;一汽-大众维修", "typecode": "030202", "pcode": 420000, "pname": "湖北省", "citycode": 27, "cityname": "武汉市", "adcode": 420116, "adname": "黄陂区", "business_a": "前川", "location": "114.365602,30.874438", "tel": " ", "fetch_time": "19/1/2025 06:44:40", "大类": "汽车维修", "中类": "大众特约维修", "小类": "一汽-大众维修", "wgs84经ti": 114.360043, "wgs84纬ti": 30.876601}}]}