{"type": "FeatureCollection", "features": [{"type": "Feature", "id": 855, "geometry": {"type": "Point", "coordinates": [114.20487899956629, 30.549279000225738]}, "properties": {"OBJECTID": 855, "poiid": "B0FFLINL3Z", "name": "北京汽车(汉阳贤良店)", "address": "龙阳大道61号", "type": "汽车销售;北京汽车销售;北京汽车销售|汽车维修;汽车维修;汽车维修", "typecode": "023200|030000", "pcode": 420000, "pname": "湖北省", "citycode": 27, "cityname": "武汉市", "adcode": 420105, "adname": "汉阳区", "business_a": "王家湾", "location": "114.204879,30.549279", "tel": " ", "fetch_time": "19/1/2025 21:24:03", "大类": "汽车销售", "中类": "北京汽车销售", "小类": "北京汽车销售|汽车维修;汽车维修;汽车维修", "wgs84经ti": 114.199393, "wgs84纬ti": 30.551722}}, {"type": "Feature", "id": 3529, "geometry": {"type": "Point", "coordinates": [114.20490199972755, 30.549297000156457]}, "properties": {"OBJECTID": 3529, "poiid": "B0FFLINL3Z", "name": "北京汽车(汉阳贤良店)", "address": "龙阳大道61号(龙阳村地铁站A口步行350米)", "type": "汽车销售;北京汽车销售;北京汽车销售|汽车维修;汽车维修;汽车维修", "typecode": "023200|030000", "pcode": 420000, "pname": "湖北省", "citycode": 27, "cityname": "武汉市", "adcode": 420105, "adname": "汉阳区", "business_a": "王家湾", "location": "114.204902,30.549297", "tel": "13871024291", "fetch_time": "19/1/2025 06:39:45", "大类": "汽车销售", "中类": "北京汽车销售", "小类": "北京汽车销售|汽车维修;汽车维修;汽车维修", "wgs84经ti": 114.199416, "wgs84纬ti": 30.55174}}]}