{"type": "FeatureCollection", "features": [{"type": "Feature", "id": 98564, "geometry": {"type": "Point", "coordinates": [114.32407499966155, 30.350947000203973]}, "properties": {"OBJECTID": 98564, "poiid": "B0G0775D8L", "name": "盈聚鑫江夏分公司", "address": "文化大道公路小区", "type": "购物服务;特殊买卖场所;典当行|公司企业;公司;公司|金融保险服务;金融保险服务机构;金融保险机构", "typecode": "061302|170200|160000", "pcode": 420000, "pname": "湖北省", "citycode": 27, "cityname": "武汉市", "adcode": 420115, "adname": "江夏区", "business_a": "纸坊", "location": "114.324075,30.350947", "tel": "18627897879", "fetch_time": "19/1/2025 12:03:55", "大类": "购物服务", "中类": "特殊买卖场所", "小类": "典当行|公司企业;公司;公司|金融保险服务;金融保险服务机构;金融保险机构", "wgs84经ti": 114.318623, "wgs84纬ti": 30.353387}}]}