{"type": "FeatureCollection", "features": [{"type": "Feature", "id": 2095, "geometry": {"type": "Point", "coordinates": [114.21394600040765, 30.513350999948727]}, "properties": {"OBJECTID": 2095, "poiid": "B0FFK9HNG8", "name": "诚誉寄售公司(四新店)", "address": "四新地区管委会四新南路金地澜菲溪岸E15-102商铺", "type": "购物服务;特殊买卖场所;特殊买卖场所|公司企业;公司;公司", "typecode": "061300|170200", "pcode": 420000, "pname": "湖北省", "citycode": 27, "cityname": "武汉市", "adcode": 420105, "adname": "汉阳区", "business_a": " ", "location": "114.213946,30.513351", "tel": "027-84669997;13657299440", "fetch_time": "19/1/2025 21:03:33", "大类": "购物服务", "中类": "特殊买卖场所", "小类": "特殊买卖场所|公司企业;公司;公司", "wgs84经ti": 114.208483, "wgs84纬ti": 30.515819}}, {"type": "Feature", "id": 120973, "geometry": {"type": "Point", "coordinates": [114.2139309997159, 30.515344000125538]}, "properties": {"OBJECTID": 120973, "poiid": "B0FFK6NF2R", "name": "鑫宏泽寄售公司", "address": "四新地区管委会四新大道梅林五街和昌都汇华府368", "type": "购物服务;特殊买卖场所;特殊买卖场所|公司企业;公司;公司", "typecode": "061300|170200", "pcode": 420000, "pname": "湖北省", "citycode": 27, "cityname": "武汉市", "adcode": 420105, "adname": "汉阳区", "business_a": " ", "location": "114.213931,30.515344", "tel": "027-84236866;15997435777", "fetch_time": "19/1/2025 12:03:55", "大类": "购物服务", "中类": "特殊买卖场所", "小类": "特殊买卖场所|公司企业;公司;公司", "wgs84经ti": 114.208468, "wgs84纬ti": 30.517811}}, {"type": "Feature", "id": 183102, "geometry": {"type": "Point", "coordinates": [114.21394600040765, 30.513350999948727]}, "properties": {"OBJECTID": 183102, "poiid": "B0FFK9HNG8", "name": "诚誉寄售公司", "address": "四新地区管委会四新南路金地澜菲溪岸E15-102商铺", "type": "购物服务;特殊买卖场所;特殊买卖场所|公司企业;公司;公司", "typecode": "061300|170200", "pcode": 420000, "pname": "湖北省", "citycode": 27, "cityname": "武汉市", "adcode": 420105, "adname": "汉阳区", "business_a": " ", "location": "114.213946,30.513351", "tel": "027-84669997;13657299440", "fetch_time": "19/1/2025 06:47:08", "大类": "购物服务", "中类": "特殊买卖场所", "小类": "特殊买卖场所|公司企业;公司;公司", "wgs84经ti": 114.208483, "wgs84纬ti": 30.515819}}]}