{"type": "FeatureCollection", "features": [{"type": "Feature", "id": 11534, "geometry": {"type": "Point", "coordinates": [114.4444320002367, 30.579425000063736]}, "properties": {"OBJECTID": 11534, "poiid": "B0FFJ24VU4", "name": "诚鑫寄存行", "address": "武东路新武东小区", "type": "购物服务;特殊买卖场所;特殊买卖场所|生活服务;生活服务场所;生活服务场所", "typecode": "061300|070000", "pcode": 420000, "pname": "湖北省", "citycode": 27, "cityname": "武汉市", "adcode": 420111, "adname": "洪山区", "business_a": " ", "location": "114.444432,30.579425", "tel": " ", "fetch_time": "19/1/2025 21:02:06", "大类": "购物服务", "中类": "特殊买卖场所", "小类": "特殊买卖场所|生活服务;生活服务场所;生活服务场所", "wgs84经ti": 114.438951, "wgs84纬ti": 30.581745}}, {"type": "Feature", "id": 38463, "geometry": {"type": "Point", "coordinates": [114.37228699984519, 30.87438099978334]}, "properties": {"OBJECTID": 38463, "poiid": "B0FFI89VXL", "name": "柯斌典(寄售行)", "address": "前川街老汽车站", "type": "购物服务;特殊买卖场所;特殊买卖场所|生活服务;生活服务场所;生活服务场所", "typecode": "061300|070000", "pcode": 420000, "pname": "湖北省", "citycode": 27, "cityname": "武汉市", "adcode": 420116, "adname": "黄陂区", "business_a": "前川", "location": "114.372287,30.874381", "tel": " ", "fetch_time": "19/1/2025 20:53:46", "大类": "购物服务", "中类": "特殊买卖场所", "小类": "特殊买卖场所|生活服务;生活服务场所;生活服务场所", "wgs84经ti": 114.366722, "wgs84纬ti": 30.876535}}, {"type": "Feature", "id": 97681, "geometry": {"type": "Point", "coordinates": [114.2602909999298, 30.586890999919774]}, "properties": {"OBJECTID": 97681, "poiid": "B0FFKT7AXC", "name": "广寄发", "address": "宝丰二路与航空路交叉口东北80米", "type": "购物服务;特殊买卖场所;特殊买卖场所|生活服务;生活服务场所;生活服务场所", "typecode": "061300|070000", "pcode": 420000, "pname": "湖北省", "citycode": 27, "cityname": "武汉市", "adcode": 420103, "adname": "江汉区", "business_a": "万松", "location": "114.260291,30.586891", "tel": " ", "fetch_time": "19/1/2025 12:03:55", "大类": "购物服务", "中类": "特殊买卖场所", "小类": "特殊买卖场所|生活服务;生活服务场所;生活服务场所", "wgs84经ti": 114.254878, "wgs84纬ti": 30.589354}}, {"type": "Feature", "id": 180073, "geometry": {"type": "Point", "coordinates": [114.28124400031038, 30.651757000085524]}, "properties": {"OBJECTID": 180073, "poiid": "B0IDOSWQHL", "name": "爱尚奢品二手奢侈品回收包包手表钻戒钻石黄金首饰回收", "address": "健康街2号越秀星汇君泊三期B座二栋一单元23层2315", "type": "购物服务;特殊买卖场所;特殊买卖场所|生活服务;生活服务场所;生活服务场所", "typecode": "061300|070000", "pcode": 420000, "pname": "湖北省", "citycode": 27, "cityname": "武汉市", "adcode": 420102, "adname": "江岸区", "business_a": "后湖", "location": "114.281244,30.651757", "tel": "13377892582;13387606781", "fetch_time": "19/1/2025 00:48:35", "大类": "购物服务", "中类": "特殊买卖场所", "小类": "特殊买卖场所|生活服务;生活服务场所;生活服务场所", "wgs84经ti": 114.27582, "wgs84纬ti": 30.654177}}]}