{"type": "FeatureCollection", "features": [{"type": "Feature", "id": 47186, "geometry": {"type": "Point", "coordinates": [114.22658499959812, 30.618318000375496]}, "properties": {"OBJECTID": 47186, "poiid": "B0FFG89X4B", "name": "佐尔美", "address": "江汉经济开发区江发路38号", "type": "购物服务;服装鞋帽皮具店;品牌服装店|公司企业;公司;公司", "typecode": "061101|170200", "pcode": 420000, "pname": "湖北省", "citycode": 27, "cityname": "武汉市", "adcode": 420103, "adname": "江汉区", "business_a": "常青", "location": "114.226585,30.618318", "tel": " ", "fetch_time": "19/1/2025 22:10:34", "大类": "购物服务", "中类": "服装鞋帽皮具店", "小类": "品牌服装店|公司企业;公司;公司", "wgs84经ti": 114.221137, "wgs84纬ti": 30.620761}}, {"type": "Feature", "id": 182939, "geometry": {"type": "Point", "coordinates": [114.22634300012942, 30.61829200007577]}, "properties": {"OBJECTID": 182939, "poiid": "B0FFG89X4B", "name": "佐尔美", "address": "江汉经济开发区江发路38号", "type": "购物服务;服装鞋帽皮具店;品牌服装店|公司企业;公司;公司", "typecode": "061101|170200", "pcode": 420000, "pname": "湖北省", "citycode": 27, "cityname": "武汉市", "adcode": 420103, "adname": "江汉区", "business_a": "常青", "location": "114.226343,30.618292", "tel": " ", "fetch_time": "19/1/2025 06:29:47", "大类": "购物服务", "中类": "服装鞋帽皮具店", "小类": "品牌服装店|公司企业;公司;公司", "wgs84经ti": 114.220895, "wgs84纬ti": 30.620735}}]}