{"type": "FeatureCollection", "features": [{"type": "Feature", "id": 54669, "geometry": {"type": "Point", "coordinates": [114.40157299959435, 30.505944000115562]}, "properties": {"OBJECTID": 54669, "poiid": "B0FFJJGOOT", "name": "洛可可(世界城广场店)", "address": "光谷街3号大洋百货三楼", "type": "购物服务;服装鞋帽皮具店;品牌服装店|商务住宅;商务住宅相关;商务住宅相关", "typecode": "061101|120000", "pcode": 420000, "pname": "湖北省", "citycode": 27, "cityname": "武汉市", "adcode": 420111, "adname": "洪山区", "business_a": "关山", "location": "114.401573,30.505944", "tel": " ", "fetch_time": "19/1/2025 22:57:27", "大类": "购物服务", "中类": "服装鞋帽皮具店", "小类": "品牌服装店|商务住宅;商务住宅相关;商务住宅相关", "wgs84经ti": 114.396033, "wgs84纬ti": 30.50825}}]}