{"type": "FeatureCollection", "features": [{"type": "Feature", "id": 4012, "geometry": {"type": "Point", "coordinates": [114.26911400031088, 30.58001600033822]}, "properties": {"OBJECTID": 4012, "poiid": "B0FFHE3QQV", "name": "goldlion(世贸广场)", "address": "解放大道686号世贸广场F4层", "type": "购物服务;服装鞋帽皮具店;品牌鞋店|购物服务;服装鞋帽皮具店;品牌服装店", "typecode": "061102|061101", "pcode": 420000, "pname": "湖北省", "citycode": 27, "cityname": "武汉市", "adcode": 420103, "adname": "江汉区", "business_a": "江滩", "location": "114.269114,30.580016", "tel": " ", "fetch_time": "19/1/2025 21:07:37", "大类": "购物服务", "中类": "服装鞋帽皮具店", "小类": "品牌鞋店|购物服务;服装鞋帽皮具店;品牌服装店", "wgs84经ti": 114.263701, "wgs84纬ti": 30.582477}}, {"type": "Feature", "id": 8448, "geometry": {"type": "Point", "coordinates": [114.33887100029654, 30.557299000448552]}, "properties": {"OBJECTID": 8448, "poiid": "B0FFHT5IY6", "name": "staccato(万达广场店)", "address": "水果湖街办事处水果湖办事处水果湖街东湖万达百货2楼", "type": "购物服务;服装鞋帽皮具店;品牌鞋店|购物服务;服装鞋帽皮具店;品牌服装店", "typecode": "061102|061101", "pcode": 420000, "pname": "湖北省", "citycode": 27, "cityname": "武汉市", "adcode": 420106, "adname": "武昌区", "business_a": "水果湖", "location": "114.338871,30.557299", "tel": "027-87732921", "fetch_time": "19/1/2025 20:36:50", "大类": "购物服务", "中类": "服装鞋帽皮具店", "小类": "品牌鞋店|购物服务;服装鞋帽皮具店;品牌服装店", "wgs84经ti": 114.333377, "wgs84纬ti": 30.559659}}, {"type": "Feature", "id": 38444, "geometry": {"type": "Point", "coordinates": [114.25690100008114, 30.73118399994172]}, "properties": {"OBJECTID": 38444, "poiid": "B0FFF3JDTO", "name": "崇高奥莱(百联奥特莱斯广场)", "address": "盘龙大道51号百联奥特莱斯广场f1层014-015", "type": "购物服务;服装鞋帽皮具店;品牌鞋店|购物服务;服装鞋帽皮具店;品牌服装店", "typecode": "061102|061101", "pcode": 420000, "pname": "湖北省", "citycode": 27, "cityname": "武汉市", "adcode": 420116, "adname": "黄陂区", "business_a": "奥特莱斯广场", "location": "114.256901,30.731184", "tel": " ", "fetch_time": "19/1/2025 20:52:10", "大类": "购物服务", "中类": "服装鞋帽皮具店", "小类": "品牌鞋店|购物服务;服装鞋帽皮具店;品牌服装店", "wgs84经ti": 114.251474, "wgs84纬ti": 30.733584}}, {"type": "Feature", "id": 94448, "geometry": {"type": "Point", "coordinates": [114.34462000011297, 30.59006199956167]}, "properties": {"OBJECTID": 94448, "poiid": "B0FFF54FVQ", "name": "goldlion(中商徐东平价广场店)", "address": "徐东大街7号中商徐东平价广场F1", "type": "购物服务;服装鞋帽皮具店;品牌鞋店|购物服务;服装鞋帽皮具店;品牌服装店", "typecode": "061102|061101", "pcode": 420000, "pname": "湖北省", "citycode": 27, "cityname": "武汉市", "adcode": 420111, "adname": "洪山区", "business_a": "杨园", "location": "114.344620,30.590062", "tel": " ", "fetch_time": "19/1/2025 12:03:55", "大类": "购物服务", "中类": "服装鞋帽皮具店", "小类": "品牌鞋店|购物服务;服装鞋帽皮具店;品牌服装店", "wgs84经ti": 114.339114, "wgs84纬ti": 30.5924}}]}