{"type": "FeatureCollection", "features": [{"type": "Feature", "id": 52283, "geometry": {"type": "Point", "coordinates": [114.33212500036848, 30.537133000387712]}, "properties": {"OBJECTID": 52283, "poiid": "B0FFHYKU42", "name": "EMZ鄂尔多斯（中商广场店）", "address": "中南路9号中商广场4楼A区鄂尔多斯店", "type": "购物服务;服装鞋帽皮具店;品牌服装店|生活服务;邮局;邮局", "typecode": "061101|070400", "pcode": 420000, "pname": "湖北省", "citycode": 27, "cityname": "武汉市", "adcode": 420106, "adname": "武昌区", "business_a": "中南路/中南", "location": "114.332125,30.537133", "tel": "027-87279886;13797021338", "fetch_time": "19/1/2025 22:39:09", "大类": "购物服务", "中类": "服装鞋帽皮具店", "小类": "品牌服装店|生活服务;邮局;邮局", "wgs84经ti": 114.326643, "wgs84纬ti": 30.539513}}]}