{"type": "FeatureCollection", "features": [{"type": "Feature", "id": 181764, "geometry": {"type": "Point", "coordinates": [114.35541499970259, 30.525334000363898]}, "properties": {"OBJECTID": 181764, "poiid": "B0FFI211QW", "name": "JEEP男装", "address": "珞瑜路6号群光广场4层(街道口地铁站B口旁)", "type": "购物服务;服装鞋帽皮具店;品牌服装店|购物服务;服装鞋帽皮具店;品牌皮具店", "typecode": "061101|061103", "pcode": 420000, "pname": "湖北省", "citycode": 27, "cityname": "武汉市", "adcode": 420111, "adname": "洪山区", "business_a": "街道口", "location": "114.355415,30.525334", "tel": " ", "fetch_time": "19/1/2025 04:30:41", "大类": "购物服务", "中类": "服装鞋帽皮具店", "小类": "品牌服装店|购物服务;服装鞋帽皮具店;品牌皮具店", "wgs84经ti": 114.349899, "wgs84纬ti": 30.527676}}]}