{"type": "FeatureCollection", "features": [{"type": "Feature", "id": 146193, "geometry": {"type": "Point", "coordinates": [114.57398999973873, 30.658028999738576]}, "properties": {"OBJECTID": 146193, "poiid": "B0FFL6P7CP", "name": "钰枫国际", "address": "长丰路100号附近", "type": "购物服务;服装鞋帽皮具店;服装鞋帽皮具店|生活服务;美容美发店;美容美发店|商务住宅;商务住宅相关;商务住宅相关", "typecode": "061100|071100|120000", "pcode": 420000, "pname": "湖北省", "citycode": 27, "cityname": "武汉市", "adcode": 420117, "adname": "新洲区", "business_a": "阳逻", "location": "114.573990,30.658029", "tel": " ", "fetch_time": "19/1/2025 12:03:55", "大类": "购物服务", "中类": "服装鞋帽皮具店", "小类": "服装鞋帽皮具店|生活服务;美容美发店;美容美发店|商务住宅;商务住宅相关;商务住宅相关", "wgs84经ti": 114.568909, "wgs84纬ti": 30.660633}}, {"type": "Feature", "id": 156168, "geometry": {"type": "Point", "coordinates": [114.38780499960114, 30.492564000028608]}, "properties": {"OBJECTID": 156168, "poiid": "B0FFI96XPM", "name": "谷阁", "address": "荣院路八一花园D2栋底商", "type": "购物服务;服装鞋帽皮具店;服装鞋帽皮具店|生活服务;美容美发店;美容美发店|商务住宅;商务住宅相关;商务住宅相关", "typecode": "061100|071100|120000", "pcode": 420000, "pname": "湖北省", "citycode": 27, "cityname": "武汉市", "adcode": 420111, "adname": "洪山区", "business_a": " ", "location": "114.387805,30.492564", "tel": " ", "fetch_time": "19/1/2025 12:03:55", "大类": "购物服务", "中类": "服装鞋帽皮具店", "小类": "服装鞋帽皮具店|生活服务;美容美发店;美容美发店|商务住宅;商务住宅相关;商务住宅相关", "wgs84经ti": 114.382265, "wgs84纬ti": 30.494878}}]}