{"type": "FeatureCollection", "features": [{"type": "Feature", "id": 132480, "geometry": {"type": "Point", "coordinates": [114.38712000038777, 30.47830699996814]}, "properties": {"OBJECTID": 132480, "poiid": "B0FFIA7MU2", "name": "潮人馆", "address": "南湖大道光谷时尚城星巴克楼上", "type": "购物服务;服装鞋帽皮具店;服装鞋帽皮具店|体育休闲服务;娱乐场所;娱乐场所", "typecode": "061100|080300", "pcode": 420000, "pname": "湖北省", "citycode": 27, "cityname": "武汉市", "adcode": 420115, "adname": "江夏区", "business_a": " ", "location": "114.387120,30.478307", "tel": "13100669257", "fetch_time": "19/1/2025 12:03:55", "大类": "购物服务", "中类": "服装鞋帽皮具店", "小类": "服装鞋帽皮具店|体育休闲服务;娱乐场所;娱乐场所", "wgs84经ti": 114.381581, "wgs84纬ti": 30.480625}}]}