{"type": "FeatureCollection", "features": [{"type": "Feature", "id": 65098, "geometry": {"type": "Point", "coordinates": [114.27594000033082, 30.56649399999816]}, "properties": {"OBJECTID": 65098, "poiid": "B0FFFFWSPI", "name": "东盛国际袜城", "address": "华贸3号楼2楼", "type": "购物服务;服装鞋帽皮具店;服装鞋帽皮具店|商务住宅;商务住宅相关;商务住宅相关", "typecode": "061100|120000", "pcode": 420000, "pname": "湖北省", "citycode": 27, "cityname": "武汉市", "adcode": 420104, "adname": "硚口区", "business_a": "江滩", "location": "114.275940,30.566494", "tel": "13237175333", "fetch_time": "19/1/2025 09:25:32", "大类": "购物服务", "中类": "服装鞋帽皮具店", "小类": "服装鞋帽皮具店|商务住宅;商务住宅相关;商务住宅相关", "wgs84经ti": 114.270526, "wgs84纬ti": 30.568954}}, {"type": "Feature", "id": 137035, "geometry": {"type": "Point", "coordinates": [114.56037399956051, 30.653458000286548]}, "properties": {"OBJECTID": 137035, "poiid": "B001B0A6W4", "name": "金海岸", "address": "老正街江北星城西南侧约210米", "type": "购物服务;服装鞋帽皮具店;服装鞋帽皮具店|商务住宅;商务住宅相关;商务住宅相关", "typecode": "061100|120000", "pcode": 420000, "pname": "湖北省", "citycode": 27, "cityname": "武汉市", "adcode": 420117, "adname": "新洲区", "business_a": "阳逻", "location": "114.560374,30.653458", "tel": " ", "fetch_time": "19/1/2025 12:03:55", "大类": "购物服务", "中类": "服装鞋帽皮具店", "小类": "服装鞋帽皮具店|商务住宅;商务住宅相关;商务住宅相关", "wgs84经ti": 114.555269, "wgs84纬ti": 30.656045}}, {"type": "Feature", "id": 147122, "geometry": {"type": "Point", "coordinates": [114.37984400030041, 30.619170000095494]}, "properties": {"OBJECTID": 147122, "poiid": "B0FFGPNVOL", "name": "东方巴黎(辽宁街)", "address": "辽宁街42号", "type": "购物服务;服装鞋帽皮具店;服装鞋帽皮具店|商务住宅;商务住宅相关;商务住宅相关", "typecode": "061100|120000", "pcode": 420000, "pname": "湖北省", "citycode": 27, "cityname": "武汉市", "adcode": 420107, "adname": "青山区", "business_a": "罗家桥", "location": "114.379844,30.619170", "tel": " ", "fetch_time": "19/1/2025 12:03:55", "大类": "购物服务", "中类": "服装鞋帽皮具店", "小类": "服装鞋帽皮具店|商务住宅;商务住宅相关;商务住宅相关", "wgs84经ti": 114.374296, "wgs84纬ti": 30.621446}}, {"type": "Feature", "id": 163907, "geometry": {"type": "Point", "coordinates": [114.34269600042012, 30.662591999721087]}, "properties": {"OBJECTID": 163907, "poiid": "B0FFHJ7FUM", "name": "迪嫚明珠", "address": "江北路与江中路交叉口北180米", "type": "购物服务;服装鞋帽皮具店;服装鞋帽皮具店|商务住宅;商务住宅相关;商务住宅相关", "typecode": "061100|120000", "pcode": 420000, "pname": "湖北省", "citycode": 27, "cityname": "武汉市", "adcode": 420102, "adname": "江岸区", "business_a": "丹水池", "location": "114.342696,30.662592", "tel": " ", "fetch_time": "19/1/2025 12:03:55", "大类": "购物服务", "中类": "服装鞋帽皮具店", "小类": "服装鞋帽皮具店|商务住宅;商务住宅相关;商务住宅相关", "wgs84经ti": 114.337187, "wgs84纬ti": 30.664903}}]}