{"type": "FeatureCollection", "features": [{"type": "Feature", "id": 111325, "geometry": {"type": "Point", "coordinates": [114.29317600017237, 30.584971999558206]}, "properties": {"OBJECTID": 111325, "poiid": "B0HR3CDGJS", "name": "梵雅生活馆", "address": "大智街办事处崇善路11号", "type": "购物服务;服装鞋帽皮具店;服装鞋帽皮具店|购物服务;家居建材市场;家居建材市场|生活服务;美容美发店;美容美发店", "typecode": "061100|060600|071100", "pcode": 420000, "pname": "湖北省", "citycode": 27, "cityname": "武汉市", "adcode": 420102, "adname": "江岸区", "business_a": "新华", "location": "114.293176,30.584972", "tel": " ", "fetch_time": "19/1/2025 12:03:55", "大类": "购物服务", "中类": "服装鞋帽皮具店", "小类": "服装鞋帽皮具店|购物服务;家居建材市场;家居建材市场|生活服务;美容美发店;美容美发店", "wgs84经ti": 114.287747, "wgs84纬ti": 30.587404}}]}