{"type": "FeatureCollection", "features": [{"type": "Feature", "id": 58610, "geometry": {"type": "Point", "coordinates": [114.26709399978836, 30.56883500003528]}, "properties": {"OBJECTID": 58610, "poiid": "B001B19SXJ", "name": "我家小馆(凯德广场店)", "address": "中山大道238号凯德广场7层14-15、19号商铺", "type": "餐饮服务;中餐厅;中餐厅|室内设施;室内设施;室内设施", "typecode": "050100|970000", "pcode": 420000, "pname": "湖北省", "citycode": 27, "cityname": "武汉市", "adcode": 420104, "adname": "硚口区", "business_a": "汉中", "location": "114.267094,30.568835", "tel": " ", "fetch_time": "19/1/2025 12:03:55", "大类": "餐饮服务", "中类": "中餐厅", "小类": "中餐厅|室内设施;室内设施;室内设施", "wgs84经ti": 114.261682, "wgs84纬ti": 30.571301}}]}