{"type": "FeatureCollection", "features": [{"type": "Feature", "id": 41155, "geometry": {"type": "Point", "coordinates": [114.41910599964228, 30.51127599958778]}, "properties": {"OBJECTID": 41155, "poiid": "B0FFFZO767", "name": "斑马智洗华中科技大学东一学生食堂衣物代收点", "address": "珞瑜路1037号华中科技大学", "type": "餐饮服务;中餐厅;中餐厅|生活服务;洗衣店;洗衣店", "typecode": "050100|071500", "pcode": 420000, "pname": "湖北省", "citycode": 27, "cityname": "武汉市", "adcode": 420111, "adname": "洪山区", "business_a": " ", "location": "114.419106,30.511276", "tel": " ", "fetch_time": "19/1/2025 08:58:34", "大类": "餐饮服务", "中类": "中餐厅", "小类": "中餐厅|生活服务;洗衣店;洗衣店", "wgs84经ti": 114.413581, "wgs84纬ti": 30.513586}}]}