{"type": "FeatureCollection", "features": [{"type": "Feature", "id": 34560, "geometry": {"type": "Point", "coordinates": [114.12544899957174, 30.61231200039856]}, "properties": {"OBJECTID": 34560, "poiid": "B0FFFV6UEQ", "name": "大圣甲(东西湖店)", "address": "八方路纽宾凯旁", "type": "餐饮服务;中餐厅;中餐厅|生活服务;美容美发店;美容美发店", "typecode": "050100|071100", "pcode": 420000, "pname": "湖北省", "citycode": 27, "cityname": "武汉市", "adcode": 420112, "adname": "东西湖区", "business_a": "吴家山", "location": "114.125449,30.612312", "tel": "027-83291077", "fetch_time": "19/1/2025 23:06:30", "大类": "餐饮服务", "中类": "中餐厅", "小类": "中餐厅|生活服务;美容美发店;美容美发店", "wgs84经ti": 114.119746, "wgs84纬ti": 30.614599}}]}