{"type": "FeatureCollection", "features": [{"type": "Feature", "id": 8952, "geometry": {"type": "Point", "coordinates": [114.01895000044226, 30.452174999976307]}, "properties": {"OBJECTID": 8952, "poiid": "B0FFFSSFX6", "name": "星月轩酒楼", "address": "奓山街星月花园1栋1层10号门面", "type": "餐饮服务;中餐厅;湖北菜(鄂菜)|餐饮服务;中餐厅;综合酒楼", "typecode": "050112|050101", "pcode": 420000, "pname": "湖北省", "citycode": 27, "cityname": "武汉市", "adcode": 420114, "adname": "蔡甸区", "business_a": " ", "location": "114.018950,30.452175", "tel": "18971346618", "fetch_time": "19/1/2025 21:27:10", "大类": "餐饮服务", "中类": "中餐厅", "小类": "湖北菜(鄂菜)|餐饮服务;中餐厅;综合酒楼", "wgs84经ti": 114.013311, "wgs84纬ti": 30.45463}}, {"type": "Feature", "id": 14587, "geometry": {"type": "Point", "coordinates": [114.4122029996688, 30.503941000376926]}, "properties": {"OBJECTID": 14587, "poiid": "B001B0JWYB", "name": "简朴田园寨(光谷航母店)", "address": "关山一路124号武汉汽轮发电厂48栋1-4层", "type": "餐饮服务;中餐厅;湖北菜(鄂菜)|餐饮服务;中餐厅;综合酒楼", "typecode": "050112|050101", "pcode": 420000, "pname": "湖北省", "citycode": 27, "cityname": "武汉市", "adcode": 420111, "adname": "洪山区", "business_a": "光谷", "location": "114.412203,30.503941", "tel": "18995579990", "fetch_time": "19/1/2025 21:25:34", "大类": "餐饮服务", "中类": "中餐厅", "小类": "湖北菜(鄂菜)|餐饮服务;中餐厅;综合酒楼", "wgs84经ti": 114.406671, "wgs84纬ti": 30.506249}}, {"type": "Feature", "id": 26506, "geometry": {"type": "Point", "coordinates": [114.30677999979719, 30.56308300008044]}, "properties": {"OBJECTID": 26506, "poiid": "B0G0CUYQNM", "name": "简朴寨农庄菜馆", "address": "临江大道88号", "type": "餐饮服务;中餐厅;湖北菜(鄂菜)|餐饮服务;中餐厅;综合酒楼", "typecode": "050112|050101", "pcode": 420000, "pname": "湖北省", "citycode": 27, "cityname": "武汉市", "adcode": 420106, "adname": "武昌区", "business_a": "积玉桥", "location": "114.306780,30.563083", "tel": "027-88221717", "fetch_time": "19/1/2025 20:52:36", "大类": "餐饮服务", "中类": "中餐厅", "小类": "湖北菜(鄂菜)|餐饮服务;中餐厅;综合酒楼", "wgs84经ti": 114.301336, "wgs84纬ti": 30.565501}}, {"type": "Feature", "id": 26522, "geometry": {"type": "Point", "coordinates": [114.32142099957957, 30.513159000087853]}, "properties": {"OBJECTID": 26522, "poiid": "B0FFFGLRCM", "name": "南湖虾蛙餐馆", "address": "瑞安街宁静苑30栋1层", "type": "餐饮服务;中餐厅;湖北菜(鄂菜)|餐饮服务;中餐厅;综合酒楼", "typecode": "050112|050101", "pcode": 420000, "pname": "湖北省", "citycode": 27, "cityname": "武汉市", "adcode": 420106, "adname": "武昌区", "business_a": "丁字桥", "location": "114.321421,30.513159", "tel": "15926239778", "fetch_time": "19/1/2025 20:52:38", "大类": "餐饮服务", "中类": "中餐厅", "小类": "湖北菜(鄂菜)|餐饮服务;中餐厅;综合酒楼", "wgs84经ti": 114.315959, "wgs84纬ti": 30.515567}}]}