{"type": "FeatureCollection", "features": [{"type": "Feature", "id": 36511, "geometry": {"type": "Point", "coordinates": [114.26070900032016, 30.7281929996073]}, "properties": {"OBJECTID": 36511, "poiid": "B0FFKNOJKQ", "name": "三五酒店(奥特莱斯店)", "address": "盘龙大道50号", "type": "餐饮服务;中餐厅;湖北菜(鄂菜)|住宿服务;宾馆酒店;宾馆酒店", "typecode": "050112|100100", "pcode": 420000, "pname": "湖北省", "citycode": 27, "cityname": "武汉市", "adcode": 420116, "adname": "黄陂区", "business_a": "奥特莱斯广场", "location": "114.260709,30.728193", "tel": "027-61907777", "fetch_time": "19/1/2025 23:42:53", "大类": "餐饮服务", "中类": "中餐厅", "小类": "湖北菜(鄂菜)|住宿服务;宾馆酒店;宾馆酒店", "wgs84经ti": 114.255284, "wgs84纬ti": 30.730593}}, {"type": "Feature", "id": 36554, "geometry": {"type": "Point", "coordinates": [114.30283400038888, 30.695352999641273]}, "properties": {"OBJECTID": 36554, "poiid": "B0FFHZGYTO", "name": "三五酒店(盘龙城万达店)", "address": "巨龙大道盘龙一路万达c1", "type": "餐饮服务;中餐厅;湖北菜(鄂菜)|住宿服务;宾馆酒店;宾馆酒店", "typecode": "050112|100100", "pcode": 420000, "pname": "湖北省", "citycode": 27, "cityname": "武汉市", "adcode": 420116, "adname": "黄陂区", "business_a": " ", "location": "114.302834,30.695353", "tel": "027-65605888", "fetch_time": "19/1/2025 23:42:54", "大类": "餐饮服务", "中类": "中餐厅", "小类": "湖北菜(鄂菜)|住宿服务;宾馆酒店;宾馆酒店", "wgs84经ti": 114.297384, "wgs84纬ti": 30.697723}}, {"type": "Feature", "id": 48046, "geometry": {"type": "Point", "coordinates": [114.28856199963661, 30.60682199993539]}, "properties": {"OBJECTID": 48046, "poiid": "B0FFICGVX7", "name": "航海大酒店", "address": "惠济路长江航运总医院", "type": "餐饮服务;中餐厅;湖北菜(鄂菜)|住宿服务;宾馆酒店;宾馆酒店", "typecode": "050112|100100", "pcode": 420000, "pname": "湖北省", "citycode": 27, "cityname": "武汉市", "adcode": 420102, "adname": "江岸区", "business_a": "二七", "location": "114.288562,30.606822", "tel": " ", "fetch_time": "19/1/2025 08:51:35", "大类": "餐饮服务", "中类": "中餐厅", "小类": "湖北菜(鄂菜)|住宿服务;宾馆酒店;宾馆酒店", "wgs84经ti": 114.283136, "wgs84纬ti": 30.609252}}, {"type": "Feature", "id": 95443, "geometry": {"type": "Point", "coordinates": [114.26070900032016, 30.7281929996073]}, "properties": {"OBJECTID": 95443, "poiid": "B0FFKNOJKQ", "name": "三五酒店(奥特莱斯店)", "address": "盘龙大道50号", "type": "餐饮服务;中餐厅;湖北菜(鄂菜)|住宿服务;宾馆酒店;宾馆酒店", "typecode": "050112|100100", "pcode": 420000, "pname": "湖北省", "citycode": 27, "cityname": "武汉市", "adcode": 420116, "adname": "黄陂区", "business_a": "奥特莱斯广场", "location": "114.260709,30.728193", "tel": "027-61907777", "fetch_time": "19/1/2025 06:47:09", "大类": "餐饮服务", "中类": "中餐厅", "小类": "湖北菜(鄂菜)|住宿服务;宾馆酒店;宾馆酒店", "wgs84经ti": 114.255284, "wgs84纬ti": 30.730593}}]}