{"type": "FeatureCollection", "features": [{"type": "Feature", "id": 6190, "geometry": {"type": "Point", "coordinates": [114.30914500004178, 30.560363999698893]}, "properties": {"OBJECTID": 6190, "poiid": "B0FFJMQNRY", "name": "积玉桥湘香狗肉馆", "address": "积玉桥地铁C出口招商银行旁", "type": "餐饮服务;中餐厅;湖南菜(湘菜)|餐饮服务;中餐厅;特色/地方风味餐厅", "typecode": "050108|050118", "pcode": 420000, "pname": "湖北省", "citycode": 27, "cityname": "武汉市", "adcode": 420106, "adname": "武昌区", "business_a": "积玉桥", "location": "114.309145,30.560364", "tel": "027-88228776;13971061312", "fetch_time": "19/1/2025 21:35:25", "大类": "餐饮服务", "中类": "中餐厅", "小类": "湖南菜(湘菜)|餐饮服务;中餐厅;特色/地方风味餐厅", "wgs84经ti": 114.303698, "wgs84纬ti": 30.562779}}, {"type": "Feature", "id": 61612, "geometry": {"type": "Point", "coordinates": [114.31181700005459, 30.44486099993526]}, "properties": {"OBJECTID": 61612, "poiid": "B0FFFEFQMG", "name": "湖南米粉(新发路)", "address": "新路村洛家里学院1号门", "type": "餐饮服务;中餐厅;湖南菜(湘菜)|餐饮服务;中餐厅;特色/地方风味餐厅", "typecode": "050108|050118", "pcode": 420000, "pname": "湖北省", "citycode": 27, "cityname": "武汉市", "adcode": 420111, "adname": "洪山区", "business_a": " ", "location": "114.311817,30.444861", "tel": " ", "fetch_time": "19/1/2025 12:03:55", "大类": "餐饮服务", "中类": "中餐厅", "小类": "湖南菜(湘菜)|餐饮服务;中餐厅;特色/地方风味餐厅", "wgs84经ti": 114.306376, "wgs84纬ti": 30.447306}}]}