{"type": "FeatureCollection", "features": [{"type": "Feature", "id": 54399, "geometry": {"type": "Point", "coordinates": [114.40473999995106, 30.503888999777587]}, "properties": {"OBJECTID": 54399, "poiid": "B0FFG4K07O", "name": "地道湘菜馆(加州阳光美食街店)", "address": "光谷世界城C地块1号楼后端特色餐饮区一楼SL037SL038号商铺", "type": "餐饮服务;中餐厅;火锅店|餐饮服务;中餐厅;湖南菜(湘菜)", "typecode": "050117|050108", "pcode": 420000, "pname": "湖北省", "citycode": 27, "cityname": "武汉市", "adcode": 420111, "adname": "洪山区", "business_a": "光谷", "location": "114.404740,30.503889", "tel": "15717189624", "fetch_time": "19/1/2025 12:03:55", "大类": "餐饮服务", "中类": "中餐厅", "小类": "火锅店|餐饮服务;中餐厅;湖南菜(湘菜)", "wgs84经ti": 114.399202, "wgs84纬ti": 30.506195}}]}