{"type": "FeatureCollection", "features": [{"type": "Feature", "id": 16990, "geometry": {"type": "Point", "coordinates": [114.67437400016001, 30.873024000157557]}, "properties": {"OBJECTID": 16990, "poiid": "B0FFLGQQ2T", "name": "泰和楼", "address": "商场街12号", "type": "餐饮服务;中餐厅;综合酒楼|商务住宅;住宅区;住宅小区", "typecode": "050101|120302", "pcode": 420000, "pname": "湖北省", "citycode": 27, "cityname": "武汉市", "adcode": 420117, "adname": "新洲区", "business_a": "李集", "location": "114.674374,30.873024", "tel": "027-89667177", "fetch_time": "19/1/2025 21:08:39", "大类": "餐饮服务", "中类": "中餐厅", "小类": "综合酒楼|商务住宅;住宅区;住宅小区", "wgs84经ti": 114.669194, "wgs84纬ti": 30.875431}}]}