{"type": "FeatureCollection", "features": [{"type": "Feature", "id": 8814, "geometry": {"type": "Point", "coordinates": [114.2924380003135, 30.58630900006034]}, "properties": {"OBJECTID": 8814, "poiid": "B0FFF5Q4NF", "name": "中华老字号", "address": "交易街亚洲证券大厦西南侧", "type": "餐饮服务;中餐厅;老字号", "typecode": "050116", "pcode": 420000, "pname": "湖北省", "citycode": 27, "cityname": "武汉市", "adcode": 420102, "adname": "江岸区", "business_a": "江滩", "location": "114.292438,30.586309", "tel": " ", "fetch_time": "19/1/2025 21:24:19", "大类": "餐饮服务", "中类": "中餐厅", "小类": "老字号", "wgs84经ti": 114.28701, "wgs84纬ti": 30.588742}}, {"type": "Feature", "id": 34441, "geometry": {"type": "Point", "coordinates": [114.23834100033696, 30.65000700032283]}, "properties": {"OBJECTID": 34441, "poiid": "B0FFFQ2PLL", "name": "永兴家味", "address": "金银潭大道康居四路2号永旺梦乐城3楼", "type": "餐饮服务;中餐厅;老字号", "typecode": "050116", "pcode": 420000, "pname": "湖北省", "citycode": 27, "cityname": "武汉市", "adcode": 420112, "adname": "东西湖区", "business_a": " ", "location": "114.238341,30.650007", "tel": "027-59608477;027-59608436", "fetch_time": "19/1/2025 23:06:16", "大类": "餐饮服务", "中类": "中餐厅", "小类": "老字号", "wgs84经ti": 114.232907, "wgs84纬ti": 30.652444}}, {"type": "Feature", "id": 41878, "geometry": {"type": "Point", "coordinates": [114.29633500016018, 30.54317900041059]}, "properties": {"OBJECTID": 41878, "poiid": "B0FFF75UVO", "name": "花太婆灌肠", "address": "大成路36号", "type": "餐饮服务;中餐厅;老字号", "typecode": "050116", "pcode": 420000, "pname": "湖北省", "citycode": 27, "cityname": "武汉市", "adcode": 420106, "adname": "武昌区", "business_a": "江滩", "location": "114.296335,30.543179", "tel": " ", "fetch_time": "19/1/2025 09:16:10", "大类": "餐饮服务", "中类": "中餐厅", "小类": "老字号", "wgs84经ti": 114.290906, "wgs84纬ti": 30.545621}}]}