{"type": "FeatureCollection", "features": [{"type": "Feature", "id": 29487, "geometry": {"type": "Point", "coordinates": [114.3032659996262, 30.622804999551136]}, "properties": {"OBJECTID": 29487, "poiid": "B0FFI1SJ5C", "name": "高塬风情清真餐厅(罗家庄店)", "address": "建设大道罗家庄长航宿舍59号楼1层6室", "type": "餐饮服务;中餐厅;西北菜|餐饮服务;中餐厅;清真菜馆", "typecode": "050115|050121", "pcode": 420000, "pname": "湖北省", "citycode": 27, "cityname": "武汉市", "adcode": 420102, "adname": "江岸区", "business_a": "二七", "location": "114.303266,30.622805", "tel": "027-82221160;15827540218", "fetch_time": "19/1/2025 21:59:08", "大类": "餐饮服务", "中类": "中餐厅", "小类": "西北菜|餐饮服务;中餐厅;清真菜馆", "wgs84经ti": 114.297822, "wgs84纬ti": 30.625206}}]}