{"type": "FeatureCollection", "features": [{"type": "Feature", "id": 748, "geometry": {"type": "Point", "coordinates": [114.41541899958725, 30.51286900020426]}, "properties": {"OBJECTID": 748, "poiid": "B001B1BXPF", "name": "华中科技大学国家机械基础课程教学基地现代制造实验与培训中心", "address": "珞瑜路1037号华中科技大学", "type": "科教文化服务;科研机构;科研机构|科教文化服务;培训机构;培训机构", "typecode": "141300|141400", "pcode": 420000, "pname": "湖北省", "citycode": 27, "cityname": "武汉市", "adcode": 420111, "adname": "洪山区", "business_a": " ", "location": "114.415419,30.512869", "tel": " ", "fetch_time": "19/1/2025 21:14:43", "大类": "科教文化服务", "中类": "科研机构", "小类": "科研机构|科教文化服务;培训机构;培训机构", "wgs84经ti": 114.40989, "wgs84纬ti": 30.515176}}, {"type": "Feature", "id": 19650, "geometry": {"type": "Point", "coordinates": [114.29804199973853, 30.63596999961584]}, "properties": {"OBJECTID": 19650, "poiid": "B001B1E6VL", "name": "新引擎个性化教育研究中心", "address": "兴业南路08号附近", "type": "科教文化服务;科研机构;科研机构|科教文化服务;培训机构;培训机构", "typecode": "141300|141400", "pcode": 420000, "pname": "湖北省", "citycode": 27, "cityname": "武汉市", "adcode": 420102, "adname": "江岸区", "business_a": "二七", "location": "114.298042,30.635970", "tel": " ", "fetch_time": "19/1/2025 08:38:28", "大类": "科教文化服务", "中类": "科研机构", "小类": "科研机构|科教文化服务;培训机构;培训机构", "wgs84经ti": 114.292603, "wgs84纬ti": 30.638374}}]}