{"type": "FeatureCollection", "features": [{"type": "Feature", "id": 142390, "geometry": {"type": "Point", "coordinates": [114.313168000303, 30.487036999657846]}, "properties": {"OBJECTID": 142390, "poiid": "B001B0JO9K", "name": "龙腾宏商贸园", "address": "南李纸路首义学校对面", "type": "购物服务;特色商业街;特色商业街|购物服务;便民商店/便利店;便民商店/便利店", "typecode": "061000|060200", "pcode": 420000, "pname": "湖北省", "citycode": 27, "cityname": "武汉市", "adcode": 420111, "adname": "洪山区", "business_a": " ", "location": "114.313168,30.487037", "tel": " ", "fetch_time": "19/1/2025 12:03:55", "大类": "购物服务", "中类": "特色商业街", "小类": "特色商业街|购物服务;便民商店/便利店;便民商店/便利店", "wgs84经ti": 114.307721, "wgs84纬ti": 30.489468}}]}