{"type": "FeatureCollection", "features": [{"type": "Feature", "id": 1018, "geometry": {"type": "Point", "coordinates": [114.28756999975576, 30.585654000431816]}, "properties": {"OBJECTID": 1018, "poiid": "B0FFLMMR8N", "name": "合内·合外", "address": "大智街街道京汉大道世纪大厦一楼合内", "type": "购物服务;特色商业街;特色商业街|餐饮服务;咖啡厅;咖啡厅", "typecode": "061000|050500", "pcode": 420000, "pname": "湖北省", "citycode": 27, "cityname": "武汉市", "adcode": 420102, "adname": "江岸区", "business_a": "江滩", "location": "114.287570,30.585654", "tel": " ", "fetch_time": "19/1/2025 20:55:52", "大类": "购物服务", "中类": "特色商业街", "小类": "特色商业街|餐饮服务;咖啡厅;咖啡厅", "wgs84经ti": 114.282146, "wgs84纬ti": 30.588094}}]}