{"type": "FeatureCollection", "features": [{"type": "Feature", "id": 17250, "geometry": {"type": "Point", "coordinates": [114.32467300025883, 30.504651999889916]}, "properties": {"OBJECTID": 17250, "poiid": "B0FFGPT6GI", "name": "秀玉coffee&kitchen(南湖店)", "address": "南国城市广场沃尔玛三楼", "type": "餐饮服务;茶艺馆;茶艺馆|餐饮服务;外国餐厅;外国餐厅", "typecode": "050600|050200", "pcode": 420000, "pname": "湖北省", "citycode": 27, "cityname": "武汉市", "adcode": 420106, "adname": "武昌区", "business_a": "红旗", "location": "114.324673,30.504652", "tel": "027-87311995", "fetch_time": "19/1/2025 21:09:16", "大类": "餐饮服务", "中类": "茶艺馆", "小类": "茶艺馆|餐饮服务;外国餐厅;外国餐厅", "wgs84经ti": 114.319206, "wgs84纬ti": 30.507057}}]}