{"type": "FeatureCollection", "features": [{"type": "Feature", "id": 31093, "geometry": {"type": "Point", "coordinates": [114.25848700037488, 30.57314600008789]}, "properties": {"OBJECTID": 31093, "poiid": "B0FFLA05N4", "name": "弘如茶·宴商务会所", "address": "京汉大道111号(第十一初级中学门口、近轻轨1号线崇仁路站)", "type": "餐饮服务;茶艺馆;茶艺馆|生活服务;生活服务场所;生活服务场所", "typecode": "050600|070000", "pcode": 420000, "pname": "湖北省", "citycode": 27, "cityname": "武汉市", "adcode": 420104, "adname": "硚口区", "business_a": "宝丰", "location": "114.258487,30.573146", "tel": "13971110365;027-83800788", "fetch_time": "19/1/2025 22:19:14", "大类": "餐饮服务", "中类": "茶艺馆", "小类": "茶艺馆|生活服务;生活服务场所;生活服务场所", "wgs84经ti": 114.253074, "wgs84纬ti": 30.575615}}, {"type": "Feature", "id": 64627, "geometry": {"type": "Point", "coordinates": [114.31042499971397, 30.54017100019155]}, "properties": {"OBJECTID": 64627, "poiid": "B0HGVKMCVL", "name": "起点人力茶楼", "address": "武珞路阅马场114-1号", "type": "餐饮服务;茶艺馆;茶艺馆|生活服务;生活服务场所;生活服务场所", "typecode": "050600|070000", "pcode": 420000, "pname": "湖北省", "citycode": 27, "cityname": "武汉市", "adcode": 420106, "adname": "武昌区", "business_a": "中南路/中南", "location": "114.310425,30.540171", "tel": " ", "fetch_time": "19/1/2025 12:03:55", "大类": "餐饮服务", "中类": "茶艺馆", "小类": "茶艺馆|生活服务;生活服务场所;生活服务场所", "wgs84经ti": 114.304978, "wgs84纬ti": 30.542591}}]}