{"type": "FeatureCollection", "features": [{"type": "Feature", "id": 424, "geometry": {"type": "Point", "coordinates": [114.36435199994492, 30.576481000098113]}, "properties": {"OBJECTID": 424, "poiid": "B0FFIXKB57", "name": "小米授权服务中心(徐东大街金禾店)", "address": "梨园街道徐东大街191号金禾中心106小米旗舰店", "type": "购物服务;购物相关场所;购物相关场所|生活服务;维修站点;维修站点", "typecode": "060000|071200", "pcode": 420000, "pname": "湖北省", "citycode": 27, "cityname": "武汉市", "adcode": 420111, "adname": "洪山区", "business_a": "东亭", "location": "114.364352,30.576481", "tel": "027-51116575", "fetch_time": "19/1/2025 20:54:55", "大类": "购物服务", "中类": "购物相关场所", "小类": "购物相关场所|生活服务;维修站点;维修站点", "wgs84经ti": 114.358821, "wgs84纬ti": 30.578792}}]}