{"type": "FeatureCollection", "features": [{"type": "Feature", "id": 56975, "geometry": {"type": "Point", "coordinates": [114.26330500042548, 30.433226000279717]}, "properties": {"OBJECTID": 56975, "poiid": "B0FFH7NO3S", "name": "即刻家主题公寓(武汉科技大学黄家湖校区东澜岸广场店)", "address": "白沙洲大道6号东澜岸广场F1", "type": "购物服务;购物相关场所;购物相关场所|住宿服务;住宿服务相关;住宿服务相关", "typecode": "060000|100000", "pcode": 420000, "pname": "湖北省", "citycode": 27, "cityname": "武汉市", "adcode": 420111, "adname": "洪山区", "business_a": " ", "location": "114.263305,30.433226", "tel": "027-86640558;17771868173", "fetch_time": "19/1/2025 23:14:42", "大类": "购物服务", "中类": "购物相关场所", "小类": "购物相关场所|住宿服务;住宿服务相关;住宿服务相关", "wgs84经ti": 114.257905, "wgs84纬ti": 30.435735}}, {"type": "Feature", "id": 170526, "geometry": {"type": "Point", "coordinates": [114.34113500038006, 30.592660999805332]}, "properties": {"OBJECTID": 170526, "poiid": "B0G07S2L87", "name": "无形山居", "address": "徐东大街与武汉大道交叉口北100米", "type": "购物服务;购物相关场所;购物相关场所|住宿服务;住宿服务相关;住宿服务相关", "typecode": "060000|100000", "pcode": 420000, "pname": "湖北省", "citycode": 27, "cityname": "武汉市", "adcode": 420106, "adname": "武昌区", "business_a": "徐东", "location": "114.341135,30.592661", "tel": " ", "fetch_time": "19/1/2025 22:56:52", "大类": "购物服务", "中类": "购物相关场所", "小类": "购物相关场所|住宿服务;住宿服务相关;住宿服务相关", "wgs84经ti": 114.335634, "wgs84纬ti": 30.595004}}]}