{"type": "FeatureCollection", "features": [{"type": "Feature", "id": 32, "geometry": {"type": "Point", "coordinates": [114.25595499962355, 30.6176330002628]}, "properties": {"OBJECTID": 32, "poiid": "B0FFHC9BL7", "name": "汉口站售票处2", "address": "发展大道185号汉口站1F层", "type": "交通设施服务;火车站;售票|生活服务;售票处;火车票代售点", "typecode": "150205|070302", "pcode": 420000, "pname": "湖北省", "citycode": 27, "cityname": "武汉市", "adcode": 420103, "adname": "江汉区", "business_a": "常青", "location": "114.255955,30.617633", "tel": " ", "fetch_time": "19/1/2025 14:56:47", "大类": "交通设施服务", "中类": "火车站", "小类": "售票|生活服务;售票处;火车票代售点", "wgs84经ti": 114.250538, "wgs84纬ti": 30.620085}}, {"type": "Feature", "id": 1925, "geometry": {"type": "Point", "coordinates": [114.25594700015404, 30.617642999824625]}, "properties": {"OBJECTID": 1925, "poiid": "B0FFHC9BL7", "name": "汉口站售票处2", "address": "发展大道185号汉口站1F层", "type": "交通设施服务;火车站;售票|生活服务;售票处;火车票代售点", "typecode": "150205|070302", "pcode": 420000, "pname": "湖北省", "citycode": 27, "cityname": "武汉市", "adcode": 420103, "adname": "江汉区", "business_a": "常青", "location": "114.255947,30.617643", "tel": " ", "fetch_time": "19/1/2025 21:09:37", "大类": "交通设施服务", "中类": "火车站", "小类": "售票|生活服务;售票处;火车票代售点", "wgs84经ti": 114.25053, "wgs84纬ti": 30.620095}}]}