{"type": "FeatureCollection", "features": [{"type": "Feature", "id": 38888, "geometry": {"type": "Point", "coordinates": [114.28056699966737, 30.620667999928287]}, "properties": {"OBJECTID": 38888, "poiid": "B0FFG715S8", "name": "烟酒奶茶店", "address": "俊才街蔡家田-A区", "type": "购物服务;便民商店/便利店;便民商店/便利店|餐饮服务;冷饮店;冷饮店", "typecode": "060200|050700", "pcode": 420000, "pname": "湖北省", "citycode": 27, "cityname": "武汉市", "adcode": 420102, "adname": "江岸区", "business_a": "竹叶山", "location": "114.280567,30.620668", "tel": " ", "fetch_time": "19/1/2025 20:56:30", "大类": "购物服务", "中类": "便民商店/便利店", "小类": "便民商店/便利店|餐饮服务;冷饮店;冷饮店", "wgs84经ti": 114.275146, "wgs84纬ti": 30.623102}}, {"type": "Feature", "id": 40218, "geometry": {"type": "Point", "coordinates": [114.2049439998658, 30.55124800019513]}, "properties": {"OBJECTID": 40218, "poiid": "B0FFHB9C8O", "name": "今天", "address": "十升路与龙阳大道交叉口西100米", "type": "购物服务;便民商店/便利店;便民商店/便利店|餐饮服务;冷饮店;冷饮店", "typecode": "060200|050700", "pcode": 420000, "pname": "湖北省", "citycode": 27, "cityname": "武汉市", "adcode": 420105, "adname": "汉阳区", "business_a": "王家湾", "location": "114.204944,30.551248", "tel": " ", "fetch_time": "19/1/2025 20:38:14", "大类": "购物服务", "中类": "便民商店/便利店", "小类": "便民商店/便利店|餐饮服务;冷饮店;冷饮店", "wgs84经ti": 114.199458, "wgs84纬ti": 30.553691}}, {"type": "Feature", "id": 99334, "geometry": {"type": "Point", "coordinates": [114.39494000038076, 30.623317999825872]}, "properties": {"OBJECTID": 99334, "poiid": "B001B0BA2U", "name": "十九小冷批", "address": "黄州街24附4号", "type": "购物服务;便民商店/便利店;便民商店/便利店|餐饮服务;冷饮店;冷饮店", "typecode": "060200|050700", "pcode": 420000, "pname": "湖北省", "citycode": 27, "cityname": "武汉市", "adcode": 420107, "adname": "青山区", "business_a": "南干渠", "location": "114.394940,30.623318", "tel": "027-86884881", "fetch_time": "19/1/2025 12:03:55", "大类": "购物服务", "中类": "便民商店/便利店", "小类": "便民商店/便利店|餐饮服务;冷饮店;冷饮店", "wgs84经ti": 114.389388, "wgs84纬ti": 30.625583}}, {"type": "Feature", "id": 109687, "geometry": {"type": "Point", "coordinates": [114.2719950000693, 30.616548999736608]}, "properties": {"OBJECTID": 109687, "poiid": "B0FFIL2DM9", "name": "转森便利店", "address": "唐家墩街街道唐家墩地铁站A出口", "type": "购物服务;便民商店/便利店;便民商店/便利店|餐饮服务;冷饮店;冷饮店", "typecode": "060200|050700", "pcode": 420000, "pname": "湖北省", "citycode": 27, "cityname": "武汉市", "adcode": 420103, "adname": "江汉区", "business_a": "新华", "location": "114.271995,30.616549", "tel": " ", "fetch_time": "19/1/2025 12:03:55", "大类": "购物服务", "中类": "便民商店/便利店", "小类": "便民商店/便利店|餐饮服务;冷饮店;冷饮店", "wgs84经ti": 114.266578, "wgs84纬ti": 30.618993}}]}