{"type": "FeatureCollection", "features": [{"type": "Feature", "id": 12841, "geometry": {"type": "Point", "coordinates": [114.13942300007147, 30.625745000231632]}, "properties": {"OBJECTID": 12841, "poiid": "B0G3ZMNQIT", "name": "快宝驿站", "address": "望丰路财政局小区", "type": "购物服务;便民商店/便利店;便民商店/便利店|生活服务;物流速递;物流速递", "typecode": "060200|070500", "pcode": 420000, "pname": "湖北省", "citycode": 27, "cityname": "武汉市", "adcode": 420112, "adname": "东西湖区", "business_a": "吴家山", "location": "114.139423,30.625745", "tel": " ", "fetch_time": "19/1/2025 21:07:58", "大类": "购物服务", "中类": "便民商店/便利店", "小类": "便民商店/便利店|生活服务;物流速递;物流速递", "wgs84经ti": 114.13375, "wgs84纬ti": 30.628045}}, {"type": "Feature", "id": 77738, "geometry": {"type": "Point", "coordinates": [114.38146699960237, 30.88144700007905]}, "properties": {"OBJECTID": 77738, "poiid": "B0HDR1TBZL", "name": "妈妈驿站", "address": "百乐街中央名都东侧", "type": "购物服务;便民商店/便利店;便民商店/便利店|生活服务;物流速递;物流速递", "typecode": "060200|070500", "pcode": 420000, "pname": "湖北省", "citycode": 27, "cityname": "武汉市", "adcode": 420116, "adname": "黄陂区", "business_a": "前川", "location": "114.381467,30.881447", "tel": " ", "fetch_time": "19/1/2025 09:02:52", "大类": "购物服务", "中类": "便民商店/便利店", "小类": "便民商店/便利店|生活服务;物流速递;物流速递", "wgs84经ti": 114.375895, "wgs84纬ti": 30.883588}}]}