{"type": "FeatureCollection", "features": [{"type": "Feature", "id": 12924, "geometry": {"type": "Point", "coordinates": [114.3018590003926, 30.54968400001661]}, "properties": {"OBJECTID": 12924, "poiid": "B0GK0RC1TV", "name": "中国福利彩票(海马巷店)", "address": "楚材巷与楚材街交叉口西北50米", "type": "购物服务;便民商店/便利店;便民商店/便利店|生活服务;彩票彩券销售点;彩票彩券销售点", "typecode": "060200|071800", "pcode": 420000, "pname": "湖北省", "citycode": 27, "cityname": "武汉市", "adcode": 420106, "adname": "武昌区", "business_a": "江滩", "location": "114.301859,30.549684", "tel": "15671555922", "fetch_time": "19/1/2025 21:12:57", "大类": "购物服务", "中类": "便民商店/便利店", "小类": "便民商店/便利店|生活服务;彩票彩券销售点;彩票彩券销售点", "wgs84经ti": 114.296423, "wgs84纬ti": 30.552115}}, {"type": "Feature", "id": 21267, "geometry": {"type": "Point", "coordinates": [114.32509599998048, 30.577160999980208]}, "properties": {"OBJECTID": 21267, "poiid": "B0FFHW2MC2", "name": "中国体育彩票(05310店)", "address": "徐家棚街办事处武昌区车辆厂长航宿舍9栋明红中医足疗馆", "type": "购物服务;便民商店/便利店;便民商店/便利店|生活服务;彩票彩券销售点;彩票彩券销售点", "typecode": "060200|071800", "pcode": 420000, "pname": "湖北省", "citycode": 27, "cityname": "武汉市", "adcode": 420106, "adname": "武昌区", "business_a": "徐家棚", "location": "114.325096,30.577161", "tel": "027-88605302;15671556031", "fetch_time": "19/1/2025 21:16:46", "大类": "购物服务", "中类": "便民商店/便利店", "小类": "便民商店/便利店|生活服务;彩票彩券销售点;彩票彩券销售点", "wgs84经ti": 114.319622, "wgs84纬ti": 30.57954}}, {"type": "Feature", "id": 97565, "geometry": {"type": "Point", "coordinates": [114.21358700004009, 30.56399099968496]}, "properties": {"OBJECTID": 97565, "poiid": "B001B1AHLR", "name": "中国体育彩票(永丰路店)", "address": "永丰街街道沌口经济开发区郭徐岭街贸易三路64号", "type": "购物服务;便民商店/便利店;便民商店/便利店|生活服务;彩票彩券销售点;彩票彩券销售点", "typecode": "060200|071800", "pcode": 420000, "pname": "湖北省", "citycode": 27, "cityname": "武汉市", "adcode": 420105, "adname": "汉阳区", "business_a": " ", "location": "114.213587,30.563991", "tel": " ", "fetch_time": "19/1/2025 12:03:55", "大类": "购物服务", "中类": "便民商店/便利店", "小类": "便民商店/便利店|生活服务;彩票彩券销售点;彩票彩券销售点", "wgs84经ti": 114.208119, "wgs84纬ti": 30.566441}}]}