{"type": "FeatureCollection", "features": [{"type": "Feature", "id": 42478, "geometry": {"type": "Point", "coordinates": [114.03862600038963, 30.57124799979539]}, "properties": {"OBJECTID": 42478, "poiid": "B0FFFFYNTN", "name": "知音尚品", "address": "金家六号9栋", "type": "餐饮服务;休闲餐饮场所;休闲餐饮场所|购物服务;购物相关场所;购物相关场所", "typecode": "050400|060000", "pcode": 420000, "pname": "湖北省", "citycode": 27, "cityname": "武汉市", "adcode": 420114, "adname": "蔡甸区", "business_a": " ", "location": "114.038626,30.571248", "tel": " ", "fetch_time": "19/1/2025 09:19:56", "大类": "餐饮服务", "中类": "休闲餐饮场所", "小类": "休闲餐饮场所|购物服务;购物相关场所;购物相关场所", "wgs84经ti": 114.032931, "wgs84纬ti": 30.573613}}, {"type": "Feature", "id": 62721, "geometry": {"type": "Point", "coordinates": [114.36751400007108, 30.873526999971148]}, "properties": {"OBJECTID": 62721, "poiid": "B0FFFZESRV", "name": "壹号生活馆", "address": "前川街向阳大街301号", "type": "餐饮服务;休闲餐饮场所;休闲餐饮场所|购物服务;购物相关场所;购物相关场所", "typecode": "050400|060000", "pcode": 420000, "pname": "湖北省", "citycode": 27, "cityname": "武汉市", "adcode": 420116, "adname": "黄陂区", "business_a": "前川", "location": "114.367514,30.873527", "tel": "027-85901608", "fetch_time": "19/1/2025 12:03:55", "大类": "餐饮服务", "中类": "休闲餐饮场所", "小类": "休闲餐饮场所|购物服务;购物相关场所;购物相关场所", "wgs84经ti": 114.361953, "wgs84纬ti": 30.875688}}]}