{"type": "FeatureCollection", "features": [{"type": "Feature", "id": 7092, "geometry": {"type": "Point", "coordinates": [114.23668699960535, 31.002344000375388]}, "properties": {"OBJECTID": 7092, "poiid": "B0FFFFYGPF", "name": "黄陂区卫生监督所李家集街派驻所", "address": "李家集街信义街", "type": "政府机构及社会团体;公检法机构;公安警察|政府机构及社会团体;政府机关;乡镇级政府及事业单位", "typecode": "130501|130105", "pcode": 420000, "pname": "湖北省", "citycode": 27, "cityname": "武汉市", "adcode": 420116, "adname": "黄陂区", "business_a": " ", "location": "114.236687,31.002344", "tel": "027-61602110", "fetch_time": "19/1/2025 20:48:23", "大类": "政府机构及社会团体", "中类": "公检法机构", "小类": "公安警察|政府机构及社会团体;政府机关;乡镇级政府及事业单位", "wgs84经ti": 114.231221, "wgs84纬ti": 31.004589}}]}