{"type": "FeatureCollection", "features": [{"type": "Feature", "id": 136, "geometry": {"type": "Point", "coordinates": [114.30308700036483, 30.603932999808137]}, "properties": {"OBJECTID": 136, "poiid": "B0FFGQ4I6C", "name": "长江航务管理局交通运输部环境监测中心站", "address": "解放大道1262号", "type": "政府机构及社会团体;公检法机构;公证鉴定机构|政府机构及社会团体;政府机关;政府机关相关", "typecode": "130505|130100", "pcode": 420000, "pname": "湖北省", "citycode": 27, "cityname": "武汉市", "adcode": 420102, "adname": "江岸区", "business_a": "永清", "location": "114.303087,30.603933", "tel": " ", "fetch_time": "19/1/2025 20:57:32", "大类": "政府机构及社会团体", "中类": "公检法机构", "小类": "公证鉴定机构|政府机构及社会团体;政府机关;政府机关相关", "wgs84经ti": 114.297644, "wgs84纬ti": 30.606342}}, {"type": "Feature", "id": 25053, "geometry": {"type": "Point", "coordinates": [114.0772510000337, 30.30706500004976]}, "properties": {"OBJECTID": 25053, "poiid": "B0FFG24CPA", "name": "中国卫生监督", "address": "纱帽街薇湖路360号", "type": "政府机构及社会团体;公检法机构;公证鉴定机构|政府机构及社会团体;政府机关;政府机关相关", "typecode": "130505|130100", "pcode": 420000, "pname": "湖北省", "citycode": 27, "cityname": "武汉市", "adcode": 420113, "adname": "汉南区", "business_a": "纱帽", "location": "114.077251,30.307065", "tel": " ", "fetch_time": "19/1/2025 12:03:55", "大类": "政府机构及社会团体", "中类": "公检法机构", "小类": "公证鉴定机构|政府机构及社会团体;政府机关;政府机关相关", "wgs84经ti": 114.071532, "wgs84纬ti": 30.309426}}, {"type": "Feature", "id": 27805, "geometry": {"type": "Point", "coordinates": [114.30308700036483, 30.603932999808137]}, "properties": {"OBJECTID": 27805, "poiid": "B0FFGQ4I6C", "name": "长江航务管理局交通运输部环境监测中心站", "address": "解放大道1262号", "type": "政府机构及社会团体;公检法机构;公证鉴定机构|政府机构及社会团体;政府机关;政府机关相关", "typecode": "130505|130100", "pcode": 420000, "pname": "湖北省", "citycode": 27, "cityname": "武汉市", "adcode": 420102, "adname": "江岸区", "business_a": "永清", "location": "114.303087,30.603933", "tel": " ", "fetch_time": "19/1/2025 06:19:04", "大类": "政府机构及社会团体", "中类": "公检法机构", "小类": "公证鉴定机构|政府机构及社会团体;政府机关;政府机关相关", "wgs84经ti": 114.297644, "wgs84纬ti": 30.606342}}, {"type": "Feature", "id": 29449, "geometry": {"type": "Point", "coordinates": [114.0771400003108, 30.30699899970415]}, "properties": {"OBJECTID": 29449, "poiid": "B0FFG24CPA", "name": "中国卫生监督", "address": "纱帽街薇湖路360号", "type": "政府机构及社会团体;公检法机构;公证鉴定机构|政府机构及社会团体;政府机关;政府机关相关", "typecode": "130505|130100", "pcode": 420000, "pname": "湖北省", "citycode": 27, "cityname": "武汉市", "adcode": 420113, "adname": "汉南区", "business_a": "纱帽", "location": "114.077140,30.306999", "tel": " ", "fetch_time": "19/1/2025 06:24:10", "大类": "政府机构及社会团体", "中类": "公检法机构", "小类": "公证鉴定机构|政府机构及社会团体;政府机关;政府机关相关", "wgs84经ti": 114.071421, "wgs84纬ti": 30.30936}}]}