{"type": "FeatureCollection", "features": [{"type": "Feature", "id": 2660, "geometry": {"type": "Point", "coordinates": [114.27566999957094, 30.551463000217325]}, "properties": {"OBJECTID": 2660, "poiid": "B0G31DXFI1", "name": "汉阳仲裁", "address": "汉阳大道10号", "type": "政府机构及社会团体;公检法机构;公证鉴定机构|政府机构及社会团体;政府机关;区县级政府及事业单位", "typecode": "130505|130104", "pcode": 420000, "pname": "湖北省", "citycode": 27, "cityname": "武汉市", "adcode": 420105, "adname": "汉阳区", "business_a": "建桥", "location": "114.275670,30.551463", "tel": "027-84762367", "fetch_time": "19/1/2025 21:27:23", "大类": "政府机构及社会团体", "中类": "公检法机构", "小类": "公证鉴定机构|政府机构及社会团体;政府机关;区县级政府及事业单位", "wgs84经ti": 114.270258, "wgs84纬ti": 30.553929}}, {"type": "Feature", "id": 15919, "geometry": {"type": "Point", "coordinates": [114.30431500033706, 30.522783999681906]}, "properties": {"OBJECTID": 15919, "poiid": "B001B0ITGX", "name": "武汉市武昌区质量技术监督检验所", "address": "汇文新都C区8-1-102室", "type": "政府机构及社会团体;公检法机构;公证鉴定机构|政府机构及社会团体;政府机关;区县级政府及事业单位", "typecode": "130505|130104", "pcode": 420000, "pname": "湖北省", "citycode": 27, "cityname": "武汉市", "adcode": 420106, "adname": "武昌区", "business_a": "紫阳路", "location": "114.304315,30.522784", "tel": " ", "fetch_time": "19/1/2025 20:55:41", "大类": "政府机构及社会团体", "中类": "公检法机构", "小类": "公证鉴定机构|政府机构及社会团体;政府机关;区县级政府及事业单位", "wgs84经ti": 114.298878, "wgs84纬ti": 30.52522}}]}