{"type": "FeatureCollection", "features": [{"type": "Feature", "id": 4606, "geometry": {"type": "Point", "coordinates": [114.53718799962655, 30.626294000367864]}, "properties": {"OBJECTID": 4606, "poiid": "B0FFGIAQ1U", "name": "(武汉化工区)化工园区安全生产应急服务中心", "address": "化工大道附近", "type": "政府机构及社会团体;公检法机构;消防机关|政府机构及社会团体;政府机关;政府机关相关", "typecode": "130504|130100", "pcode": 420000, "pname": "湖北省", "citycode": 27, "cityname": "武汉市", "adcode": 420111, "adname": "洪山区", "business_a": " ", "location": "114.537188,30.626294", "tel": "027-59901119", "fetch_time": "19/1/2025 20:57:31", "大类": "政府机构及社会团体", "中类": "公检法机构", "小类": "消防机关|政府机构及社会团体;政府机关;政府机关相关", "wgs84经ti": 114.532024, "wgs84纬ti": 30.628845}}, {"type": "Feature", "id": 15966, "geometry": {"type": "Point", "coordinates": [114.32703000013441, 30.554428000252074]}, "properties": {"OBJECTID": 15966, "poiid": "B0FFI27XEF", "name": "湖北省消防救援指挥中心", "address": "公正路小湖口特1号", "type": "政府机构及社会团体;公检法机构;消防机关|政府机构及社会团体;政府机关;政府机关相关", "typecode": "130504|130100", "pcode": 420000, "pname": "湖北省", "citycode": 27, "cityname": "武汉市", "adcode": 420106, "adname": "武昌区", "business_a": "小东门", "location": "114.327030,30.554428", "tel": " ", "fetch_time": "19/1/2025 20:55:55", "大类": "政府机构及社会团体", "中类": "公检法机构", "小类": "消防机关|政府机构及社会团体;政府机关;政府机关相关", "wgs84经ti": 114.321555, "wgs84纬ti": 30.556812}}, {"type": "Feature", "id": 27301, "geometry": {"type": "Point", "coordinates": [114.40567199976306, 30.50073600006641]}, "properties": {"OBJECTID": 27301, "poiid": "B0G0DS6UM4", "name": "武汉东湖新技术开发区关山消防救援站", "address": "珞雄路27号", "type": "政府机构及社会团体;公检法机构;消防机关|政府机构及社会团体;政府机关;政府机关相关", "typecode": "130504|130100", "pcode": 420000, "pname": "湖北省", "citycode": 27, "cityname": "武汉市", "adcode": 420111, "adname": "洪山区", "business_a": "关山", "location": "114.405672,30.500736", "tel": " ", "fetch_time": "19/1/2025 04:50:56", "大类": "政府机构及社会团体", "中类": "公检法机构", "小类": "消防机关|政府机构及社会团体;政府机关;政府机关相关", "wgs84经ti": 114.400135, "wgs84纬ti": 30.503043}}]}