{"type": "FeatureCollection", "features": [{"type": "Feature", "id": 16432, "geometry": {"type": "Point", "coordinates": [114.22412999969981, 30.63295900015777]}, "properties": {"OBJECTID": 16432, "poiid": "B0FFIFOMZ8", "name": "湖北煜嘉消防", "address": "金南一路129-130号附近", "type": "政府机构及社会团体;公检法机构;消防机关|公司企业;公司;公司", "typecode": "130504|170200", "pcode": 420000, "pname": "湖北省", "citycode": 27, "cityname": "武汉市", "adcode": 420112, "adname": "东西湖区", "business_a": " ", "location": "114.224130,30.632959", "tel": " ", "fetch_time": "19/1/2025 20:42:13", "大类": "政府机构及社会团体", "中类": "公检法机构", "小类": "消防机关|公司企业;公司;公司", "wgs84经ti": 114.218677, "wgs84纬ti": 30.635394}}]}