{"type": "FeatureCollection", "features": [{"type": "Feature", "id": 56929, "geometry": {"type": "Point", "coordinates": [114.02863900028967, 30.53598300041517]}, "properties": {"OBJECTID": 56929, "poiid": "B0FFF0282V", "name": "华林超市(长大店)", "address": "蔡甸街华林村华林公寓商铺27号", "type": "购物服务;超级市场;超市|购物服务;便民商店/便利店;便民商店/便利店|生活服务;生活服务场所;生活服务场所", "typecode": "060400|060200|070000", "pcode": 420000, "pname": "湖北省", "citycode": 27, "cityname": "武汉市", "adcode": 420114, "adname": "蔡甸区", "business_a": " ", "location": "114.028639,30.535983", "tel": "027-69111799", "fetch_time": "19/1/2025 23:14:36", "大类": "购物服务", "中类": "超级市场", "小类": "超市|购物服务;便民商店/便利店;便民商店/便利店|生活服务;生活服务场所;生活服务场所", "wgs84经ti": 114.022969, "wgs84纬ti": 30.538386}}]}