{"type": "FeatureCollection", "features": [{"type": "Feature", "id": 102659, "geometry": {"type": "Point", "coordinates": [114.3544009997064, 30.563650000147447]}, "properties": {"OBJECTID": 102659, "poiid": "B0FFJWHFIS", "name": "武汉人才创新创业超市", "address": "水果湖街街道中北路148号", "type": "购物服务;超级市场;超市|生活服务;人才市场;人才市场", "typecode": "060400|070800", "pcode": 420000, "pname": "湖北省", "citycode": 27, "cityname": "武汉市", "adcode": 420106, "adname": "武昌区", "business_a": "中北路", "location": "114.354401,30.563650", "tel": " ", "fetch_time": "19/1/2025 12:03:55", "大类": "购物服务", "中类": "超级市场", "小类": "超市|生活服务;人才市场;人才市场", "wgs84经ti": 114.348883, "wgs84纬ti": 30.565981}}]}