{"type": "FeatureCollection", "features": [{"type": "Feature", "id": 9436, "geometry": {"type": "Point", "coordinates": [114.20492099970443, 30.64121200033361]}, "properties": {"OBJECTID": 9436, "poiid": "B0FFJTPE3Q", "name": "海棠汇国际商务会馆", "address": "金银湖路20号", "type": "生活服务;洗浴推拿场所;洗浴推拿场所|住宿服务;旅馆招待所;旅馆招待所", "typecode": "071400|100200", "pcode": 420000, "pname": "湖北省", "citycode": 27, "cityname": "武汉市", "adcode": 420112, "adname": "东西湖区", "business_a": "金银湖", "location": "114.204921,30.641212", "tel": "027-83916666", "fetch_time": "19/1/2025 21:05:24", "大类": "生活服务", "中类": "洗浴推拿场所", "小类": "洗浴推拿场所|住宿服务;旅馆招待所;旅馆招待所", "wgs84经ti": 114.199427, "wgs84纬ti": 30.64362}}]}