{"type": "FeatureCollection", "features": [{"type": "Feature", "id": 7700, "geometry": {"type": "Point", "coordinates": [114.37147200003278, 30.608945999858065]}, "properties": {"OBJECTID": 7700, "poiid": "B0FFGCDRDP", "name": "玉明堂(园林路站店)", "address": "钢都花园管理委员会园林路绿景花园73附3号", "type": "生活服务;洗浴推拿场所;洗浴推拿场所|购物服务;专卖店;专营店", "typecode": "071400|061200", "pcode": 420000, "pname": "湖北省", "citycode": 27, "cityname": "武汉市", "adcode": 420107, "adname": "青山区", "business_a": "钢都", "location": "114.371472,30.608946", "tel": " ", "fetch_time": "19/1/2025 20:47:20", "大类": "生活服务", "中类": "洗浴推拿场所", "小类": "洗浴推拿场所|购物服务;专卖店;专营店", "wgs84经ti": 114.365931, "wgs84纬ti": 30.611235}}, {"type": "Feature", "id": 7719, "geometry": {"type": "Point", "coordinates": [114.39852400018253, 30.61906999998058]}, "properties": {"OBJECTID": 7719, "poiid": "B0FFFU3YMV", "name": "鑫沁缘", "address": "友谊大道东方红青山客运公交车站", "type": "生活服务;洗浴推拿场所;洗浴推拿场所|购物服务;专卖店;专营店", "typecode": "071400|061200", "pcode": 420000, "pname": "湖北省", "citycode": 27, "cityname": "武汉市", "adcode": 420107, "adname": "青山区", "business_a": "南干渠", "location": "114.398524,30.619070", "tel": " ", "fetch_time": "19/1/2025 20:47:44", "大类": "生活服务", "中类": "洗浴推拿场所", "小类": "洗浴推拿场所|购物服务;专卖店;专营店", "wgs84经ti": 114.392973, "wgs84纬ti": 30.621336}}]}