{"type": "FeatureCollection", "features": [{"type": "Feature", "id": 72912, "geometry": {"type": "Point", "coordinates": [114.31492600043464, 30.693587000040054]}, "properties": {"OBJECTID": 72912, "poiid": "B0FFI30QO4", "name": "桃源行(汉北康城店)", "address": "盘龙城经济开发区刘店汉北康城7栋", "type": "生活服务;洗浴推拿场所;洗浴推拿场所|购物服务;购物相关场所;购物相关场所|体育休闲服务;体育休闲服务场所;体育休闲服务场所", "typecode": "071400|060000|080000", "pcode": 420000, "pname": "湖北省", "citycode": 27, "cityname": "武汉市", "adcode": 420116, "adname": "黄陂区", "business_a": " ", "location": "114.314926,30.693587", "tel": " ", "fetch_time": "19/1/2025 12:03:55", "大类": "生活服务", "中类": "洗浴推拿场所", "小类": "洗浴推拿场所|购物服务;购物相关场所;购物相关场所|体育休闲服务;体育休闲服务场所;体育休闲服务场所", "wgs84经ti": 114.309459, "wgs84纬ti": 30.695936}}]}