{"type": "FeatureCollection", "features": [{"type": "Feature", "id": 12690, "geometry": {"type": "Point", "coordinates": [114.2177600000241, 30.77330399977984]}, "properties": {"OBJECTID": 12690, "poiid": "B0FFJ96Y21", "name": "缘林港湾足道(武汉天河国际机场T3航站楼)", "address": "机场大道武汉天河国际机场T3航站楼F2层", "type": "生活服务;洗浴推拿场所;洗浴推拿场所|餐饮服务;茶艺馆;茶艺馆", "typecode": "071400|050600", "pcode": 420000, "pname": "湖北省", "citycode": 27, "cityname": "武汉市", "adcode": 420116, "adname": "黄陂区", "business_a": "天河", "location": "114.217760,30.773304", "tel": " ", "fetch_time": "19/1/2025 20:49:37", "大类": "生活服务", "中类": "洗浴推拿场所", "小类": "洗浴推拿场所|餐饮服务;茶艺馆;茶艺馆", "wgs84经ti": 114.212283, "wgs84纬ti": 30.775665}}]}