{"type": "FeatureCollection", "features": [{"type": "Feature", "id": 59180, "geometry": {"type": "Point", "coordinates": [114.27326400013351, 30.601140999657446]}, "properties": {"OBJECTID": 59180, "poiid": "B0FFIBQ5KT", "name": "8号铭邸", "address": "北湖正街6号2栋", "type": "生活服务;洗浴推拿场所;洗浴推拿场所|餐饮服务;休闲餐饮场所;休闲餐饮场所", "typecode": "071400|050400", "pcode": 420000, "pname": "湖北省", "citycode": 27, "cityname": "武汉市", "adcode": 420103, "adname": "江汉区", "business_a": "新华路", "location": "114.273264,30.601141", "tel": " ", "fetch_time": "19/1/2025 12:03:55", "大类": "生活服务", "中类": "洗浴推拿场所", "小类": "洗浴推拿场所|餐饮服务;休闲餐饮场所;休闲餐饮场所", "wgs84经ti": 114.267848, "wgs84纬ti": 30.60359}}]}