{"type": "FeatureCollection", "features": [{"type": "Feature", "id": 10574, "geometry": {"type": "Point", "coordinates": [114.03491900031167, 30.577559000347662]}, "properties": {"OBJECTID": 10574, "poiid": "B0G0Z7ZL9C", "name": "天尔宝婴儿游泳馆", "address": "汉阳大街123号-9", "type": "生活服务;婴儿服务场所;婴儿游泳馆|购物服务;购物相关场所;购物相关场所", "typecode": "072001|060000", "pcode": 420000, "pname": "湖北省", "citycode": 27, "cityname": "武汉市", "adcode": 420114, "adname": "蔡甸区", "business_a": " ", "location": "114.034919,30.577559", "tel": "15342351138", "fetch_time": "19/1/2025 21:25:55", "大类": "生活服务", "中类": "婴儿服务场所", "小类": "婴儿游泳馆|购物服务;购物相关场所;购物相关场所", "wgs84经ti": 114.029231, "wgs84纬ti": 30.579931}}]}