{"type": "FeatureCollection", "features": [{"type": "Feature", "id": 2390, "geometry": {"type": "Point", "coordinates": [114.27202699974634, 30.592744000035623]}, "properties": {"OBJECTID": 2390, "poiid": "B001B0J6PQ", "name": "新华明珠地下停车场(出入口)", "address": "红松巷16附近", "type": "交通设施服务;停车场;停车场出入口|交通设施服务;停车场;公共停车场", "typecode": "150909|150904", "pcode": 420000, "pname": "湖北省", "citycode": 27, "cityname": "武汉市", "adcode": 420103, "adname": "江汉区", "business_a": "西北湖", "location": "114.272027,30.592744", "tel": " ", "fetch_time": "19/1/2025 21:09:58", "大类": "交通设施服务", "中类": "停车场", "小类": "停车场出入口|交通设施服务;停车场;公共停车场", "wgs84经ti": 114.266612, "wgs84纬ti": 30.595198}}]}