{"type": "FeatureCollection", "features": [{"type": "Feature", "id": 35654, "geometry": {"type": "Point", "coordinates": [114.17561499993235, 30.61225499956862]}, "properties": {"OBJECTID": 35654, "poiid": "B0FFL04GLB", "name": "8号车库", "address": "长丰大道30号附近", "type": "交通设施服务;停车场;停车场相关|汽车服务;汽车服务相关;汽车服务相关", "typecode": "150900|010000", "pcode": 420000, "pname": "湖北省", "citycode": 27, "cityname": "武汉市", "adcode": 420104, "adname": "硚口区", "business_a": " ", "location": "114.175615,30.612255", "tel": " ", "fetch_time": "19/1/2025 12:03:55", "大类": "交通设施服务", "中类": "停车场", "小类": "停车场相关|汽车服务;汽车服务相关;汽车服务相关", "wgs84经ti": 114.170044, "wgs84纬ti": 30.614624}}]}