{"type": "FeatureCollection", "features": [{"type": "Feature", "id": 36917, "geometry": {"type": "Point", "coordinates": [114.34967100011659, 30.544474999921363]}, "properties": {"OBJECTID": 36917, "poiid": "B0FFG1WW4S", "name": "桃山村停车场(出口)", "address": "洪山路62附2号附近", "type": "交通设施服务;停车场;公共停车场|交通设施服务;停车场;停车场出口", "typecode": "150904|150908", "pcode": 420000, "pname": "湖北省", "citycode": 27, "cityname": "武汉市", "adcode": 420106, "adname": "武昌区", "business_a": "水果湖", "location": "114.349671,30.544475", "tel": " ", "fetch_time": "19/1/2025 12:03:55", "大类": "交通设施服务", "中类": "停车场", "小类": "公共停车场|交通设施服务;停车场;停车场出口", "wgs84经ti": 114.344161, "wgs84纬ti": 30.54682}}]}