{"type": "FeatureCollection", "features": [{"type": "Feature", "id": 3664, "geometry": {"type": "Point", "coordinates": [114.44695399962745, 30.42852300013641]}, "properties": {"OBJECTID": 3664, "poiid": "B0FFG3XWPF", "name": "腾飞达汽车美护·维修服务专家", "address": "梁山头社区三期门面15栋4号", "type": "汽车维修;汽车综合维修;汽车综合维修|汽车服务;汽车养护/装饰;汽车养护|汽车服务;洗车场;洗车场", "typecode": "030100|010400|010500", "pcode": 420000, "pname": "湖北省", "citycode": 27, "cityname": "武汉市", "adcode": 420115, "adname": "江夏区", "business_a": "藏龙岛", "location": "114.446954,30.428523", "tel": "15002766885", "fetch_time": "19/1/2025 21:30:50", "大类": "汽车维修", "中类": "汽车综合维修", "小类": "汽车综合维修|汽车服务;汽车养护/装饰;汽车养护|汽车服务;洗车场;洗车场", "wgs84经ti": 114.441492, "wgs84纬ti": 30.430893}}]}