{"type": "FeatureCollection", "features": [{"type": "Feature", "id": 383, "geometry": {"type": "Point", "coordinates": [114.18057999956739, 30.591501000271023]}, "properties": {"OBJECTID": 383, "poiid": "B0FFH0T9DJ", "name": "盛德世通", "address": "沿河大道633附1号", "type": "汽车维修;汽车综合维修;汽车综合维修|公司企业;公司;公司", "typecode": "030100|170200", "pcode": 420000, "pname": "湖北省", "citycode": 27, "cityname": "武汉市", "adcode": 420104, "adname": "硚口区", "business_a": "古田", "location": "114.180580,30.591501", "tel": "13720309618", "fetch_time": "19/1/2025 20:54:19", "大类": "汽车维修", "中类": "汽车综合维修", "小类": "汽车综合维修|公司企业;公司;公司", "wgs84经ti": 114.175025, "wgs84纬ti": 30.593888}}, {"type": "Feature", "id": 2096, "geometry": {"type": "Point", "coordinates": [114.2187859996742, 30.481665000139685]}, "properties": {"OBJECTID": 2096, "poiid": "B0FFHZ6V7S", "name": "武汉轨道交通6号线老关村车辆综合维修基地", "address": "江堤街办事处蔡旬经济开发区", "type": "汽车维修;汽车综合维修;汽车综合维修|公司企业;公司;公司", "typecode": "030100|170200", "pcode": 420000, "pname": "湖北省", "citycode": 27, "cityname": "武汉市", "adcode": 420114, "adname": "蔡甸区", "business_a": " ", "location": "114.218786,30.481665", "tel": " ", "fetch_time": "19/1/2025 21:23:46", "大类": "汽车维修", "中类": "汽车综合维修", "小类": "汽车综合维修|公司企业;公司;公司", "wgs84经ti": 114.213336, "wgs84纬ti": 30.484147}}, {"type": "Feature", "id": 5355, "geometry": {"type": "Point", "coordinates": [114.38087099999666, 30.719743000239305]}, "properties": {"OBJECTID": 5355, "poiid": "B0FFF01NVA", "name": "宏达汽修", "address": "汉口北大道19号一汽特约维修站", "type": "汽车维修;汽车综合维修;汽车综合维修|公司企业;公司;公司", "typecode": "030100|170200", "pcode": 420000, "pname": "湖北省", "citycode": 27, "cityname": "武汉市", "adcode": 420116, "adname": "黄陂区", "business_a": "长江新区", "location": "114.380871,30.719743", "tel": " ", "fetch_time": "19/1/2025 03:29:37", "大类": "汽车维修", "中类": "汽车综合维修", "小类": "汽车综合维修|公司企业;公司;公司", "wgs84经ti": 114.375314, "wgs84纬ti": 30.721972}}]}