{"type": "FeatureCollection", "features": [{"type": "Feature", "id": 28624, "geometry": {"type": "Point", "coordinates": [114.08553299974824, 30.313628999678656]}, "properties": {"OBJECTID": 28624, "poiid": "B0FFG77V52", "name": "中国邮政(纱帽邮政所)", "address": "纱帽邮局院里", "type": "生活服务;邮局;邮局|公司企业;公司;公司", "typecode": "070400|170200", "pcode": 420000, "pname": "湖北省", "citycode": 27, "cityname": "武汉市", "adcode": 420113, "adname": "汉南区", "business_a": "纱帽", "location": "114.085533,30.313629", "tel": "027-84737203", "fetch_time": "19/1/2025 21:19:30", "大类": "生活服务", "中类": "邮局", "小类": "邮局|公司企业;公司;公司", "wgs84经ti": 114.079813, "wgs84纬ti": 30.315983}}, {"type": "Feature", "id": 33846, "geometry": {"type": "Point", "coordinates": [114.29753999997104, 30.540047999915316]}, "properties": {"OBJECTID": 33846, "poiid": "B0FFH28M3H", "name": "中国邮政(武昌邮局)", "address": "彭刘杨路215号", "type": "生活服务;邮局;邮局|公司企业;公司;公司", "typecode": "070400|170200", "pcode": 420000, "pname": "湖北省", "citycode": 27, "cityname": "武汉市", "adcode": 420106, "adname": "武昌区", "business_a": "江滩", "location": "114.297540,30.540048", "tel": "11185", "fetch_time": "19/1/2025 20:53:56", "大类": "生活服务", "中类": "邮局", "小类": "邮局|公司企业;公司;公司", "wgs84经ti": 114.29211, "wgs84纬ti": 30.54249}}]}