{"type": "FeatureCollection", "features": [{"type": "Feature", "id": 2916, "geometry": {"type": "Point", "coordinates": [114.18941899978711, 30.481668000278034]}, "properties": {"OBJECTID": 2916, "poiid": "B0KDF13HVI", "name": "武汉元合汽车", "address": "江城大道与滨湖西路交叉口西320米", "type": "汽车销售;大众特约销售;上海大众销售|汽车维修;大众特约维修;大众维修", "typecode": "020101|030200", "pcode": 420000, "pname": "湖北省", "citycode": 27, "cityname": "武汉市", "adcode": 420114, "adname": "蔡甸区", "business_a": "沌口", "location": "114.189419,30.481668", "tel": " ", "fetch_time": "19/1/2025 04:52:27", "大类": "汽车销售", "中类": "大众特约销售", "小类": "上海大众销售|汽车维修;大众特约维修;大众维修", "wgs84经ti": 114.183898, "wgs84纬ti": 30.484107}}]}