{"type": "FeatureCollection", "features": [{"type": "Feature", "id": 681, "geometry": {"type": "Point", "coordinates": [114.30247199988298, 30.660473000028958]}, "properties": {"OBJECTID": 681, "poiid": "B0H3L5KODZ", "name": "武汉鸿鹄至诚大众直营店", "address": "金桥大道1号", "type": "汽车销售;大众特约销售;大众销售", "typecode": "020100", "pcode": 420000, "pname": "湖北省", "citycode": 27, "cityname": "武汉市", "adcode": 420102, "adname": "江岸区", "business_a": "后湖", "location": "114.302472,30.660473", "tel": "13080669654", "fetch_time": "19/1/2025 21:11:18", "大类": "汽车销售", "中类": "大众特约销售", "小类": "大众销售", "wgs84经ti": 114.297025, "wgs84纬ti": 30.662859}}, {"type": "Feature", "id": 3221, "geometry": {"type": "Point", "coordinates": [114.30253400004415, 30.660489999913636]}, "properties": {"OBJECTID": 3221, "poiid": "B0H3L5KODZ", "name": "武汉鸿鹄至诚大众直营店", "address": "金桥大道1号(市民之家地铁站G口步行340米)", "type": "汽车销售;大众特约销售;大众销售", "typecode": "020100", "pcode": 420000, "pname": "湖北省", "citycode": 27, "cityname": "武汉市", "adcode": 420102, "adname": "江岸区", "business_a": "后湖", "location": "114.302534,30.660490", "tel": "13080669654", "fetch_time": "19/1/2025 07:13:30", "大类": "汽车销售", "中类": "大众特约销售", "小类": "大众销售", "wgs84经ti": 114.297087, "wgs84纬ti": 30.662876}}, {"type": "Feature", "id": 3418, "geometry": {"type": "Point", "coordinates": [114.20127199960314, 30.620950000342305]}, "properties": {"OBJECTID": 3418, "poiid": "B0FFL9CXBH", "name": "大众", "address": "古田二路蓝焰物流园", "type": "汽车销售;大众特约销售;大众销售", "typecode": "020100", "pcode": 420000, "pname": "湖北省", "citycode": 27, "cityname": "武汉市", "adcode": 420104, "adname": "硚口区", "business_a": "金银湖", "location": "114.201272,30.620950", "tel": "027-83888857;13006385326", "fetch_time": "19/1/2025 06:31:12", "大类": "汽车销售", "中类": "大众特约销售", "小类": "大众销售", "wgs84经ti": 114.195771, "wgs84纬ti": 30.623361}}]}