{"type": "FeatureCollection", "features": [{"type": "Feature", "id": 692, "geometry": {"type": "Point", "coordinates": [114.2874359998716, 30.667050000257348]}, "properties": {"OBJECTID": 692, "poiid": "B0G2M10TJI", "name": "上汽大众斯柯达武汉捷科(金银潭店)", "address": "银潭路(武汉医疗救治中心正对面)", "type": "汽车销售;大众特约销售;斯柯达销售|汽车维修;汽车维修;汽车维修", "typecode": "020103|030000", "pcode": 420000, "pname": "湖北省", "citycode": 27, "cityname": "武汉市", "adcode": 420112, "adname": "东西湖区", "business_a": " ", "location": "114.287436,30.667050", "tel": "027-88138866", "fetch_time": "19/1/2025 21:11:24", "大类": "汽车销售", "中类": "大众特约销售", "小类": "斯柯达销售|汽车维修;汽车维修;汽车维修", "wgs84经ti": 114.282006, "wgs84纬ti": 30.669456}}]}