{"type": "FeatureCollection", "features": [{"type": "Feature", "id": 2283, "geometry": {"type": "Point", "coordinates": [114.40266699968231, 30.45783100000068]}, "properties": {"OBJECTID": 2283, "poiid": "B0FFGBNYMP", "name": "武汉三环瀚通汽车销售服务有限公司", "address": "关山大道大学园路10号", "type": "汽车销售;大众特约销售;斯柯达销售", "typecode": "020103", "pcode": 420000, "pname": "湖北省", "citycode": 27, "cityname": "武汉市", "adcode": 420115, "adname": "江夏区", "business_a": " ", "location": "114.402667,30.457831", "tel": "027-81811333", "fetch_time": "19/1/2025 12:03:55", "大类": "汽车销售", "中类": "大众特约销售", "小类": "斯柯达销售", "wgs84经ti": 114.397132, "wgs84纬ti": 30.46015}}, {"type": "Feature", "id": 2732, "geometry": {"type": "Point", "coordinates": [114.27604499977701, 30.629027999642517]}, "properties": {"OBJECTID": 2732, "poiid": "B0G0PACJS4", "name": "上汽大众(兴业路店)", "address": "兴业路108号", "type": "汽车销售;大众特约销售;斯柯达销售", "typecode": "020103", "pcode": 420000, "pname": "湖北省", "citycode": 27, "cityname": "武汉市", "adcode": 420102, "adname": "江岸区", "business_a": "后湖", "location": "114.276045,30.629028", "tel": " ", "fetch_time": "19/1/2025 03:28:20", "大类": "汽车销售", "中类": "大众特约销售", "小类": "斯柯达销售", "wgs84经ti": 114.270626, "wgs84纬ti": 30.631463}}, {"type": "Feature", "id": 2904, "geometry": {"type": "Point", "coordinates": [114.20764100013207, 30.557096000080378]}, "properties": {"OBJECTID": 2904, "poiid": "B0LB9CP97W", "name": "武汉友芝友汽车贸易服务有限公司", "address": "龙阳大道46附1号(王家湾地铁站E口步行250米)", "type": "汽车销售;大众特约销售;斯柯达销售", "typecode": "020103", "pcode": 420000, "pname": "湖北省", "citycode": 27, "cityname": "武汉市", "adcode": 420105, "adname": "汉阳区", "business_a": "王家湾", "location": "114.207641,30.557096", "tel": "027-84872991", "fetch_time": "19/1/2025 04:48:42", "大类": "汽车销售", "中类": "大众特约销售", "小类": "斯柯达销售", "wgs84经ti": 114.202161, "wgs84纬ti": 30.559541}}, {"type": "Feature", "id": 3810, "geometry": {"type": "Point", "coordinates": [114.32324500005677, 30.477984000361403]}, "properties": {"OBJECTID": 3810, "poiid": "B0H2R41P7C", "name": "上汽斯柯达", "address": "狮子山西街与野芷湖西路交叉口西240米", "type": "汽车销售;大众特约销售;斯柯达销售", "typecode": "020103", "pcode": 420000, "pname": "湖北省", "citycode": 27, "cityname": "武汉市", "adcode": 420111, "adname": "洪山区", "business_a": " ", "location": "114.323245,30.477984", "tel": " ", "fetch_time": "19/1/2025 07:04:27", "大类": "汽车销售", "中类": "大众特约销售", "小类": "斯柯达销售", "wgs84经ti": 114.317783, "wgs84纬ti": 30.480399}}]}