{"type": "FeatureCollection", "features": [{"type": "Feature", "id": 30789, "geometry": {"type": "Point", "coordinates": [114.26107400006515, 30.623849000031385]}, "properties": {"OBJECTID": 30789, "poiid": "B0FFKU9JSQ", "name": "最后防线", "address": "常青一路京华时代3栋一层5室", "type": "餐饮服务;冷饮店;冷饮店|购物服务;便民商店/便利店;便民商店/便利店", "typecode": "050700|060200", "pcode": 420000, "pname": "湖北省", "citycode": 27, "cityname": "武汉市", "adcode": 420103, "adname": "江汉区", "business_a": "汉兴", "location": "114.261074,30.623849", "tel": "17320513812", "fetch_time": "19/1/2025 22:09:21", "大类": "餐饮服务", "中类": "冷饮店", "小类": "冷饮店|购物服务;便民商店/便利店;便民商店/便利店", "wgs84经ti": 114.255658, "wgs84纬ti": 30.626297}}]}