{"type": "FeatureCollection", "features": [{"type": "Feature", "id": 3172, "geometry": {"type": "Point", "coordinates": [114.29070599958231, 30.578608000159136]}, "properties": {"OBJECTID": 3172, "poiid": "B0FFGJN70J", "name": "肯德基甜品站(启新店)", "address": "中山大道818号新佳丽时尚广场b1层F座F2", "type": "餐饮服务;冷饮店;冷饮店|餐饮服务;快餐厅;快餐厅", "typecode": "050700|050300", "pcode": 420000, "pname": "湖北省", "citycode": 27, "cityname": "武汉市", "adcode": 420103, "adname": "江汉区", "business_a": "江滩", "location": "114.290706,30.578608", "tel": " ", "fetch_time": "19/1/2025 21:04:52", "大类": "餐饮服务", "中类": "冷饮店", "小类": "冷饮店|餐饮服务;快餐厅;快餐厅", "wgs84经ti": 114.28528, "wgs84纬ti": 30.581046}}, {"type": "Feature", "id": 27261, "geometry": {"type": "Point", "coordinates": [114.36931300029482, 30.514030999830823]}, "properties": {"OBJECTID": 27261, "poiid": "B0FFHKZRXO", "name": "1点点(虎泉店)", "address": "卓刀泉特1号虎泉广场1层1号", "type": "餐饮服务;冷饮店;冷饮店|餐饮服务;快餐厅;快餐厅", "typecode": "050700|050300", "pcode": 420000, "pname": "湖北省", "citycode": 27, "cityname": "武汉市", "adcode": 420111, "adname": "洪山区", "business_a": "卓刀泉", "location": "114.369313,30.514031", "tel": "027-65388633", "fetch_time": "19/1/2025 21:20:30", "大类": "餐饮服务", "中类": "冷饮店", "小类": "冷饮店|餐饮服务;快餐厅;快餐厅", "wgs84经ti": 114.363782, "wgs84纬ti": 30.516356}}, {"type": "Feature", "id": 66903, "geometry": {"type": "Point", "coordinates": [114.29847700001358, 30.54807300036873]}, "properties": {"OBJECTID": 66903, "poiid": "B0FFK858HD", "name": "老万成酸梅汤(户部巷店)", "address": "中华路街街道自由路45号", "type": "餐饮服务;冷饮店;冷饮店|餐饮服务;快餐厅;快餐厅", "typecode": "050700|050300", "pcode": 420000, "pname": "湖北省", "citycode": 27, "cityname": "武汉市", "adcode": 420106, "adname": "武昌区", "business_a": "江滩", "location": "114.298477,30.548073", "tel": " ", "fetch_time": "19/1/2025 12:03:55", "大类": "餐饮服务", "中类": "冷饮店", "小类": "冷饮店|餐饮服务;快餐厅;快餐厅", "wgs84经ti": 114.293045, "wgs84纬ti": 30.55051}}, {"type": "Feature", "id": 79166, "geometry": {"type": "Point", "coordinates": [114.2169450002117, 30.805033999819273]}, "properties": {"OBJECTID": 79166, "poiid": "B0FFLAI8XS", "name": "CoCo", "address": "中兴路天河街道航天小学东南侧约100米", "type": "餐饮服务;冷饮店;冷饮店|餐饮服务;快餐厅;快餐厅", "typecode": "050700|050300", "pcode": 420000, "pname": "湖北省", "citycode": 27, "cityname": "武汉市", "adcode": 420116, "adname": "黄陂区", "business_a": " ", "location": "114.216945,30.805034", "tel": " ", "fetch_time": "19/1/2025 12:03:55", "大类": "餐饮服务", "中类": "冷饮店", "小类": "冷饮店|餐饮服务;快餐厅;快餐厅", "wgs84经ti": 114.211463, "wgs84纬ti": 30.807377}}]}