{"type": "FeatureCollection", "features": [{"type": "Feature", "id": 89118, "geometry": {"type": "Point", "coordinates": [114.39657300014392, 30.335581000263005]}, "properties": {"OBJECTID": 89118, "poiid": "B0FFFZ2U0S", "name": "王记榨油厂", "address": "五里界镇界山路13号", "type": "购物服务;综合市场;农副产品市场|公司企业;工厂;工厂", "typecode": "060703|170300", "pcode": 420000, "pname": "湖北省", "citycode": 27, "cityname": "武汉市", "adcode": 420115, "adname": "江夏区", "business_a": " ", "location": "114.396573,30.335581", "tel": "15347077121;13367280985", "fetch_time": "19/1/2025 09:17:21", "大类": "购物服务", "中类": "综合市场", "小类": "农副产品市场|公司企业;工厂;工厂", "wgs84经ti": 114.391047, "wgs84纬ti": 30.337925}}, {"type": "Feature", "id": 89120, "geometry": {"type": "Point", "coordinates": [114.31270200039705, 30.36229400006812]}, "properties": {"OBJECTID": 89120, "poiid": "B0FFHVIC4G", "name": "八分山油厂", "address": "武昌大道1243号(富丽畅馨园正对面)", "type": "购物服务;综合市场;农副产品市场|公司企业;工厂;工厂", "typecode": "060703|170300", "pcode": 420000, "pname": "湖北省", "citycode": 27, "cityname": "武汉市", "adcode": 420115, "adname": "江夏区", "business_a": "纸坊", "location": "114.312702,30.362294", "tel": "15971444726", "fetch_time": "19/1/2025 09:17:24", "大类": "购物服务", "中类": "综合市场", "小类": "农副产品市场|公司企业;工厂;工厂", "wgs84经ti": 114.307267, "wgs84纬ti": 30.364754}}, {"type": "Feature", "id": 175982, "geometry": {"type": "Point", "coordinates": [114.17893300005801, 30.892466000105856]}, "properties": {"OBJECTID": 175982, "poiid": "B0G0XAZFNF", "name": "廖岗榨油厂", "address": "110省道与078乡道交叉口东北40米", "type": "购物服务;综合市场;农副产品市场|公司企业;工厂;工厂", "typecode": "060703|170300", "pcode": 420000, "pname": "湖北省", "citycode": 27, "cityname": "武汉市", "adcode": 420116, "adname": "黄陂区", "business_a": " ", "location": "114.178933,30.892466", "tel": " ", "fetch_time": "19/1/2025 23:14:27", "大类": "购物服务", "中类": "综合市场", "小类": "农副产品市场|公司企业;工厂;工厂", "wgs84经ti": 114.173347, "wgs84纬ti": 30.894699}}]}