{"type": "FeatureCollection", "features": [{"type": "Feature", "id": 21365, "geometry": {"type": "Point", "coordinates": [114.26865399978237, 30.603411000017672]}, "properties": {"OBJECTID": 21365, "poiid": "B0FFG6J88P", "name": "好又鲜(北湖西路店)", "address": "北湖公寓1栋1层12号", "type": "购物服务;综合市场;果品市场|购物服务;综合市场;蔬菜市场", "typecode": "060704|060705", "pcode": 420000, "pname": "湖北省", "citycode": 27, "cityname": "武汉市", "adcode": 420103, "adname": "江汉区", "business_a": "新华", "location": "114.268654,30.603411", "tel": "13997926630", "fetch_time": "19/1/2025 21:21:09", "大类": "购物服务", "中类": "综合市场", "小类": "果品市场|购物服务;综合市场;蔬菜市场", "wgs84经ti": 114.263239, "wgs84纬ti": 30.605863}}, {"type": "Feature", "id": 130934, "geometry": {"type": "Point", "coordinates": [114.20840899957568, 30.61217200023765]}, "properties": {"OBJECTID": 130934, "poiid": "B0FFHI0CBQ", "name": "好又鲜(团结佳兴园店)", "address": "天顺园小区2栋3单元1层2号房", "type": "购物服务;综合市场;果品市场|购物服务;综合市场;蔬菜市场", "typecode": "060704|060705", "pcode": 420000, "pname": "湖北省", "citycode": 27, "cityname": "武汉市", "adcode": 420104, "adname": "硚口区", "business_a": "古田", "location": "114.208409,30.612172", "tel": " ", "fetch_time": "19/1/2025 12:03:55", "大类": "购物服务", "中类": "综合市场", "小类": "果品市场|购物服务;综合市场;蔬菜市场", "wgs84经ti": 114.202926, "wgs84纬ti": 30.614597}}]}