{"type": "FeatureCollection", "features": [{"type": "Feature", "id": 9447, "geometry": {"type": "Point", "coordinates": [114.39780700039285, 30.635466999802247]}, "properties": {"OBJECTID": 9447, "poiid": "B0FFG8RYQN", "name": "曾氏海鲜店", "address": "红钢城20街青山生鲜市场", "type": "购物服务;综合市场;水产海鲜市场|餐饮服务;餐饮相关场所;餐饮相关", "typecode": "060706|050000", "pcode": 420000, "pname": "湖北省", "citycode": 27, "cityname": "武汉市", "adcode": 420107, "adname": "青山区", "business_a": "冶金", "location": "114.397807,30.635467", "tel": "13006133936;15307189017", "fetch_time": "19/1/2025 20:46:41", "大类": "购物服务", "中类": "综合市场", "小类": "水产海鲜市场|餐饮服务;餐饮相关场所;餐饮相关", "wgs84经ti": 114.392255, "wgs84纬ti": 30.637726}}, {"type": "Feature", "id": 28726, "geometry": {"type": "Point", "coordinates": [114.80041400020605, 30.839875000331062]}, "properties": {"OBJECTID": 28726, "poiid": "B0G2RXILL5", "name": "潜江怡品汇龙虾新洲直销点", "address": "南安街与古城大道交叉口东140米", "type": "购物服务;综合市场;水产海鲜市场|餐饮服务;餐饮相关场所;餐饮相关", "typecode": "060706|050000", "pcode": 420000, "pname": "湖北省", "citycode": 27, "cityname": "武汉市", "adcode": 420117, "adname": "新洲区", "business_a": "邾城", "location": "114.800414,30.839875", "tel": " ", "fetch_time": "19/1/2025 21:09:03", "大类": "购物服务", "中类": "综合市场", "小类": "水产海鲜市场|餐饮服务;餐饮相关场所;餐饮相关", "wgs84经ti": 114.795184, "wgs84纬ti": 30.842254}}, {"type": "Feature", "id": 76670, "geometry": {"type": "Point", "coordinates": [113.85458100001324, 30.25985800034647]}, "properties": {"OBJECTID": 76670, "poiid": "B0G0ALWIEO", "name": "龙虾螃蟹各种鱼类", "address": "康泰路与晨曦路交叉口南220米", "type": "购物服务;综合市场;水产海鲜市场|餐饮服务;餐饮相关场所;餐饮相关", "typecode": "060706|050000", "pcode": 420000, "pname": "湖北省", "citycode": 27, "cityname": "武汉市", "adcode": 420113, "adname": "汉南区", "business_a": " ", "location": "113.854581,30.259858", "tel": " ", "fetch_time": "19/1/2025 08:42:38", "大类": "购物服务", "中类": "综合市场", "小类": "水产海鲜市场|餐饮服务;餐饮相关场所;餐饮相关", "wgs84经ti": 113.849065, "wgs84纬ti": 30.262544}}, {"type": "Feature", "id": 128368, "geometry": {"type": "Point", "coordinates": [114.35553299974822, 30.513463999763815]}, "properties": {"OBJECTID": 128368, "poiid": "B0FFFLIHTH", "name": "霞浦海带", "address": "珞桂路与美满路交叉口东80米", "type": "购物服务;综合市场;水产海鲜市场|餐饮服务;餐饮相关场所;餐饮相关", "typecode": "060706|050000", "pcode": 420000, "pname": "湖北省", "citycode": 27, "cityname": "武汉市", "adcode": 420111, "adname": "洪山区", "business_a": "陈家湾", "location": "114.355533,30.513464", "tel": " ", "fetch_time": "19/1/2025 12:03:55", "大类": "购物服务", "中类": "综合市场", "小类": "水产海鲜市场|餐饮服务;餐饮相关场所;餐饮相关", "wgs84经ti": 114.350018, "wgs84纬ti": 30.515809}}]}