{"type": "FeatureCollection", "features": [{"type": "Feature", "id": 9078, "geometry": {"type": "Point", "coordinates": [114.37170800012416, 30.61683000010447]}, "properties": {"OBJECTID": 9078, "poiid": "B0FFGXY9ZF", "name": "建一综合市场", "address": "红卫路街道建设一路58街", "type": "购物服务;综合市场;综合市场|政府机构及社会团体;政府及社会团体相关;政府及社会团体相关", "typecode": "060700|130000", "pcode": 420000, "pname": "湖北省", "citycode": 27, "cityname": "武汉市", "adcode": 420107, "adname": "青山区", "business_a": "建二", "location": "114.371708,30.616830", "tel": " ", "fetch_time": "19/1/2025 20:46:12", "大类": "购物服务", "中类": "综合市场", "小类": "综合市场|政府机构及社会团体;政府及社会团体相关;政府及社会团体相关", "wgs84经ti": 114.366166, "wgs84纬ti": 30.619115}}]}