{"type": "FeatureCollection", "features": [{"type": "Feature", "id": 40972, "geometry": {"type": "Point", "coordinates": [114.3803749996066, 30.629697999962787]}, "properties": {"OBJECTID": 40972, "poiid": "B0FFGA62JX", "name": "天惠佳市场", "address": "钢都花园街道友谊大道武汉市普仁医院对门", "type": "购物服务;综合市场;综合市场|公司企业;公司;公司", "typecode": "060700|170200", "pcode": 420000, "pname": "湖北省", "citycode": 27, "cityname": "武汉市", "adcode": 420107, "adname": "青山区", "business_a": "八大家", "location": "114.380375,30.629698", "tel": " ", "fetch_time": "19/1/2025 21:14:32", "大类": "购物服务", "中类": "综合市场", "小类": "综合市场|公司企业;公司;公司", "wgs84经ti": 114.374826, "wgs84纬ti": 30.631969}}]}