{"type": "FeatureCollection", "features": [{"type": "Feature", "id": 29897, "geometry": {"type": "Point", "coordinates": [114.29009900036863, 30.58330299993355]}, "properties": {"OBJECTID": 29897, "poiid": "B001B1FJHH", "name": "保成路夜市", "address": "保成路与江汉二路交叉口西北50米", "type": "购物服务;综合市场;综合市场|生活服务;生活服务场所;生活服务场所", "typecode": "060700|070000", "pcode": 420000, "pname": "湖北省", "citycode": 27, "cityname": "武汉市", "adcode": 420102, "adname": "江岸区", "business_a": "江滩", "location": "114.290099,30.583303", "tel": " ", "fetch_time": "19/1/2025 20:42:50", "大类": "购物服务", "中类": "综合市场", "小类": "综合市场|生活服务;生活服务场所;生活服务场所", "wgs84经ti": 114.284673, "wgs84纬ti": 30.58574}}, {"type": "Feature", "id": 138933, "geometry": {"type": "Point", "coordinates": [114.36805299974617, 30.514002000292123]}, "properties": {"OBJECTID": 138933, "poiid": "B0FFL7BY8H", "name": "宝业卓刀泉综合市场", "address": "虎泉街80号", "type": "购物服务;综合市场;综合市场|生活服务;生活服务场所;生活服务场所", "typecode": "060700|070000", "pcode": 420000, "pname": "湖北省", "citycode": 27, "cityname": "武汉市", "adcode": 420111, "adname": "洪山区", "business_a": "陈家湾", "location": "114.368053,30.514002", "tel": "027-85885870", "fetch_time": "19/1/2025 12:03:55", "大类": "购物服务", "中类": "综合市场", "小类": "综合市场|生活服务;生活服务场所;生活服务场所", "wgs84经ti": 114.362523, "wgs84纬ti": 30.516329}}]}