{"type": "FeatureCollection", "features": [{"type": "Feature", "id": 105961, "geometry": {"type": "Point", "coordinates": [114.31246000002909, 30.405193999903247]}, "properties": {"OBJECTID": 105961, "poiid": "B0FFIKY7EW", "name": "佰品优菜", "address": "文化大道与新华街交汇处俪湖天地小区4号楼底商第14、15号商铺", "type": "购物服务;综合市场;蔬菜市场|购物服务;专卖店;专营店", "typecode": "060705|061200", "pcode": 420000, "pname": "湖北省", "citycode": 27, "cityname": "武汉市", "adcode": 420115, "adname": "江夏区", "business_a": "大花岭", "location": "114.312460,30.405194", "tel": " ", "fetch_time": "19/1/2025 12:03:55", "大类": "购物服务", "中类": "综合市场", "小类": "蔬菜市场|购物服务;专卖店;专营店", "wgs84经ti": 114.307021, "wgs84纬ti": 30.407646}}]}