{"type": "FeatureCollection", "features": [{"type": "Feature", "id": 1632, "geometry": {"type": "Point", "coordinates": [114.31416999974579, 30.650672000412555]}, "properties": {"OBJECTID": 1632, "poiid": "B0FFJ2ZXT5", "name": "华庭蔬果超市", "address": "后湖街街道万锦江城对面", "type": "购物服务;综合市场;蔬菜市场|购物服务;超级市场;超市", "typecode": "060705|060400", "pcode": 420000, "pname": "湖北省", "citycode": 27, "cityname": "武汉市", "adcode": 420102, "adname": "江岸区", "business_a": "后湖", "location": "114.314170,30.650672", "tel": " ", "fetch_time": "19/1/2025 21:01:27", "大类": "购物服务", "中类": "综合市场", "小类": "蔬菜市场|购物服务;超级市场;超市", "wgs84经ti": 114.308707, "wgs84纬ti": 30.653042}}, {"type": "Feature", "id": 118911, "geometry": {"type": "Point", "coordinates": [114.24000499973101, 30.565470999587035]}, "properties": {"OBJECTID": 118911, "poiid": "B0FFG84CHP", "name": "菜夫人(华润中央公园店)", "address": "华润置地中央公园一期A-2层02号", "type": "购物服务;综合市场;蔬菜市场|购物服务;超级市场;超市", "typecode": "060705|060400", "pcode": 420000, "pname": "湖北省", "citycode": 27, "cityname": "武汉市", "adcode": 420105, "adname": "汉阳区", "business_a": "七里庙", "location": "114.240005,30.565471", "tel": "15337277779", "fetch_time": "19/1/2025 12:03:55", "大类": "购物服务", "中类": "综合市场", "小类": "蔬菜市场|购物服务;超级市场;超市", "wgs84经ti": 114.234581, "wgs84纬ti": 30.567942}}]}