{"type": "FeatureCollection", "features": [{"type": "Feature", "id": 5894, "geometry": {"type": "Point", "coordinates": [114.24554899998645, 30.59976800019308]}, "properties": {"OBJECTID": 5894, "poiid": "B0HG4URQ4Z", "name": "医普茂轰脂工场(泛海cbd店)", "address": "泛海国际SOHO城1号楼602号", "type": "医疗保健服务;医药保健销售店;医疗保健用品|生活服务;美容美发店;美容美发店", "typecode": "090602|071100", "pcode": 420000, "pname": "湖北省", "citycode": 27, "cityname": "武汉市", "adcode": 420103, "adname": "江汉区", "business_a": " ", "location": "114.245549,30.599768", "tel": "18040559161", "fetch_time": "19/1/2025 21:15:42", "大类": "医疗保健服务", "中类": "医药保健销售店", "小类": "医疗保健用品|生活服务;美容美发店;美容美发店", "wgs84经ti": 114.240127, "wgs84纬ti": 30.602228}}, {"type": "Feature", "id": 20116, "geometry": {"type": "Point", "coordinates": [114.3937969998317, 30.505400000209875]}, "properties": {"OBJECTID": 20116, "poiid": "B0FFHFU1S9", "name": "灰指甲(甲美天下光谷店)", "address": "虎泉街709所后门467附107(奥康国际隔壁)灰指甲门面", "type": "医疗保健服务;医药保健销售店;医疗保健用品|生活服务;美容美发店;美容美发店", "typecode": "090602|071100", "pcode": 420000, "pname": "湖北省", "citycode": 27, "cityname": "武汉市", "adcode": 420111, "adname": "洪山区", "business_a": "关山", "location": "114.393797,30.505400", "tel": "13871489105", "fetch_time": "19/1/2025 12:03:55", "大类": "医疗保健服务", "中类": "医药保健销售店", "小类": "医疗保健用品|生活服务;美容美发店;美容美发店", "wgs84经ti": 114.388255, "wgs84纬ti": 30.507707}}]}