{"type": "FeatureCollection", "features": [{"type": "Feature", "id": 1085, "geometry": {"type": "Point", "coordinates": [114.26027700018346, 30.565034000119056]}, "properties": {"OBJECTID": 1085, "poiid": "B0FFGD5S2E", "name": "御顺汽车养护", "address": "沿河大道253号", "type": "汽车服务;汽车养护/装饰;汽车养护|餐饮服务;餐饮相关场所;餐饮相关", "typecode": "010400|050000", "pcode": 420000, "pname": "湖北省", "citycode": 27, "cityname": "武汉市", "adcode": 420104, "adname": "硚口区", "business_a": "汉中", "location": "114.260277,30.565034", "tel": "027-83322595;15926201116", "fetch_time": "19/1/2025 21:12:42", "大类": "汽车服务", "中类": "汽车养护/装饰", "小类": "汽车养护|餐饮服务;餐饮相关场所;餐饮相关", "wgs84经ti": 114.254866, "wgs84纬ti": 30.567505}}, {"type": "Feature", "id": 17394, "geometry": {"type": "Point", "coordinates": [114.26020200032212, 30.56504399968088]}, "properties": {"OBJECTID": 17394, "poiid": "B0FFGD5S2E", "name": "御顺汽车养护", "address": "沿河大道253号", "type": "汽车服务;汽车养护/装饰;汽车养护|餐饮服务;餐饮相关场所;餐饮相关", "typecode": "010400|050000", "pcode": 420000, "pname": "湖北省", "citycode": 27, "cityname": "武汉市", "adcode": 420104, "adname": "硚口区", "business_a": "汉中", "location": "114.260202,30.565044", "tel": "027-83322595;15107144591", "fetch_time": "19/1/2025 06:32:10", "大类": "汽车服务", "中类": "汽车养护/装饰", "小类": "汽车养护|餐饮服务;餐饮相关场所;餐饮相关", "wgs84经ti": 114.254791, "wgs84纬ti": 30.567515}}]}