{"type": "FeatureCollection", "features": [{"type": "Feature", "id": 8203, "geometry": {"type": "Point", "coordinates": [114.23459900044361, 30.621461999671624]}, "properties": {"OBJECTID": 8203, "poiid": "B0FFI0WT2Q", "name": "瑞昌行", "address": "江发路9号", "type": "汽车服务;汽车养护/装饰;汽车养护|购物服务;购物相关场所;购物相关场所", "typecode": "010400|060000", "pcode": 420000, "pname": "湖北省", "citycode": 27, "cityname": "武汉市", "adcode": 420103, "adname": "江汉区", "business_a": "常青", "location": "114.234599,30.621462", "tel": "13807173057", "fetch_time": "19/1/2025 21:07:36", "大类": "汽车服务", "中类": "汽车养护/装饰", "小类": "汽车养护|购物服务;购物相关场所;购物相关场所", "wgs84经ti": 114.229163, "wgs84纬ti": 30.623909}}, {"type": "Feature", "id": 10691, "geometry": {"type": "Point", "coordinates": [114.44717900011085, 30.43809600003044]}, "properties": {"OBJECTID": 10691, "poiid": "B0FFL0PXC0", "name": "壹嘉壹", "address": "流芳一路佛祖岭A区邮政储蓄南50米", "type": "汽车服务;汽车养护/装饰;汽车养护|购物服务;购物相关场所;购物相关场所", "typecode": "010400|060000", "pcode": 420000, "pname": "湖北省", "citycode": 27, "cityname": "武汉市", "adcode": 420115, "adname": "江夏区", "business_a": "藏龙岛", "location": "114.447179,30.438096", "tel": "17771732896", "fetch_time": "19/1/2025 23:33:06", "大类": "汽车服务", "中类": "汽车养护/装饰", "小类": "汽车养护|购物服务;购物相关场所;购物相关场所", "wgs84经ti": 114.441717, "wgs84纬ti": 30.440464}}, {"type": "Feature", "id": 17107, "geometry": {"type": "Point", "coordinates": [114.23459900044361, 30.621461999671624]}, "properties": {"OBJECTID": 17107, "poiid": "B0FFI0WT2Q", "name": "瑞昌行", "address": "江发路9号", "type": "汽车服务;汽车养护/装饰;汽车养护|购物服务;购物相关场所;购物相关场所", "typecode": "010400|060000", "pcode": 420000, "pname": "湖北省", "citycode": 27, "cityname": "武汉市", "adcode": 420103, "adname": "江汉区", "business_a": "常青", "location": "114.234599,30.621462", "tel": "13807173057", "fetch_time": "19/1/2025 06:22:26", "大类": "汽车服务", "中类": "汽车养护/装饰", "小类": "汽车养护|购物服务;购物相关场所;购物相关场所", "wgs84经ti": 114.229163, "wgs84纬ti": 30.623909}}]}