{"type": "FeatureCollection", "features": [{"type": "Feature", "id": 19394, "geometry": {"type": "Point", "coordinates": [114.29820600010692, 30.597344999971824]}, "properties": {"OBJECTID": 19394, "poiid": "B0FFI13RLH", "name": "花半里", "address": "球场街街道球场街办事处球场街融科天城三期", "type": "商务住宅;楼宇;商务写字楼|购物服务;特色商业街;特色商业街|商务住宅;住宅区;住宅区", "typecode": "120201|061000|120300", "pcode": 420000, "pname": "湖北省", "citycode": 27, "cityname": "武汉市", "adcode": 420102, "adname": "江岸区", "business_a": "劳动", "location": "114.298206,30.597345", "tel": " ", "fetch_time": "19/1/2025 07:18:51", "大类": "商务住宅", "中类": "楼宇", "小类": "商务写字楼|购物服务;特色商业街;特色商业街|商务住宅;住宅区;住宅区", "wgs84经ti": 114.29277, "wgs84纬ti": 30.599765}}]}