{"type": "FeatureCollection", "features": [{"type": "Feature", "id": 20016, "geometry": {"type": "Point", "coordinates": [114.19539400013309, 30.566696000320235]}, "properties": {"OBJECTID": 20016, "poiid": "B0FFILGURS", "name": "安邦大厦", "address": "永丰街街道汉阳大道792号", "type": "商务住宅;楼宇;商务写字楼|购物服务;家电电子卖场;手机销售", "typecode": "120201|060305", "pcode": 420000, "pname": "湖北省", "citycode": 27, "cityname": "武汉市", "adcode": 420105, "adname": "汉阳区", "business_a": "王家湾", "location": "114.195394,30.566696", "tel": " ", "fetch_time": "19/1/2025 06:44:52", "大类": "商务住宅", "中类": "楼宇", "小类": "商务写字楼|购物服务;家电电子卖场;手机销售", "wgs84经ti": 114.189882, "wgs84纬ti": 30.569118}}]}