{"type": "FeatureCollection", "features": [{"type": "Feature", "id": 3980, "geometry": {"type": "Point", "coordinates": [114.15817100039146, 30.48767999963235]}, "properties": {"OBJECTID": 3980, "poiid": "B0FFIMHGVG", "name": "武汉建工科技中心", "address": "武汉经济技术开发区沌阳大道409号", "type": "商务住宅;楼宇;商务写字楼|科教文化服务;科研机构;科研机构|公司企业;公司;公司", "typecode": "120201|141300|170200", "pcode": 420000, "pname": "湖北省", "citycode": 27, "cityname": "武汉市", "adcode": 420114, "adname": "蔡甸区", "business_a": "沌口", "location": "114.158171,30.48768", "tel": "027-84782655", "fetch_time": "19/1/2025 21:24:41", "大类": "商务住宅", "中类": "楼宇", "小类": "商务写字楼|科教文化服务;科研机构;科研机构|公司企业;公司;公司", "wgs84经ti": 114.15256, "wgs84纬ti": 30.49006}}, {"type": "Feature", "id": 21119, "geometry": {"type": "Point", "coordinates": [114.15817699976878, 30.48762499979398]}, "properties": {"OBJECTID": 21119, "poiid": "B0FFIMHGVG", "name": "武汉建工科技中心", "address": "沌阳大道409号", "type": "商务住宅;楼宇;商务写字楼|科教文化服务;科研机构;科研机构|公司企业;公司;公司", "typecode": "120201|141300|170200", "pcode": 420000, "pname": "湖北省", "citycode": 27, "cityname": "武汉市", "adcode": 420114, "adname": "蔡甸区", "business_a": "沌口", "location": "114.158177,30.487625", "tel": "027-84782655", "fetch_time": "19/1/2025 06:32:49", "大类": "商务住宅", "中类": "楼宇", "小类": "商务写字楼|科教文化服务;科研机构;科研机构|公司企业;公司;公司", "wgs84经ti": 114.152566, "wgs84纬ti": 30.490005}}]}