{"type": "FeatureCollection", "features": [{"type": "Feature", "id": 8985, "geometry": {"type": "Point", "coordinates": [114.25468899969769, 30.61341099981786]}, "properties": {"OBJECTID": 8985, "poiid": "B001B1DFIY", "name": "中共兴城大厦联合总支委员会", "address": "发展大道176号兴城大厦B座", "type": "商务住宅;楼宇;商务写字楼|政府机构及社会团体;社会团体;社会团体相关", "typecode": "120201|130400", "pcode": 420000, "pname": "湖北省", "citycode": 27, "cityname": "武汉市", "adcode": 420103, "adname": "江汉区", "business_a": "常青", "location": "114.254689,30.613411", "tel": "027-65681126", "fetch_time": "19/1/2025 22:12:57", "大类": "商务住宅", "中类": "楼宇", "小类": "商务写字楼|政府机构及社会团体;社会团体;社会团体相关", "wgs84经ti": 114.249272, "wgs84纬ti": 30.615865}}]}