{"type": "FeatureCollection", "features": [{"type": "Feature", "id": 42083, "geometry": {"type": "Point", "coordinates": [114.328930999666, 30.34756699991715]}, "properties": {"OBJECTID": 42083, "poiid": "B0FFFE4YDR", "name": "伟燕科技", "address": "江夏大道108号", "type": "生活服务;维修站点;维修站点|购物服务;家电电子卖场;数码电子", "typecode": "071200|060306", "pcode": 420000, "pname": "湖北省", "citycode": 27, "cityname": "武汉市", "adcode": 420115, "adname": "江夏区", "business_a": "纸坊", "location": "114.328931,30.347567", "tel": "027-86636020", "fetch_time": "19/1/2025 23:33:52", "大类": "生活服务", "中类": "维修站点", "小类": "维修站点|购物服务;家电电子卖场;数码电子", "wgs84经ti": 114.323471, "wgs84纬ti": 30.349998}}]}