{"type": "FeatureCollection", "features": [{"type": "Feature", "id": 27910, "geometry": {"type": "Point", "coordinates": [114.05687200004286, 30.628050000407256]}, "properties": {"OBJECTID": 27910, "poiid": "B0FFKZKSFW", "name": "八方汽修冷机维修", "address": "高桥三路万国汽配城", "type": "生活服务;维修站点;维修站点|汽车维修;汽车综合维修;汽车综合维修", "typecode": "071200|030100", "pcode": 420000, "pname": "湖北省", "citycode": 27, "cityname": "武汉市", "adcode": 420112, "adname": "东西湖区", "business_a": " ", "location": "114.056872,30.628050", "tel": " ", "fetch_time": "19/1/2025 20:59:55", "大类": "生活服务", "中类": "维修站点", "小类": "维修站点|汽车维修;汽车综合维修;汽车综合维修", "wgs84经ti": 114.051141, "wgs84纬ti": 30.630354}}, {"type": "Feature", "id": 29080, "geometry": {"type": "Point", "coordinates": [114.31278199958967, 30.357282000064288]}, "properties": {"OBJECTID": 29080, "poiid": "B0FFFV8OEA", "name": "小付修配", "address": "北华街与徐家巷交叉口西北50米", "type": "生活服务;维修站点;维修站点|汽车维修;汽车综合维修;汽车综合维修", "typecode": "071200|030100", "pcode": 420000, "pname": "湖北省", "citycode": 27, "cityname": "武汉市", "adcode": 420115, "adname": "江夏区", "business_a": "纸坊", "location": "114.312782,30.357282", "tel": " ", "fetch_time": "19/1/2025 21:31:01", "大类": "生活服务", "中类": "维修站点", "小类": "维修站点|汽车维修;汽车综合维修;汽车综合维修", "wgs84经ti": 114.307347, "wgs84纬ti": 30.359742}}]}