{"type": "FeatureCollection", "features": [{"type": "Feature", "id": 27637, "geometry": {"type": "Point", "coordinates": [114.27638400012154, 30.599719999778245]}, "properties": {"OBJECTID": 27637, "poiid": "B0FFGCDVRG", "name": "共青团小蓝鲸健康美食管理公司委员会", "address": "黄孝北路32-44号附近", "type": "政府机构及社会团体;社会团体;共青团|公司企业;公司企业;公司企业", "typecode": "130401|170000", "pcode": 420000, "pname": "湖北省", "citycode": 27, "cityname": "武汉市", "adcode": 420103, "adname": "江汉区", "business_a": "建设大道", "location": "114.276384,30.599720", "tel": " ", "fetch_time": "19/1/2025 06:22:57", "大类": "政府机构及社会团体", "中类": "社会团体", "小类": "共青团|公司企业;公司企业;公司企业", "wgs84经ti": 114.270967, "wgs84纬ti": 30.602167}}]}