{"type": "FeatureCollection", "features": [{"type": "Feature", "id": 2389, "geometry": {"type": "Point", "coordinates": [114.22558600029379, 30.563328999733585]}, "properties": {"OBJECTID": 2389, "poiid": "B0HAPZSW01", "name": "汉阳区职工服务中心", "address": "玫瑰街31号", "type": "政府机构及社会团体;社会团体;慈善机构|生活服务;生活服务场所;生活服务场所", "typecode": "130408|070000", "pcode": 420000, "pname": "湖北省", "citycode": 27, "cityname": "武汉市", "adcode": 420105, "adname": "汉阳区", "business_a": " ", "location": "114.225586,30.563329", "tel": "027-84595991", "fetch_time": "19/1/2025 21:27:14", "大类": "政府机构及社会团体", "中类": "社会团体", "小类": "慈善机构|生活服务;生活服务场所;生活服务场所", "wgs84经ti": 114.220142, "wgs84纬ti": 30.565792}}, {"type": "Feature", "id": 6703, "geometry": {"type": "Point", "coordinates": [114.31589800029258, 30.28508199983446]}, "properties": {"OBJECTID": 6703, "poiid": "B001B1615R", "name": "武汉市江夏区残疾人托养服务中心", "address": "101乡道南50米", "type": "政府机构及社会团体;社会团体;慈善机构|生活服务;生活服务场所;生活服务场所", "typecode": "130408|070000", "pcode": 420000, "pname": "湖北省", "citycode": 27, "cityname": "武汉市", "adcode": 420115, "adname": "江夏区", "business_a": " ", "location": "114.315898,30.285082", "tel": " ", "fetch_time": "19/1/2025 20:37:07", "大类": "政府机构及社会团体", "中类": "社会团体", "小类": "慈善机构|生活服务;生活服务场所;生活服务场所", "wgs84经ti": 114.310464, "wgs84纬ti": 30.287546}}, {"type": "Feature", "id": 6726, "geometry": {"type": "Point", "coordinates": [114.31320900039509, 30.31424600025275]}, "properties": {"OBJECTID": 6726, "poiid": "B0FFLG9AP2", "name": "武汉市农村留守儿童关爱服务站", "address": " ", "type": "政府机构及社会团体;社会团体;慈善机构|生活服务;生活服务场所;生活服务场所", "typecode": "130408|070000", "pcode": 420000, "pname": "湖北省", "citycode": 27, "cityname": "武汉市", "adcode": 420115, "adname": "江夏区", "business_a": " ", "location": "114.313209,30.314246", "tel": " ", "fetch_time": "19/1/2025 20:37:13", "大类": "政府机构及社会团体", "中类": "社会团体", "小类": "慈善机构|生活服务;生活服务场所;生活服务场所", "wgs84经ti": 114.307777, "wgs84纬ti": 30.316712}}]}