{"type": "FeatureCollection", "features": [{"type": "Feature", "id": 10929, "geometry": {"type": "Point", "coordinates": [114.41834300042922, 30.96267700034332]}, "properties": {"OBJECTID": 10929, "poiid": "B001B0K676", "name": "武汉市黄陂区王家河供销合作社", "address": "顺河大街王家河东方小区西南侧约40米", "type": "政府机构及社会团体;社会团体;行业协会|购物服务;超级市场;超市", "typecode": "130407|060400", "pcode": 420000, "pname": "湖北省", "citycode": 27, "cityname": "武汉市", "adcode": 420116, "adname": "黄陂区", "business_a": " ", "location": "114.418343,30.962677", "tel": " ", "fetch_time": "19/1/2025 20:53:43", "大类": "政府机构及社会团体", "中类": "社会团体", "小类": "行业协会|购物服务;超级市场;超市", "wgs84经ti": 114.412778, "wgs84纬ti": 30.964767}}]}