{"type": "FeatureCollection", "features": [{"type": "Feature", "id": 7694, "geometry": {"type": "Point", "coordinates": [114.43707800014965, 30.275283000310253]}, "properties": {"OBJECTID": 7694, "poiid": "B0FFKPPBQU", "name": "小朱湾品悦居农庄", "address": "五里界童周岭村小朱湾18号", "type": "住宿服务;住宿服务相关;住宿服务相关|餐饮服务;中餐厅;中餐厅", "typecode": "100000|050100", "pcode": 420000, "pname": "湖北省", "citycode": 27, "cityname": "武汉市", "adcode": 420115, "adname": "江夏区", "business_a": " ", "location": "114.437078,30.275283", "tel": "13971534314;17362931319", "fetch_time": "19/1/2025 21:34:46", "大类": "住宿服务", "中类": "住宿服务相关", "小类": "住宿服务相关|餐饮服务;中餐厅;中餐厅", "wgs84经ti": 114.431606, "wgs84纬ti": 30.27766}}]}