{"type": "FeatureCollection", "features": [{"type": "Feature", "id": 534, "geometry": {"type": "Point", "coordinates": [114.26942999959488, 30.57293000001954]}, "properties": {"OBJECTID": 534, "poiid": "B0HAOKHGP0", "name": "白玉兰武汉武胜路地铁站店", "address": "武胜路荣东社区8栋", "type": "住宿服务;住宿服务相关;住宿服务相关|餐饮服务;餐饮相关场所;餐饮相关", "typecode": "100000|050000", "pcode": 420000, "pname": "湖北省", "citycode": 27, "cityname": "武汉市", "adcode": 420104, "adname": "硚口区", "business_a": "江滩", "location": "114.269430,30.572930", "tel": "027-59300559", "fetch_time": "19/1/2025 21:16:59", "大类": "住宿服务", "中类": "住宿服务相关", "小类": "住宿服务相关|餐饮服务;餐饮相关场所;餐饮相关", "wgs84经ti": 114.264018, "wgs84纬ti": 30.575393}}, {"type": "Feature", "id": 17431, "geometry": {"type": "Point", "coordinates": [114.26947599991752, 30.57294699990416]}, "properties": {"OBJECTID": 17431, "poiid": "B0HBKSOECH", "name": "白玉兰酒店(武汉武胜路地铁站店)", "address": "荣东社区107号", "type": "住宿服务;住宿服务相关;住宿服务相关|餐饮服务;餐饮相关场所;餐饮相关", "typecode": "100000|050000", "pcode": 420000, "pname": "湖北省", "citycode": 27, "cityname": "武汉市", "adcode": 420104, "adname": "硚口区", "business_a": "江滩", "location": "114.269476,30.572947", "tel": "027-59300559", "fetch_time": "19/1/2025 06:36:00", "大类": "住宿服务", "中类": "住宿服务相关", "小类": "住宿服务相关|餐饮服务;餐饮相关场所;餐饮相关", "wgs84经ti": 114.264064, "wgs84纬ti": 30.57541}}]}