{"type": "FeatureCollection", "features": [{"type": "Feature", "id": 19196, "geometry": {"type": "Point", "coordinates": [114.57324699964943, 30.66922699992614]}, "properties": {"OBJECTID": 19196, "poiid": "B0G0PACK6N", "name": "武汉华阳大酒店", "address": "阳逻街新阳大道669号", "type": "住宿服务;住宿服务相关;住宿服务相关|餐饮服务;中餐厅;综合酒楼", "typecode": "100000|050101", "pcode": 420000, "pname": "湖北省", "citycode": 27, "cityname": "武汉市", "adcode": 420117, "adname": "新洲区", "business_a": "阳逻", "location": "114.573247,30.669227", "tel": "027-89771799;027-89772799", "fetch_time": "19/1/2025 06:54:24", "大类": "住宿服务", "中类": "住宿服务相关", "小类": "住宿服务相关|餐饮服务;中餐厅;综合酒楼", "wgs84经ti": 114.568164, "wgs84纬ti": 30.671825}}]}