{"type": "FeatureCollection", "features": [{"type": "Feature", "id": 1012, "geometry": {"type": "Point", "coordinates": [114.31653499999027, 30.707128000356988]}, "properties": {"OBJECTID": 1012, "poiid": "B0FFIN6IZG", "name": "武汉顺祥晓晖汽车贸易有限公司", "address": "汉口北汽车大世界", "type": "汽车销售;奇瑞特约销售;奇瑞销售|汽车服务;汽车养护/装饰;汽车养护", "typecode": "022400|010400", "pcode": 420000, "pname": "湖北省", "citycode": 27, "cityname": "武汉市", "adcode": 420116, "adname": "黄陂区", "business_a": " ", "location": "114.316535,30.707128", "tel": "027-83882735", "fetch_time": "19/1/2025 20:44:17", "大类": "汽车销售", "中类": "奇瑞特约销售", "小类": "奇瑞销售|汽车服务;汽车养护/装饰;汽车养护", "wgs84经ti": 114.311064, "wgs84纬ti": 30.709468}}]}