{"type": "FeatureCollection", "features": [{"type": "Feature", "id": 589, "geometry": {"type": "Point", "coordinates": [114.44123000006448, 30.450802999658777]}, "properties": {"OBJECTID": 589, "poiid": "B0FFFYYDBR", "name": "东风本田汽车惠盛特约销售服务店", "address": "光谷大道高新四路12号", "type": "汽车销售;本田特约销售;广汽本田销售|汽车维修;本田特约维修;东风本田维修", "typecode": "020201|030302", "pcode": 420000, "pname": "湖北省", "citycode": 27, "cityname": "武汉市", "adcode": 420115, "adname": "江夏区", "business_a": "藏龙岛", "location": "114.441230,30.450803", "tel": "027-66661766;4008806622", "fetch_time": "19/1/2025 21:03:41", "大类": "汽车销售", "中类": "本田特约销售", "小类": "广汽本田销售|汽车维修;本田特约维修;东风本田维修", "wgs84经ti": 114.435752, "wgs84纬ti": 30.453157}}, {"type": "Feature", "id": 4138, "geometry": {"type": "Point", "coordinates": [114.4411190003417, 30.450838000373494]}, "properties": {"OBJECTID": 4138, "poiid": "B0FFFYYDBR", "name": "东风本田汽车惠盛特约销售服务店", "address": "东湖新技术开发区高新四路12号", "type": "汽车销售;本田特约销售;广汽本田销售|汽车维修;本田特约维修;东风本田维修", "typecode": "020201|030302", "pcode": 420000, "pname": "湖北省", "citycode": 27, "cityname": "武汉市", "adcode": 420115, "adname": "江夏区", "business_a": "流芳", "location": "114.441119,30.450838", "tel": "027-66661766;4008806622", "fetch_time": "19/1/2025 06:35:58", "大类": "汽车销售", "中类": "本田特约销售", "小类": "广汽本田销售|汽车维修;本田特约维修;东风本田维修", "wgs84经ti": 114.435641, "wgs84纬ti": 30.453192}}]}