{"type": "FeatureCollection", "features": [{"type": "Feature", "id": 595, "geometry": {"type": "Point", "coordinates": [114.33796199974654, 30.51335600017933]}, "properties": {"OBJECTID": 595, "poiid": "B0FFGXM9RO", "name": "广汽本田汽车景田特约销售服务店", "address": "雄楚大街248号", "type": "汽车销售;本田特约销售;广汽本田销售", "typecode": "020201", "pcode": 420000, "pname": "湖北省", "citycode": 27, "cityname": "武汉市", "adcode": 420111, "adname": "洪山区", "business_a": "丁字桥", "location": "114.337962,30.513356", "tel": "027-87751010", "fetch_time": "19/1/2025 21:03:42", "大类": "汽车销售", "中类": "本田特约销售", "小类": "广汽本田销售", "wgs84经ti": 114.332473, "wgs84纬ti": 30.515733}}, {"type": "Feature", "id": 3162, "geometry": {"type": "Point", "coordinates": [114.27603600026123, 30.629064000403332]}, "properties": {"OBJECTID": 3162, "poiid": "B0ID2BTJUD", "name": "HONDA", "address": "文清路与兴业路辅路交叉口东南60米", "type": "汽车销售;本田特约销售;广汽本田销售", "typecode": "020201", "pcode": 420000, "pname": "湖北省", "citycode": 27, "cityname": "武汉市", "adcode": 420102, "adname": "江岸区", "business_a": "后湖", "location": "114.276036,30.629064", "tel": " ", "fetch_time": "19/1/2025 07:13:28", "大类": "汽车销售", "中类": "本田特约销售", "小类": "广汽本田销售", "wgs84经ti": 114.270617, "wgs84纬ti": 30.631499}}, {"type": "Feature", "id": 3229, "geometry": {"type": "Point", "coordinates": [114.30375799983187, 30.660038999800065]}, "properties": {"OBJECTID": 3229, "poiid": "B0G2UP1LYX", "name": "广汽HONDA星冠合旗舰店", "address": "和谐大道与商贸四街交叉口西60米", "type": "汽车销售;本田特约销售;广汽本田销售", "typecode": "020201", "pcode": 420000, "pname": "湖北省", "citycode": 27, "cityname": "武汉市", "adcode": 420102, "adname": "江岸区", "business_a": "后湖", "location": "114.303758,30.660039", "tel": " ", "fetch_time": "19/1/2025 07:13:31", "大类": "汽车销售", "中类": "本田特约销售", "小类": "广汽本田销售", "wgs84经ti": 114.29831, "wgs84纬ti": 30.662423}}, {"type": "Feature", "id": 3744, "geometry": {"type": "Point", "coordinates": [114.33796199974654, 30.51335600017933]}, "properties": {"OBJECTID": 3744, "poiid": "B0FFGXM9RO", "name": "广汽本田汽车景田特约销售服务店", "address": "雄楚大街248号", "type": "汽车销售;本田特约销售;广汽本田销售", "typecode": "020201", "pcode": 420000, "pname": "湖北省", "citycode": 27, "cityname": "武汉市", "adcode": 420111, "adname": "洪山区", "business_a": "丁字桥", "location": "114.337962,30.513356", "tel": "027-87751010", "fetch_time": "19/1/2025 07:04:25", "大类": "汽车销售", "中类": "本田特约销售", "小类": "广汽本田销售", "wgs84经ti": 114.332473, "wgs84纬ti": 30.515733}}]}