{"type": "FeatureCollection", "features": [{"type": "Feature", "id": 170, "geometry": {"type": "Point", "coordinates": [114.29545500004826, 30.485943999615927]}, "properties": {"OBJECTID": 170, "poiid": "B0KUJAQ5HE", "name": "武汉宝马中达江宝南湖汽车销售服务有限公司", "address": "白沙一路19号武汉智电新能源汽车产业园c2-101", "type": "汽车销售;宝马特约销售;宝马销售", "typecode": "020600", "pcode": 420000, "pname": "湖北省", "citycode": 27, "cityname": "武汉市", "adcode": 420111, "adname": "洪山区", "business_a": "张家湾", "location": "114.295455,30.485944", "tel": "027-59271111", "fetch_time": "19/1/2025 06:33:57", "大类": "汽车销售", "中类": "宝马特约销售", "小类": "宝马销售", "wgs84经ti": 114.290032, "wgs84纬ti": 30.488405}}, {"type": "Feature", "id": 431, "geometry": {"type": "Point", "coordinates": [114.32413699982271, 30.47793299980816]}, "properties": {"OBJECTID": 431, "poiid": "B0FFH67KTZ", "name": "BMW武汉中达江宝南湖", "address": "南湖街街道野芷湖西路保利心语", "type": "汽车销售;宝马特约销售;宝马销售", "typecode": "020600", "pcode": 420000, "pname": "湖北省", "citycode": 27, "cityname": "武汉市", "adcode": 420111, "adname": "洪山区", "business_a": " ", "location": "114.324137,30.477933", "tel": " ", "fetch_time": "19/1/2025 20:54:16", "大类": "汽车销售", "中类": "宝马特约销售", "小类": "宝马销售", "wgs84经ti": 114.318674, "wgs84纬ti": 30.480346}}, {"type": "Feature", "id": 437, "geometry": {"type": "Point", "coordinates": [114.10256600012087, 30.616404000244472]}, "properties": {"OBJECTID": 437, "poiid": "B0HUV14CT6", "name": "武汉运通益宝", "address": "台中北路与富民路交叉口西60米", "type": "汽车销售;宝马特约销售;宝马销售", "typecode": "020600", "pcode": 420000, "pname": "湖北省", "citycode": 27, "cityname": "武汉市", "adcode": 420112, "adname": "东西湖区", "business_a": " ", "location": "114.102566,30.616404", "tel": "027-83232999", "fetch_time": "19/1/2025 20:54:19", "大类": "汽车销售", "中类": "宝马特约销售", "小类": "宝马销售", "wgs84经ti": 114.096828, "wgs84纬ti": 30.618675}}, {"type": "Feature", "id": 2798, "geometry": {"type": "Point", "coordinates": [114.29545500004826, 30.485943999615927]}, "properties": {"OBJECTID": 2798, "poiid": "B0KUJAQ5HE", "name": "武汉宝马中达江宝南湖汽车销售服务有限公司", "address": "白沙一路19号武汉智电新能源汽车产业园c2-101", "type": "汽车销售;宝马特约销售;宝马销售", "typecode": "020600", "pcode": 420000, "pname": "湖北省", "citycode": 27, "cityname": "武汉市", "adcode": 420111, "adname": "洪山区", "business_a": "张家湾", "location": "114.295455,30.485944", "tel": "027-59271111", "fetch_time": "19/1/2025 04:30:04", "大类": "汽车销售", "中类": "宝马特约销售", "小类": "宝马销售", "wgs84经ti": 114.290032, "wgs84纬ti": 30.488405}}, {"type": "Feature", "id": 4553, "geometry": {"type": "Point", "coordinates": [114.29545500004826, 30.485943999615927]}, "properties": {"OBJECTID": 4553, "poiid": "B0KUJAQ5HE", "name": "武汉宝马中达江宝南湖汽车销售服务有限公司", "address": "白沙一路19号武汉智电新能源汽车产业园c2-101", "type": "汽车销售;宝马特约销售;宝马销售", "typecode": "020600", "pcode": 420000, "pname": "湖北省", "citycode": 27, "cityname": "武汉市", "adcode": 420111, "adname": "洪山区", "business_a": "张家湾", "location": "114.295455,30.485944", "tel": "027-59271111", "fetch_time": "19/1/2025 07:57:19", "大类": "汽车销售", "中类": "宝马特约销售", "小类": "宝马销售", "wgs84经ti": 114.290032, "wgs84纬ti": 30.488405}}]}