{"type": "FeatureCollection", "features": [{"type": "Feature", "id": 518, "geometry": {"type": "Point", "coordinates": [114.49970999981667, 30.511162999772694]}, "properties": {"OBJECTID": 518, "poiid": "B001B08ON3", "name": "武汉市公安局关山治安检查站", "address": "铺刘村", "type": "政府机构及社会团体;交通车辆管理;交通管理机构|政府机构及社会团体;公检法机构;公安警察", "typecode": "130601|130501", "pcode": 420000, "pname": "湖北省", "citycode": 27, "cityname": "武汉市", "adcode": 420111, "adname": "洪山区", "business_a": " ", "location": "114.499710,30.511163", "tel": " ", "fetch_time": "19/1/2025 20:58:08", "大类": "政府机构及社会团体", "中类": "交通车辆管理", "小类": "交通管理机构|政府机构及社会团体;公检法机构;公安警察", "wgs84经ti": 114.494421, "wgs84纬ti": 30.51365}}]}