{"type": "FeatureCollection", "features": [{"type": "Feature", "id": 13, "geometry": {"type": "Point", "coordinates": [114.2070059996272, 30.563118999941935]}, "properties": {"OBJECTID": 13, "poiid": "B0FFH44DTL", "name": "武汉市酒驾警示教育基地", "address": "汉阳大道695号(王家湾地铁站A口步行260米)", "type": "政府机构及社会团体;交通车辆管理;交通管理机构|科教文化服务;驾校;驾校|科教文化服务;培训机构;培训机构", "typecode": "130601|141500|141400", "pcode": 420000, "pname": "湖北省", "citycode": 27, "cityname": "武汉市", "adcode": 420105, "adname": "汉阳区", "business_a": "王家湾", "location": "114.207006,30.563119", "tel": " ", "fetch_time": "19/1/2025 19:56:00", "大类": "政府机构及社会团体", "中类": "交通车辆管理", "小类": "交通管理机构|科教文化服务;驾校;驾校|科教文化服务;培训机构;培训机构", "wgs84经ti": 114.201524, "wgs84纬ti": 30.565561}}, {"type": "Feature", "id": 1687, "geometry": {"type": "Point", "coordinates": [114.20684899958178, 30.563090000403236]}, "properties": {"OBJECTID": 1687, "poiid": "B0FFH44DTL", "name": "武汉市酒驾警示教育基地", "address": "汉阳大道695号", "type": "政府机构及社会团体;交通车辆管理;交通管理机构|科教文化服务;驾校;驾校|科教文化服务;培训机构;培训机构", "typecode": "130601|141500|141400", "pcode": 420000, "pname": "湖北省", "citycode": 27, "cityname": "武汉市", "adcode": 420105, "adname": "汉阳区", "business_a": "王家湾", "location": "114.206849,30.563090", "tel": " ", "fetch_time": "19/1/2025 21:11:34", "大类": "政府机构及社会团体", "中类": "交通车辆管理", "小类": "交通管理机构|科教文化服务;驾校;驾校|科教文化服务;培训机构;培训机构", "wgs84经ti": 114.201366, "wgs84纬ti": 30.565531}}]}