{"type": "FeatureCollection", "features": [{"type": "Feature", "id": 56, "geometry": {"type": "Point", "coordinates": [114.32453200005182, 30.57148599997896]}, "properties": {"OBJECTID": 56, "poiid": "B0FFFR2SWD", "name": "武汉市公安局交通管理局车辆管理所", "address": "友谊大道314号", "type": "政府机构及社会团体;交通车辆管理;车辆管理机构|政府机构及社会团体;交通车辆管理;交通管理机构", "typecode": "130602|130601", "pcode": 420000, "pname": "湖北省", "citycode": 27, "cityname": "武汉市", "adcode": 420106, "adname": "武昌区", "business_a": "徐家棚", "location": "114.324532,30.571486", "tel": "027-12123", "fetch_time": "19/1/2025 07:43:31", "大类": "政府机构及社会团体", "中类": "交通车辆管理", "小类": "车辆管理机构|政府机构及社会团体;交通车辆管理;交通管理机构", "wgs84经ti": 114.31906, "wgs84纬ti": 30.573869}}, {"type": "Feature", "id": 30264, "geometry": {"type": "Point", "coordinates": [114.32453200005182, 30.57148599997896]}, "properties": {"OBJECTID": 30264, "poiid": "B0FFFR2SWD", "name": "武汉市公安局交通管理局车辆管理所", "address": "友谊大道314号", "type": "政府机构及社会团体;交通车辆管理;车辆管理机构|政府机构及社会团体;交通车辆管理;交通管理机构", "typecode": "130602|130601", "pcode": 420000, "pname": "湖北省", "citycode": 27, "cityname": "武汉市", "adcode": 420106, "adname": "武昌区", "business_a": "徐家棚", "location": "114.324532,30.571486", "tel": "027-12123", "fetch_time": "19/1/2025 09:00:48", "大类": "政府机构及社会团体", "中类": "交通车辆管理", "小类": "车辆管理机构|政府机构及社会团体;交通车辆管理;交通管理机构", "wgs84经ti": 114.31906, "wgs84纬ti": 30.573869}}]}