{"type": "FeatureCollection", "features": [{"type": "Feature", "id": 5476, "geometry": {"type": "Point", "coordinates": [114.31792000000803, 30.70754499980194]}, "properties": {"OBJECTID": 5476, "poiid": "B0LBLCDWTS", "name": "长城汽车哈弗(武汉博悦兴店)", "address": "汉口北大道88号汉口北汽车大世界W2区1层", "type": "汽车维修;长城汽车维修;长城汽车维修", "typecode": "033400", "pcode": 420000, "pname": "湖北省", "citycode": 27, "cityname": "武汉市", "adcode": 420116, "adname": "黄陂区", "business_a": " ", "location": "114.317920,30.707545", "tel": "027-61598178", "fetch_time": "19/1/2025 05:01:49", "大类": "汽车维修", "中类": "长城汽车维修", "小类": "长城汽车维修", "wgs84经ti": 114.312447, "wgs84纬ti": 30.709882}}]}