{"type": "FeatureCollection", "features": [{"type": "Feature", "id": 12677, "geometry": {"type": "Point", "coordinates": [114.26853599973663, 30.567952999831107]}, "properties": {"OBJECTID": 12677, "poiid": "B001B0B7TB", "name": "武汉市皮肤病防治院(武胜路)", "address": "武胜路64号", "type": "医疗保健服务;专科医院;整形美容|医疗保健服务;疾病预防机构;疾病预防", "typecode": "090201|090500", "pcode": 420000, "pname": "湖北省", "citycode": 27, "cityname": "武汉市", "adcode": 420104, "adname": "硚口区", "business_a": "汉中", "location": "114.268536,30.567953", "tel": "027-85663860;027-85749036", "fetch_time": "19/1/2025 21:26:23", "大类": "医疗保健服务", "中类": "专科医院", "小类": "整形美容|医疗保健服务;疾病预防机构;疾病预防", "wgs84经ti": 114.263124, "wgs84纬ti": 30.570419}}]}