{"type": "FeatureCollection", "features": [{"type": "Feature", "id": 4523, "geometry": {"type": "Point", "coordinates": [114.35821100003773, 30.533837000377332]}, "properties": {"OBJECTID": 4523, "poiid": "B001B1DI38", "name": "武汉大学出版社读者服务部", "address": "珞珈山16号武汉大学", "type": "科教文化服务;传媒机构;出版社|生活服务;生活服务场所;生活服务场所", "typecode": "141105|070000", "pcode": 420000, "pname": "湖北省", "citycode": 27, "cityname": "武汉市", "adcode": 420106, "adname": "武昌区", "business_a": "武汉大学珞珈山", "location": "114.358211,30.533837", "tel": " ", "fetch_time": "19/1/2025 21:23:30", "大类": "科教文化服务", "中类": "传媒机构", "小类": "出版社|生活服务;生活服务场所;生活服务场所", "wgs84经ti": 114.352691, "wgs84纬ti": 30.536172}}]}