{"type": "FeatureCollection", "features": [{"type": "Feature", "id": 181127, "geometry": {"type": "Point", "coordinates": [114.34254899993641, 30.55637300001399]}, "properties": {"OBJECTID": 181127, "poiid": "B0J3PL5TNM", "name": "FILA(楚河汉街北区店)", "address": "楚河汉街1号楚河汉街北区F1层", "type": "购物服务;体育用品店;体育用品店|购物服务;服装鞋帽皮具店;服装鞋帽皮具店", "typecode": "060900|061100", "pcode": 420000, "pname": "湖北省", "citycode": 27, "cityname": "武汉市", "adcode": 420106, "adname": "武昌区", "business_a": "中北路", "location": "114.342549,30.556373", "tel": " ", "fetch_time": "19/1/2025 00:50:13", "大类": "购物服务", "中类": "体育用品店", "小类": "体育用品店|购物服务;服装鞋帽皮具店;服装鞋帽皮具店", "wgs84经ti": 114.337049, "wgs84纬ti": 30.558727}}]}