{"type": "FeatureCollection", "features": [{"type": "Feature", "id": 179640, "geometry": {"type": "Point", "coordinates": [114.28073500022015, 30.598644999667044]}, "properties": {"OBJECTID": 179640, "poiid": "B0I337XK1Z", "name": "DESCENTE 迪桑特(武汉万象城店)", "address": "建设大道668号武汉万象城外街1楼P112A", "type": "购物服务;体育用品店;户外用品|购物服务;服装鞋帽皮具店;服装鞋帽皮具店", "typecode": "060907|061100", "pcode": 420000, "pname": "湖北省", "citycode": 27, "cityname": "武汉市", "adcode": 420102, "adname": "江岸区", "business_a": "建设大道", "location": "114.280735,30.598645", "tel": "027-85363700", "fetch_time": "19/1/2025 00:48:15", "大类": "购物服务", "中类": "体育用品店", "小类": "户外用品|购物服务;服装鞋帽皮具店;服装鞋帽皮具店", "wgs84经ti": 114.275316, "wgs84纬ti": 30.601088}}, {"type": "Feature", "id": 179647, "geometry": {"type": "Point", "coordinates": [114.28019200036056, 30.59892299989656]}, "properties": {"OBJECTID": 179647, "poiid": "B0K1OCYT4L", "name": "Columbia", "address": "建设大道668号武汉万象城L5层", "type": "购物服务;体育用品店;户外用品|购物服务;服装鞋帽皮具店;服装鞋帽皮具店", "typecode": "060907|061100", "pcode": 420000, "pname": "湖北省", "citycode": 27, "cityname": "武汉市", "adcode": 420102, "adname": "江岸区", "business_a": "建设大道", "location": "114.280192,30.598923", "tel": " ", "fetch_time": "19/1/2025 00:48:15", "大类": "购物服务", "中类": "体育用品店", "小类": "户外用品|购物服务;服装鞋帽皮具店;服装鞋帽皮具店", "wgs84经ti": 114.274773, "wgs84纬ti": 30.601366}}]}