{"type": "FeatureCollection", "features": [{"type": "Feature", "id": 2558, "geometry": {"type": "Point", "coordinates": [114.30976199971656, 30.534696999566904]}, "properties": {"OBJECTID": 2558, "poiid": "B0FFHCR2FX", "name": "湖北省人民医院双向转诊医院", "address": "紫阳路241号", "type": "医疗保健服务;综合医院;三级甲等医院|医疗保健服务;专科医院;妇科医院", "typecode": "090101|090209", "pcode": 420000, "pname": "湖北省", "citycode": 27, "cityname": "武汉市", "adcode": 420106, "adname": "武昌区", "business_a": "中南路/中南", "location": "114.309762,30.534697", "tel": " ", "fetch_time": "19/1/2025 20:38:51", "大类": "医疗保健服务", "中类": "综合医院", "小类": "三级甲等医院|医疗保健服务;专科医院;妇科医院", "wgs84经ti": 114.304316, "wgs84纬ti": 30.53712}}, {"type": "Feature", "id": 25133, "geometry": {"type": "Point", "coordinates": [114.30976199971656, 30.534696999566904]}, "properties": {"OBJECTID": 25133, "poiid": "B0FFHCR2FX", "name": "湖北省人民医院双向转诊医院", "address": "紫阳路241号(首义路地铁站D3口步行100米)", "type": "医疗保健服务;综合医院;三级甲等医院|医疗保健服务;专科医院;妇科医院", "typecode": "090101|090209", "pcode": 420000, "pname": "湖北省", "citycode": 27, "cityname": "武汉市", "adcode": 420106, "adname": "武昌区", "business_a": "中南路/中南", "location": "114.309762,30.534697", "tel": " ", "fetch_time": "19/1/2025 06:51:22", "大类": "医疗保健服务", "中类": "综合医院", "小类": "三级甲等医院|医疗保健服务;专科医院;妇科医院", "wgs84经ti": 114.304316, "wgs84纬ti": 30.53712}}]}