{"type": "FeatureCollection", "features": [{"type": "Feature", "id": 17519, "geometry": {"type": "Point", "coordinates": [114.26997599959282, 30.59498499995783]}, "properties": {"OBJECTID": 17519, "poiid": "B001B16OK1", "name": "法国领事馆文化教育合作处高等教育署武汉中心", "address": "建设大道568新世界国贸大厦1717", "type": "政府机构及社会团体;外国机构;外国机构相关|科教文化服务;科教文化场所;科教文化场所", "typecode": "130200|140000", "pcode": 420000, "pname": "湖北省", "citycode": 27, "cityname": "武汉市", "adcode": 420103, "adname": "江汉区", "business_a": "新华", "location": "114.269976,30.594985", "tel": " ", "fetch_time": "19/1/2025 22:30:02", "大类": "政府机构及社会团体", "中类": "外国机构", "小类": "外国机构相关|科教文化服务;科教文化场所;科教文化场所", "wgs84经ti": 114.264562, "wgs84纬ti": 30.597439}}]}