{"type": "FeatureCollection", "features": [{"type": "Feature", "id": 509, "geometry": {"type": "Point", "coordinates": [114.4205509997289, 30.433493000001988]}, "properties": {"OBJECTID": 509, "poiid": "B0FFH1VRRT", "name": "广汽广本友谊店", "address": "光谷高新4路", "type": "汽车维修;本田特约维修;广汽本田维修|购物服务;购物相关场所;购物相关场所", "typecode": "030301|060000", "pcode": 420000, "pname": "湖北省", "citycode": 27, "cityname": "武汉市", "adcode": 420115, "adname": "江夏区", "business_a": "藏龙岛", "location": "114.420551,30.433493", "tel": "027-88618188", "fetch_time": "19/1/2025 21:03:51", "大类": "汽车维修", "中类": "本田特约维修", "小类": "广汽本田维修|购物服务;购物相关场所;购物相关场所", "wgs84经ti": 114.415035, "wgs84纬ti": 30.435825}}]}