{"type": "FeatureCollection", "features": [{"type": "Feature", "id": 262, "geometry": {"type": "Point", "coordinates": [114.3014599999791, 30.6618060003467]}, "properties": {"OBJECTID": 262, "poiid": "B0FFH1JKSR", "name": "武汉三环泽通汽车有限公司", "address": "金桥大道1号中环商贸城内", "type": "汽车销售;日产特约销售;东风日产销售|汽车维修;东风特约维修;东风维修", "typecode": "020701|032300", "pcode": 420000, "pname": "湖北省", "citycode": 27, "cityname": "武汉市", "adcode": 420102, "adname": "江岸区", "business_a": "后湖", "location": "114.30146,30.661806", "tel": "027-88605399;18627793133", "fetch_time": "19/1/2025 20:52:48", "大类": "汽车销售", "中类": "日产特约销售", "小类": "东风日产销售|汽车维修;东风特约维修;东风维修", "wgs84经ti": 114.296015, "wgs84纬ti": 30.664193}}, {"type": "Feature", "id": 3175, "geometry": {"type": "Point", "coordinates": [114.3014599999791, 30.6618060003467]}, "properties": {"OBJECTID": 3175, "poiid": "B0FFH1JKSR", "name": "东风日产武汉三环泽通专营店", "address": "金桥大道1号中环商贸城内", "type": "汽车销售;日产特约销售;东风日产销售|汽车维修;东风特约维修;东风维修", "typecode": "020701|032300", "pcode": 420000, "pname": "湖北省", "citycode": 27, "cityname": "武汉市", "adcode": 420102, "adname": "江岸区", "business_a": "后湖", "location": "114.301460,30.661806", "tel": "027-88605399;18627793133", "fetch_time": "19/1/2025 07:13:29", "大类": "汽车销售", "中类": "日产特约销售", "小类": "东风日产销售|汽车维修;东风特约维修;东风维修", "wgs84经ti": 114.296015, "wgs84纬ti": 30.664193}}]}