{"type": "FeatureCollection", "features": [{"type": "Feature", "id": 6035, "geometry": {"type": "Point", "coordinates": [114.05605199999991, 30.62603700020742]}, "properties": {"OBJECTID": 6035, "poiid": "B0FFGFRW3W", "name": "奔峰电器超市", "address": "万国汽配高桥国际城1D-11号", "type": "汽车服务;汽车配件销售;汽车配件销售|购物服务;家电电子卖场;家电电子卖场", "typecode": "010800|060300", "pcode": 420000, "pname": "湖北省", "citycode": 27, "cityname": "武汉市", "adcode": 420112, "adname": "东西湖区", "business_a": " ", "location": "114.056052,30.626037", "tel": "027-83388687;13720320078", "fetch_time": "19/1/2025 20:43:23", "大类": "汽车服务", "中类": "汽车配件销售", "小类": "汽车配件销售|购物服务;家电电子卖场;家电电子卖场", "wgs84经ti": 114.050323, "wgs84纬ti": 30.628343}}]}