{"type": "FeatureCollection", "features": [{"type": "Feature", "id": 1068, "geometry": {"type": "Point", "coordinates": [114.13874200014322, 30.63936299960278]}, "properties": {"OBJECTID": 1068, "poiid": "B001B0I0JJ", "name": "随园会馆", "address": "五环路特1号", "type": "住宿服务;宾馆酒店;六星级及以上宾馆", "typecode": "100101", "pcode": 420000, "pname": "湖北省", "citycode": 27, "cityname": "武汉市", "adcode": 420112, "adname": "东西湖区", "business_a": "三店", "location": "114.138742,30.639363", "tel": "027-83378777", "fetch_time": "19/1/2025 21:26:54", "大类": "住宿服务", "中类": "宾馆酒店", "小类": "六星级及以上宾馆", "wgs84经ti": 114.133066, "wgs84纬ti": 30.641656}}]}