{"type": "FeatureCollection", "features": [{"type": "Feature", "id": 1553, "geometry": {"type": "Point", "coordinates": [114.34703299987314, 30.528789999658784]}, "properties": {"OBJECTID": 1553, "poiid": "B001B16MKW", "name": "7天优品酒店(武汉武大街道口店)", "address": "武珞路675号", "type": "住宿服务;宾馆酒店;经济型连锁酒店|住宿服务;旅馆招待所;旅馆招待所|购物服务;便民商店/便利店;便民商店/便利店", "typecode": "100105|100200|060200", "pcode": 420000, "pname": "湖北省", "citycode": 27, "cityname": "武汉市", "adcode": 420111, "adname": "洪山区", "business_a": "珞南", "location": "114.347033,30.528790", "tel": "027-87860777", "fetch_time": "19/1/2025 20:51:09", "大类": "住宿服务", "中类": "宾馆酒店", "小类": "经济型连锁酒店|住宿服务;旅馆招待所;旅馆招待所|购物服务;便民商店/便利店;便民商店/便利店", "wgs84经ti": 114.341529, "wgs84纬ti": 30.531145}}]}