{"type": "FeatureCollection", "features": [{"type": "Feature", "id": 125, "geometry": {"type": "Point", "coordinates": [114.32256099999017, 30.66196499958511]}, "properties": {"OBJECTID": 125, "poiid": "B0FFHCQ6NN", "name": "宝驹汽车美容装饰", "address": "后湖百步亭路", "type": "汽车维修;汽车维修;汽车维修|汽车服务;汽车养护/装饰;汽车养护", "typecode": "030000|010400", "pcode": 420000, "pname": "湖北省", "citycode": 27, "cityname": "武汉市", "adcode": 420102, "adname": "江岸区", "business_a": "岱山", "location": "114.322561,30.661965", "tel": "18771071579", "fetch_time": "19/1/2025 20:53:40", "大类": "汽车维修", "中类": "汽车维修", "小类": "汽车维修|汽车服务;汽车养护/装饰;汽车养护", "wgs84经ti": 114.317084, "wgs84纬ti": 30.664314}}, {"type": "Feature", "id": 1875, "geometry": {"type": "Point", "coordinates": [114.2574320002866, 30.633375999602777]}, "properties": {"OBJECTID": 1875, "poiid": "B0FFFFUE0W", "name": "别克雪佛兰", "address": "长港路姑嫂树路口", "type": "汽车维修;汽车维修;汽车维修|汽车服务;汽车养护/装饰;汽车养护", "typecode": "030000|010400", "pcode": 420000, "pname": "湖北省", "citycode": 27, "cityname": "武汉市", "adcode": 420103, "adname": "江汉区", "business_a": "常青", "location": "114.257432,30.633376", "tel": "15902783655", "fetch_time": "19/1/2025 21:22:43", "大类": "汽车维修", "中类": "汽车维修", "小类": "汽车维修|汽车服务;汽车养护/装饰;汽车养护", "wgs84经ti": 114.252014, "wgs84纬ti": 30.635821}}, {"type": "Feature", "id": 2651, "geometry": {"type": "Point", "coordinates": [114.57681300041975, 30.66614900007636]}, "properties": {"OBJECTID": 2651, "poiid": "B0FFIPO6X4", "name": "车龙汽车维修养护", "address": "阳逻街长丰路329号(与高新路交汇处)", "type": "汽车维修;汽车维修;汽车维修|汽车服务;汽车养护/装饰;汽车养护", "typecode": "030000|010400", "pcode": 420000, "pname": "湖北省", "citycode": 27, "cityname": "武汉市", "adcode": 420117, "adname": "新洲区", "business_a": "阳逻", "location": "114.576813,30.666149", "tel": "13995536913;15387048337", "fetch_time": "19/1/2025 20:55:03", "大类": "汽车维修", "中类": "汽车维修", "小类": "汽车维修|汽车服务;汽车养护/装饰;汽车养护", "wgs84经ti": 114.571736, "wgs84纬ti": 30.668752}}, {"type": "Feature", "id": 5605, "geometry": {"type": "Point", "coordinates": [114.32256099999017, 30.66196499958511]}, "properties": {"OBJECTID": 5605, "poiid": "B0FFHCQ6NN", "name": "宝驹汽车美容装饰", "address": "后湖百步亭路", "type": "汽车维修;汽车维修;汽车维修|汽车服务;汽车养护/装饰;汽车养护", "typecode": "030000|010400", "pcode": 420000, "pname": "湖北省", "citycode": 27, "cityname": "武汉市", "adcode": 420102, "adname": "江岸区", "business_a": "岱山", "location": "114.322561,30.661965", "tel": "18771071579", "fetch_time": "19/1/2025 07:13:18", "大类": "汽车维修", "中类": "汽车维修", "小类": "汽车维修|汽车服务;汽车养护/装饰;汽车养护", "wgs84经ti": 114.317084, "wgs84纬ti": 30.664314}}]}