{"type": "FeatureCollection", "features": [{"type": "Feature", "id": 1227, "geometry": {"type": "Point", "coordinates": [114.12557499998627, 30.626198000437398]}, "properties": {"OBJECTID": 1227, "poiid": "B0HB2CW4PH", "name": "钣金油漆", "address": "七雄路山水星辰东南侧约60米", "type": "汽车维修;汽车维修;汽车维修|购物服务;购物相关场所;购物相关场所", "typecode": "030000|060000", "pcode": 420000, "pname": "湖北省", "citycode": 27, "cityname": "武汉市", "adcode": 420112, "adname": "东西湖区", "business_a": "长青", "location": "114.125575,30.626198", "tel": " ", "fetch_time": "19/1/2025 20:45:03", "大类": "汽车维修", "中类": "汽车维修", "小类": "汽车维修|购物服务;购物相关场所;购物相关场所", "wgs84经ti": 114.119871, "wgs84纬ti": 30.62848}}, {"type": "Feature", "id": 2368, "geometry": {"type": "Point", "coordinates": [114.35423099996069, 30.718802000012317]}, "properties": {"OBJECTID": 2368, "poiid": "B0H33CWE0H", "name": "钣金油漆", "address": "明富街楚街一品热干面馆旁", "type": "汽车维修;汽车维修;汽车维修|购物服务;购物相关场所;购物相关场所", "typecode": "030000|060000", "pcode": 420000, "pname": "湖北省", "citycode": 27, "cityname": "武汉市", "adcode": 420116, "adname": "黄陂区", "business_a": "滠口", "location": "114.354231,30.718802", "tel": "13871197367;15337272918", "fetch_time": "19/1/2025 20:43:50", "大类": "汽车维修", "中类": "汽车维修", "小类": "汽车维修|购物服务;购物相关场所;购物相关场所", "wgs84经ti": 114.3487, "wgs84纬ti": 30.721066}}, {"type": "Feature", "id": 3510, "geometry": {"type": "Point", "coordinates": [114.05513900016479, 30.630128000007232]}, "properties": {"OBJECTID": 3510, "poiid": "B0H67D2CDR", "name": "南阳校油泵（东西湖大道）", "address": "东西湖大道与东西湖南桥交叉口", "type": "汽车维修;汽车维修;汽车维修|购物服务;购物相关场所;购物相关场所", "typecode": "030000|060000", "pcode": 420000, "pname": "湖北省", "citycode": 27, "cityname": "武汉市", "adcode": 420112, "adname": "东西湖区", "business_a": " ", "location": "114.055139,30.630128", "tel": "15997406878", "fetch_time": "19/1/2025 20:59:54", "大类": "汽车维修", "中类": "汽车维修", "小类": "汽车维修|购物服务;购物相关场所;购物相关场所", "wgs84经ti": 114.04941, "wgs84纬ti": 30.632434}}, {"type": "Feature", "id": 4564, "geometry": {"type": "Point", "coordinates": [114.37271199965915, 30.39932700004107]}, "properties": {"OBJECTID": 4564, "poiid": "B0FFJ1PVVQ", "name": "航宇隆昇(保利海寓店)", "address": "经济开发区江夏大道西保利海寓1层2-3-4室", "type": "汽车维修;汽车维修;汽车维修|购物服务;购物相关场所;购物相关场所", "typecode": "030000|060000", "pcode": 420000, "pname": "湖北省", "citycode": 27, "cityname": "武汉市", "adcode": 420115, "adname": "江夏区", "business_a": "庙山", "location": "114.372712,30.399327", "tel": "027-51334267", "fetch_time": "19/1/2025 12:03:55", "大类": "汽车维修", "中类": "汽车维修", "小类": "汽车维修|购物服务;购物相关场所;购物相关场所", "wgs84经ti": 114.367188, "wgs84纬ti": 30.401677}}]}