{"type": "FeatureCollection", "features": [{"type": "Feature", "id": 30870, "geometry": {"type": "Point", "coordinates": [114.29499699961195, 30.550594999759483]}, "properties": {"OBJECTID": 30870, "poiid": "B0H1V5S7OL", "name": "中华路1号码头(出港)", "address": "临江大道与中华路交叉口西北20米", "type": "交通设施服务;港口码头;出港", "typecode": "150306", "pcode": 420000, "pname": "湖北省", "citycode": 27, "cityname": "武汉市", "adcode": 420106, "adname": "武昌区", "business_a": "江滩", "location": "114.294997,30.550595", "tel": " ", "fetch_time": "19/1/2025 22:50:31", "大类": "交通设施服务", "中类": "港口码头", "小类": "出港", "wgs84经ti": 114.289569, "wgs84纬ti": 30.553037}}]}