{"type": "FeatureCollection", "features": [{"type": "Feature", "id": 44, "geometry": {"type": "Point", "coordinates": [114.4243719996681, 30.656326000344677]}, "properties": {"OBJECTID": 44, "poiid": "B0FFHNI1QM", "name": "武汉轮渡青山码头", "address": "武惠街福汉钢谷建材批发城西北侧约290米", "type": "交通设施服务;港口码头;客运港", "typecode": "150301", "pcode": 420000, "pname": "湖北省", "citycode": 27, "cityname": "武汉市", "adcode": 420107, "adname": "青山区", "business_a": " ", "location": "114.424372,30.656326", "tel": " ", "fetch_time": "19/1/2025 19:55:48", "大类": "交通设施服务", "中类": "港口码头", "小类": "客运港", "wgs84经ti": 114.418842, "wgs84纬ti": 30.658586}}, {"type": "Feature", "id": 20111, "geometry": {"type": "Point", "coordinates": [114.42439599987551, 30.656283000160386]}, "properties": {"OBJECTID": 20111, "poiid": "B0FFHNI1QM", "name": "武汉轮渡青山码头", "address": "武惠街福汉钢谷建材批发城西北侧约290米", "type": "交通设施服务;港口码头;客运港", "typecode": "150301", "pcode": 420000, "pname": "湖北省", "citycode": 27, "cityname": "武汉市", "adcode": 420107, "adname": "青山区", "business_a": " ", "location": "114.424396,30.656283", "tel": " ", "fetch_time": "19/1/2025 21:14:36", "大类": "交通设施服务", "中类": "港口码头", "小类": "客运港", "wgs84经ti": 114.418866, "wgs84纬ti": 30.658543}}]}