{"type": "FeatureCollection", "features": [{"type": "Feature", "id": 20473, "geometry": {"type": "Point", "coordinates": [114.403737999609, 30.544891000219536]}, "properties": {"OBJECTID": 20473, "poiid": "B0FFFGNU34", "name": "梅园码头", "address": "东湖东路鲁磨路交叉口", "type": "交通设施服务;港口码头;港口码头|风景名胜;风景名胜;风景名胜", "typecode": "150300|110200", "pcode": 420000, "pname": "湖北省", "citycode": 27, "cityname": "武汉市", "adcode": 420106, "adname": "武昌区", "business_a": " ", "location": "114.403738,30.544891", "tel": " ", "fetch_time": "19/1/2025 21:32:05", "大类": "交通设施服务", "中类": "港口码头", "小类": "港口码头|风景名胜;风景名胜;风景名胜", "wgs84经ti": 114.398196, "wgs84纬ti": 30.547184}}]}