{"type": "FeatureCollection", "features": [{"type": "Feature", "id": 73914, "geometry": {"type": "Point", "coordinates": [114.26578299958578, 30.431024000357354]}, "properties": {"OBJECTID": 73914, "poiid": "B0FFF01QA3", "name": "明星文具百货超市", "address": "青菱街红霞村福星惠誉东澜岸44-1-商51", "type": "购物服务;文化用品店;文化用品店|购物服务;超级市场;超市", "typecode": "060800|060400", "pcode": 420000, "pname": "湖北省", "citycode": 27, "cityname": "武汉市", "adcode": 420111, "adname": "洪山区", "business_a": " ", "location": "114.265783,30.431024", "tel": "15927076873", "fetch_time": "19/1/2025 09:29:06", "大类": "购物服务", "中类": "文化用品店", "小类": "文化用品店|购物服务;超级市场;超市", "wgs84经ti": 114.260383, "wgs84纬ti": 30.433532}}]}