{"type": "FeatureCollection", "features": [{"type": "Feature", "id": 5764, "geometry": {"type": "Point", "coordinates": [114.32038699956047, 30.523879999862174]}, "properties": {"OBJECTID": 5764, "poiid": "B0GUAC9TO9", "name": "一嗨chi", "address": "静安路与晒湖南路交叉口西20米", "type": "汽车服务;汽车租赁;汽车租赁|购物服务;购物相关场所;购物相关场所", "typecode": "010900|060000", "pcode": 420000, "pname": "湖北省", "citycode": 27, "cityname": "武汉市", "adcode": 420106, "adname": "武昌区", "business_a": "丁字桥", "location": "114.320387,30.523880", "tel": " ", "fetch_time": "19/1/2025 20:49:55", "大类": "汽车服务", "中类": "汽车租赁", "小类": "汽车租赁|购物服务;购物相关场所;购物相关场所", "wgs84经ti": 114.314926, "wgs84纬ti": 30.526287}}, {"type": "Feature", "id": 17243, "geometry": {"type": "Point", "coordinates": [114.20254299975966, 30.594919999658316]}, "properties": {"OBJECTID": 17243, "poiid": "B0FFL9P5YN", "name": "一嗨ehi(硚口古田三路店)", "address": "解放大道109号付79", "type": "汽车服务;汽车租赁;汽车租赁|购物服务;购物相关场所;购物相关场所", "typecode": "010900|060000", "pcode": 420000, "pname": "湖北省", "citycode": 27, "cityname": "武汉市", "adcode": 420104, "adname": "硚口区", "business_a": "古田", "location": "114.202543,30.594920", "tel": "027-83350227", "fetch_time": "19/1/2025 06:30:51", "大类": "汽车服务", "中类": "汽车租赁", "小类": "汽车租赁|购物服务;购物相关场所;购物相关场所", "wgs84经ti": 114.197047, "wgs84纬ti": 30.597343}}]}