{"type": "FeatureCollection", "features": [{"type": "Feature", "id": 47260, "geometry": {"type": "Point", "coordinates": [114.35602299986158, 30.71680499965106]}, "properties": {"OBJECTID": 47260, "poiid": "B0FFGHC1Y8", "name": "武汉哥特公司(富兴道)", "address": "富兴道190号", "type": "公司企业;公司;公司|购物服务;家居建材市场;家居建材市场", "typecode": "170200|060600", "pcode": 420000, "pname": "湖北省", "citycode": 27, "cityname": "武汉市", "adcode": 420116, "adname": "黄陂区", "business_a": "滠口", "location": "114.356023,30.716805", "tel": "13307183068", "fetch_time": "19/1/2025 12:03:55", "大类": "公司企业", "中类": "公司", "小类": "公司|购物服务;家居建材市场;家居建材市场", "wgs84经ti": 114.350489, "wgs84纬ti": 30.719067}}]}