{"type": "FeatureCollection", "features": [{"type": "Feature", "id": 55916, "geometry": {"type": "Point", "coordinates": [114.31514499974196, 30.568368000083183]}, "properties": {"OBJECTID": 55916, "poiid": "B0KRPONMTF", "name": "国兴出租车公司", "address": "新生路与幸福里三路交叉口东北80米", "type": "公司企业;公司;公司|汽车服务;汽车租赁;汽车租赁", "typecode": "170200|010900", "pcode": 420000, "pname": "湖北省", "citycode": 27, "cityname": "武汉市", "adcode": 420106, "adname": "武昌区", "business_a": "积玉桥", "location": "114.315145,30.568368", "tel": " ", "fetch_time": "19/1/2025 04:03:49", "大类": "公司企业", "中类": "公司", "小类": "公司|汽车服务;汽车租赁;汽车租赁", "wgs84经ti": 114.309688, "wgs84纬ti": 30.570769}}]}