{"type": "FeatureCollection", "features": [{"type": "Feature", "id": 5412, "geometry": {"type": "Point", "coordinates": [114.80814599973814, 30.837667000132]}, "properties": {"OBJECTID": 5412, "poiid": "B001B17GE9", "name": "雕琢时光管理有限公司", "address": "邾城街道红旗广场8号楼雕琢时光一楼", "type": "公司企业;公司;公司|餐饮服务;咖啡厅;咖啡厅|餐饮服务;休闲餐饮场所;休闲餐饮场所", "typecode": "170200|050500|050400", "pcode": 420000, "pname": "湖北省", "citycode": 27, "cityname": "武汉市", "adcode": 420117, "adname": "新洲区", "business_a": "邾城", "location": "114.808146,30.837667", "tel": "027-86926877", "fetch_time": "19/1/2025 21:02:41", "大类": "公司企业", "中类": "公司", "小类": "公司|餐饮服务;咖啡厅;咖啡厅|餐饮服务;休闲餐饮场所;休闲餐饮场所", "wgs84经ti": 114.802931, "wgs84纬ti": 30.84006}}]}