{"type": "FeatureCollection", "features": [{"type": "Feature", "id": 3784, "geometry": {"type": "Point", "coordinates": [114.18748499963306, 30.493528000416916]}, "properties": {"OBJECTID": 3784, "poiid": "B001B19IJA", "name": "公交集团江怡路维护中心", "address": "太子湖路与车城北路交叉口东南80米", "type": "公司企业;公司;公司|汽车维修;汽车综合维修;汽车综合维修", "typecode": "170200|030100", "pcode": 420000, "pname": "湖北省", "citycode": 27, "cityname": "武汉市", "adcode": 420114, "adname": "蔡甸区", "business_a": " ", "location": "114.187485,30.493528", "tel": " ", "fetch_time": "19/1/2025 21:23:47", "大类": "公司企业", "中类": "公司", "小类": "公司|汽车维修;汽车综合维修;汽车综合维修", "wgs84经ti": 114.181958, "wgs84纬ti": 30.49596}}]}