{"type": "FeatureCollection", "features": [{"type": "Feature", "id": 3563, "geometry": {"type": "Point", "coordinates": [114.12900499988086, 30.607293000071934]}, "properties": {"OBJECTID": 3563, "poiid": "B0FFGXX6LN", "name": "湖北惠源医药有限公司", "address": "柏泉办事处街道七支沟南鑫斯特产业园2号楼", "type": "公司企业;公司;医药公司|购物服务;便民商店/便利店;便民商店/便利店", "typecode": "170203|060200", "pcode": 420000, "pname": "湖北省", "citycode": 27, "cityname": "武汉市", "adcode": 420112, "adname": "东西湖区", "business_a": " ", "location": "114.129005,30.607293", "tel": "027-83090821", "fetch_time": "19/1/2025 21:10:27", "大类": "公司企业", "中类": "公司", "小类": "医药公司|购物服务;便民商店/便利店;便民商店/便利店", "wgs84经ti": 114.12331, "wgs84纬ti": 30.609587}}]}