{"type": "FeatureCollection", "features": [{"type": "Feature", "id": 2595, "geometry": {"type": "Point", "coordinates": [114.30504799996527, 30.546556999705842]}, "properties": {"OBJECTID": 2595, "poiid": "B0FFGPTKCV", "name": "湖北省医药工业研究院有限公司", "address": "粮道街办事处民主路三道街12号", "type": "公司企业;公司;医药公司|科教文化服务;科研机构;科研机构", "typecode": "170203|141300", "pcode": 420000, "pname": "湖北省", "citycode": 27, "cityname": "武汉市", "adcode": 420106, "adname": "武昌区", "business_a": "司门口", "location": "114.305048,30.546557", "tel": "027-88849957", "fetch_time": "19/1/2025 20:41:41", "大类": "公司企业", "中类": "公司", "小类": "医药公司|科教文化服务;科研机构;科研机构", "wgs84经ti": 114.299608, "wgs84纬ti": 30.548984}}]}