{"type": "FeatureCollection", "features": [{"type": "Feature", "id": 7030, "geometry": {"type": "Point", "coordinates": [114.04769899970916, 30.47522700002611]}, "properties": {"OBJECTID": 7030, "poiid": "B0FFITKB56", "name": "上药科园", "address": "花园湾一街附近", "type": "公司企业;公司;医药公司|生活服务;生活服务场所;生活服务场所", "typecode": "170203|070000", "pcode": 420000, "pname": "湖北省", "citycode": 27, "cityname": "武汉市", "adcode": 420114, "adname": "蔡甸区", "business_a": " ", "location": "114.047699,30.475227", "tel": " ", "fetch_time": "19/1/2025 21:22:04", "大类": "公司企业", "中类": "公司", "小类": "医药公司|生活服务;生活服务场所;生活服务场所", "wgs84经ti": 114.041996, "wgs84纬ti": 30.477602}}]}