{"type": "FeatureCollection", "features": [{"type": "Feature", "id": 4504, "geometry": {"type": "Point", "coordinates": [114.54300099969646, 30.476505999652204]}, "properties": {"OBJECTID": 4504, "poiid": "B0FFLCPE76", "name": "武汉璟泓科技股份有限公司", "address": "高新大道858号高新二路与生物园路交汇处璟泓科技1层", "type": "公司企业;公司;医药公司|购物服务;家电电子卖场;数码电子", "typecode": "170203|060306", "pcode": 420000, "pname": "湖北省", "citycode": 27, "cityname": "武汉市", "adcode": 420115, "adname": "江夏区", "business_a": " ", "location": "114.543001,30.476506", "tel": "027-87531767;15907137123", "fetch_time": "19/1/2025 20:41:29", "大类": "公司企业", "中类": "公司", "小类": "医药公司|购物服务;家电电子卖场;数码电子", "wgs84经ti": 114.537867, "wgs84纬ti": 30.479122}}]}