{"type": "FeatureCollection", "features": [{"type": "Feature", "id": 22850, "geometry": {"type": "Point", "coordinates": [114.15990300022338, 30.58222200044503]}, "properties": {"OBJECTID": 22850, "poiid": "B0FFGWLHYV", "name": "武汉福运隆商贸有限公司", "address": "金花路18号", "type": "公司企业;公司;商业贸易|汽车服务;汽车配件销售;汽车配件销售|购物服务;购物相关场所;购物相关场所", "typecode": "170207|010800|060000", "pcode": 420000, "pname": "湖北省", "citycode": 27, "cityname": "武汉市", "adcode": 420105, "adname": "汉阳区", "business_a": " ", "location": "114.159903,30.582222", "tel": " ", "fetch_time": "19/1/2025 09:20:38", "大类": "公司企业", "中类": "公司", "小类": "商业贸易|汽车服务;汽车配件销售;汽车配件销售|购物服务;购物相关场所;购物相关场所", "wgs84经ti": 114.154289, "wgs84纬ti": 30.584574}}, {"type": "Feature", "id": 57009, "geometry": {"type": "Point", "coordinates": [114.15982900040808, 30.582220000352777]}, "properties": {"OBJECTID": 57009, "poiid": "B0FFGWLHYV", "name": "武汉福运隆商贸有限公司", "address": "金花路18号", "type": "公司企业;公司;商业贸易|汽车服务;汽车配件销售;汽车配件销售|购物服务;购物相关场所;购物相关场所", "typecode": "170207|010800|060000", "pcode": 420000, "pname": "湖北省", "citycode": 27, "cityname": "武汉市", "adcode": 420105, "adname": "汉阳区", "business_a": " ", "location": "114.159829,30.582220", "tel": "027-66666657", "fetch_time": "19/1/2025 06:47:08", "大类": "公司企业", "中类": "公司", "小类": "商业贸易|汽车服务;汽车配件销售;汽车配件销售|购物服务;购物相关场所;购物相关场所", "wgs84经ti": 114.154215, "wgs84纬ti": 30.584571}}]}