{"type": "FeatureCollection", "features": [{"type": "Feature", "id": 53285, "geometry": {"type": "Point", "coordinates": [114.3144479999753, 30.360710999912783]}, "properties": {"OBJECTID": 53285, "poiid": "B0FFFFP9GF", "name": "联升装饰", "address": "纸坊街八分山路546号", "type": "公司企业;公司;广告装饰|购物服务;家居建材市场;家具城|生活服务;生活服务场所;生活服务场所", "typecode": "170201|060602|070000", "pcode": 420000, "pname": "湖北省", "citycode": 27, "cityname": "武汉市", "adcode": 420115, "adname": "江夏区", "business_a": "纸坊", "location": "114.314448,30.360711", "tel": " ", "fetch_time": "19/1/2025 23:20:49", "大类": "公司企业", "中类": "公司", "小类": "广告装饰|购物服务;家居建材市场;家具城|生活服务;生活服务场所;生活服务场所", "wgs84经ti": 114.30901, "wgs84纬ti": 30.363168}}]}