{"type": "FeatureCollection", "features": [{"type": "Feature", "id": 821, "geometry": {"type": "Point", "coordinates": [114.2467620001662, 30.724871000196572]}, "properties": {"OBJECTID": 821, "poiid": "B001B17DYI", "name": "武汉中南工程机械设备有限责任公司", "address": "盘龙城经济开发区宋岗一路特1号", "type": "公司企业;公司;机械电子|汽车销售;吉利特约销售;沃尔沃汽车销售", "typecode": "170204|022301", "pcode": 420000, "pname": "湖北省", "citycode": 27, "cityname": "武汉市", "adcode": 420116, "adname": "黄陂区", "business_a": "奥特莱斯广场", "location": "114.246762,30.724871", "tel": "027-61889088", "fetch_time": "19/1/2025 21:04:10", "大类": "公司企业", "中类": "公司", "小类": "机械电子|汽车销售;吉利特约销售;沃尔沃汽车销售", "wgs84经ti": 114.24133, "wgs84纬ti": 30.727275}}, {"type": "Feature", "id": 58675, "geometry": {"type": "Point", "coordinates": [114.24605499993834, 30.725808000239056]}, "properties": {"OBJECTID": 58675, "poiid": "B001B17DYI", "name": "武汉中南工程机械设备有限责任公司", "address": "盘龙城经济开发区宋岗一路特1号", "type": "公司企业;公司;机械电子|汽车销售;吉利特约销售;沃尔沃汽车销售", "typecode": "170204|022301", "pcode": 420000, "pname": "湖北省", "citycode": 27, "cityname": "武汉市", "adcode": 420116, "adname": "黄陂区", "business_a": "奥特莱斯广场", "location": "114.246055,30.725808", "tel": " ", "fetch_time": "19/1/2025 06:45:01", "大类": "公司企业", "中类": "公司", "小类": "机械电子|汽车销售;吉利特约销售;沃尔沃汽车销售", "wgs84经ti": 114.240622, "wgs84纬ti": 30.728212}}]}