{"type": "FeatureCollection", "features": [{"type": "Feature", "id": 8965, "geometry": {"type": "Point", "coordinates": [114.40422599963028, 30.634165000014775]}, "properties": {"OBJECTID": 8965, "poiid": "B001B0JHD4", "name": "武汉精城成套机电设备有限公司", "address": "沿港路17-10号", "type": "公司企业;公司;机械电子|购物服务;家居建材市场;建材五金市场", "typecode": "170204|060603", "pcode": 420000, "pname": "湖北省", "citycode": 27, "cityname": "武汉市", "adcode": 420107, "adname": "青山区", "business_a": "冶金", "location": "114.404226,30.634165", "tel": "13971694620;18086015113", "fetch_time": "19/1/2025 20:43:33", "大类": "公司企业", "中类": "公司", "小类": "机械电子|购物服务;家居建材市场;建材五金市场", "wgs84经ti": 114.398676, "wgs84纬ti": 30.636424}}, {"type": "Feature", "id": 15143, "geometry": {"type": "Point", "coordinates": [114.24216799965347, 30.382325000198648]}, "properties": {"OBJECTID": 15143, "poiid": "B0FFGB4XYD", "name": "天胤机电", "address": "郑店黄金大道工业园", "type": "公司企业;公司;机械电子|购物服务;家居建材市场;建材五金市场", "typecode": "170204|060603", "pcode": 420000, "pname": "湖北省", "citycode": 27, "cityname": "武汉市", "adcode": 420115, "adname": "江夏区", "business_a": " ", "location": "114.242168,30.382325", "tel": " ", "fetch_time": "19/1/2025 23:35:49", "大类": "公司企业", "中类": "公司", "小类": "机械电子|购物服务;家居建材市场;建材五金市场", "wgs84经ti": 114.236761, "wgs84纬ti": 30.384847}}, {"type": "Feature", "id": 19135, "geometry": {"type": "Point", "coordinates": [114.05620499986094, 30.569162999872617]}, "properties": {"OBJECTID": 19135, "poiid": "B0FFGFQUOX", "name": "良山机电", "address": "蔡甸经济开发区凤凰山事处新天大道武汉凯威印务有限公司内", "type": "公司企业;公司;机械电子|购物服务;家居建材市场;建材五金市场", "typecode": "170204|060603", "pcode": 420000, "pname": "湖北省", "citycode": 27, "cityname": "武汉市", "adcode": 420114, "adname": "蔡甸区", "business_a": " ", "location": "114.056205,30.569163", "tel": " ", "fetch_time": "19/1/2025 09:20:31", "大类": "公司企业", "中类": "公司", "小类": "机械电子|购物服务;家居建材市场;建材五金市场", "wgs84经ti": 114.05048, "wgs84纬ti": 30.571491}}, {"type": "Feature", "id": 32440, "geometry": {"type": "Point", "coordinates": [114.43169500012425, 30.50329300017188]}, "properties": {"OBJECTID": 32440, "poiid": "B001B0JXO4", "name": "盛隆电气集团研发设计中心", "address": "关东科技工业园3-1号", "type": "公司企业;公司;机械电子|购物服务;家居建材市场;建材五金市场", "typecode": "170204|060603", "pcode": 420000, "pname": "湖北省", "citycode": 27, "cityname": "武汉市", "adcode": 420111, "adname": "洪山区", "business_a": "关山", "location": "114.431695,30.503293", "tel": "027-87586201;027-87592176", "fetch_time": "19/1/2025 12:03:55", "大类": "公司企业", "中类": "公司", "小类": "机械电子|购物服务;家居建材市场;建材五金市场", "wgs84经ti": 114.426192, "wgs84纬ti": 30.505619}}]}