{"type": "FeatureCollection", "features": [{"type": "Feature", "id": 29145, "geometry": {"type": "Point", "coordinates": [114.33777400007011, 30.342629999774715]}, "properties": {"OBJECTID": 29145, "poiid": "B0FFK942KL", "name": "众享仁才", "address": "纸坊大街纸坊苗苗幼儿园西侧约30米", "type": "生活服务;人才市场;人才市场|购物服务;购物相关场所;购物相关场所", "typecode": "070800|060000", "pcode": 420000, "pname": "湖北省", "citycode": 27, "cityname": "武汉市", "adcode": 420115, "adname": "江夏区", "business_a": "纸坊", "location": "114.337774,30.342630", "tel": " ", "fetch_time": "19/1/2025 21:33:17", "大类": "生活服务", "中类": "人才市场", "小类": "人才市场|购物服务;购物相关场所;购物相关场所", "wgs84经ti": 114.3323, "wgs84纬ti": 30.345045}}, {"type": "Feature", "id": 91404, "geometry": {"type": "Point", "coordinates": [114.17120399976488, 30.5071239996729]}, "properties": {"OBJECTID": 91404, "poiid": "B0FFLGFFM5", "name": "HR名企直招", "address": "东风大道天鹅湖山庄(体育中心地铁站C口旁)", "type": "生活服务;人才市场;人才市场|购物服务;购物相关场所;购物相关场所", "typecode": "070800|060000", "pcode": 420000, "pname": "湖北省", "citycode": 27, "cityname": "武汉市", "adcode": 420114, "adname": "蔡甸区", "business_a": "沌口", "location": "114.171204,30.507124", "tel": " ", "fetch_time": "19/1/2025 12:03:55", "大类": "生活服务", "中类": "人才市场", "小类": "人才市场|购物服务;购物相关场所;购物相关场所", "wgs84经ti": 114.165629, "wgs84纬ti": 30.509522}}]}