{"type": "FeatureCollection", "features": [{"type": "Feature", "id": 9452, "geometry": {"type": "Point", "coordinates": [114.31649700003663, 30.35707699960392]}, "properties": {"OBJECTID": 9452, "poiid": "B0FFLH3NBS", "name": "闲暇驿站", "address": "北华街与四贤路交叉口西南40米", "type": "体育休闲服务;休闲场所;休闲场所|餐饮服务;休闲餐饮场所;休闲餐饮场所", "typecode": "080500|050400", "pcode": 420000, "pname": "湖北省", "citycode": 27, "cityname": "武汉市", "adcode": 420115, "adname": "江夏区", "business_a": "纸坊", "location": "114.316497,30.357077", "tel": " ", "fetch_time": "19/1/2025 23:34:49", "大类": "体育休闲服务", "中类": "休闲场所", "小类": "休闲场所|餐饮服务;休闲餐饮场所;休闲餐饮场所", "wgs84经ti": 114.311056, "wgs84纬ti": 30.359531}}]}