{"type": "FeatureCollection", "features": [{"type": "Feature", "id": 934, "geometry": {"type": "Point", "coordinates": [113.98209399963844, 30.58259599970569]}, "properties": {"OBJECTID": 934, "poiid": "B001B15PNX", "name": "张湾街文体中心", "address": "柏林街55号", "type": "体育休闲服务;休闲场所;休闲场所|体育休闲服务;娱乐场所;娱乐场所", "typecode": "080500|080300", "pcode": 420000, "pname": "湖北省", "citycode": 27, "cityname": "武汉市", "adcode": 420114, "adname": "蔡甸区", "business_a": " ", "location": "113.982094,30.582596", "tel": " ", "fetch_time": "19/1/2025 21:22:20", "大类": "体育休闲服务", "中类": "休闲场所", "小类": "休闲场所|体育休闲服务;娱乐场所;娱乐场所", "wgs84经ti": 113.976542, "wgs84纬ti": 30.58512}}, {"type": "Feature", "id": 9456, "geometry": {"type": "Point", "coordinates": [114.43712899980358, 30.44881999994311]}, "properties": {"OBJECTID": 9456, "poiid": "B0FFGPZ8X4", "name": "魅力之城会所", "address": "东湖高新区高新四路万科魅力之城北区会所附近", "type": "体育休闲服务;休闲场所;休闲场所|体育休闲服务;娱乐场所;娱乐场所", "typecode": "080500|080300", "pcode": 420000, "pname": "湖北省", "citycode": 27, "cityname": "武汉市", "adcode": 420115, "adname": "江夏区", "business_a": "藏龙岛", "location": "114.437129,30.448820", "tel": " ", "fetch_time": "19/1/2025 23:36:53", "大类": "体育休闲服务", "中类": "休闲场所", "小类": "休闲场所|体育休闲服务;娱乐场所;娱乐场所", "wgs84经ti": 114.431642, "wgs84纬ti": 30.451168}}, {"type": "Feature", "id": 16266, "geometry": {"type": "Point", "coordinates": [114.75699599986558, 30.79124099957255]}, "properties": {"OBJECTID": 16266, "poiid": "B0FFLGV3Q4", "name": "新港文化娱乐活动室", "address": " ", "type": "体育休闲服务;休闲场所;休闲场所|体育休闲服务;娱乐场所;娱乐场所", "typecode": "080500|080300", "pcode": 420000, "pname": "湖北省", "citycode": 27, "cityname": "武汉市", "adcode": 420117, "adname": "新洲区", "business_a": " ", "location": "114.756996,30.791241", "tel": " ", "fetch_time": "19/1/2025 12:03:55", "大类": "体育休闲服务", "中类": "休闲场所", "小类": "休闲场所|体育休闲服务;娱乐场所;娱乐场所", "wgs84经ti": 114.751722, "wgs84纬ti": 30.793604}}, {"type": "Feature", "id": 16427, "geometry": {"type": "Point", "coordinates": [114.23765600022432, 30.643239000279664]}, "properties": {"OBJECTID": 16427, "poiid": "B0FFHCPSW2", "name": "康居三路活动室", "address": "常青花园康居三路72号", "type": "体育休闲服务;休闲场所;休闲场所|体育休闲服务;娱乐场所;娱乐场所", "typecode": "080500|080300", "pcode": 420000, "pname": "湖北省", "citycode": 27, "cityname": "武汉市", "adcode": 420112, "adname": "东西湖区", "business_a": "常青", "location": "114.237656,30.643239", "tel": " ", "fetch_time": "19/1/2025 12:03:55", "大类": "体育休闲服务", "中类": "休闲场所", "小类": "休闲场所|体育休闲服务;娱乐场所;娱乐场所", "wgs84经ti": 114.232222, "wgs84纬ti": 30.645679}}]}