{"type": "FeatureCollection", "features": [{"type": "Feature", "id": 11567, "geometry": {"type": "Point", "coordinates": [114.37196000005406, 30.403108999980418]}, "properties": {"OBJECTID": 11567, "poiid": "B0FFFQZBVK", "name": "华舟文体中心", "address": "江夏大道武汉信息传播学院对面", "type": "体育休闲服务;休闲场所;休闲场所|科教文化服务;文化宫;文化宫", "typecode": "080500|140800", "pcode": 420000, "pname": "湖北省", "citycode": 27, "cityname": "武汉市", "adcode": 420115, "adname": "江夏区", "business_a": "庙山", "location": "114.371960,30.403109", "tel": "18802787367", "fetch_time": "19/1/2025 08:30:43", "大类": "体育休闲服务", "中类": "休闲场所", "小类": "休闲场所|科教文化服务;文化宫;文化宫", "wgs84经ti": 114.366436, "wgs84纬ti": 30.405459}}]}