{"type": "FeatureCollection", "features": [{"type": "Feature", "id": 3376, "geometry": {"type": "Point", "coordinates": [114.20440300009841, 30.594007999869348]}, "properties": {"OBJECTID": 3376, "poiid": "B0FFFOG31A", "name": "乐艺教育(古萧路)", "address": "古田三路轻轨站2层CD出口乐艺教育基地内", "type": "体育休闲服务;休闲场所;游乐场|科教文化服务;培训机构;培训机构", "typecode": "080501|141400", "pcode": 420000, "pname": "湖北省", "citycode": 27, "cityname": "武汉市", "adcode": 420104, "adname": "硚口区", "business_a": "古田", "location": "114.204403,30.594008", "tel": "027-83316751", "fetch_time": "19/1/2025 21:29:58", "大类": "体育休闲服务", "中类": "休闲场所", "小类": "游乐场|科教文化服务;培训机构;培训机构", "wgs84经ti": 114.198912, "wgs84纬ti": 30.596434}}, {"type": "Feature", "id": 6468, "geometry": {"type": "Point", "coordinates": [114.20443699986777, 30.502362000406038]}, "properties": {"OBJECTID": 6468, "poiid": "B0FFLKPZAV", "name": "巧虎KIDS体验中心", "address": "经济技术开发区江城大道388号永旺梦乐城B馆二楼", "type": "体育休闲服务;休闲场所;游乐场|科教文化服务;培训机构;培训机构", "typecode": "080501|141400", "pcode": 420000, "pname": "湖北省", "citycode": 27, "cityname": "武汉市", "adcode": 420105, "adname": "汉阳区", "business_a": " ", "location": "114.204437,30.502362", "tel": "027-84755377;027-84757377", "fetch_time": "19/1/2025 20:39:15", "大类": "体育休闲服务", "中类": "休闲场所", "小类": "游乐场|科教文化服务;培训机构;培训机构", "wgs84经ti": 114.198954, "wgs84纬ti": 30.50482}}, {"type": "Feature", "id": 14595, "geometry": {"type": "Point", "coordinates": [114.26693899983502, 30.549408999925447]}, "properties": {"OBJECTID": 14595, "poiid": "B0FFFCMH3J", "name": "卡巴kabba(汉阳钟家村)科技活动中心", "address": "汉阳大道139号汉商银座购物中心F5层", "type": "体育休闲服务;休闲场所;游乐场|科教文化服务;培训机构;培训机构", "typecode": "080501|141400", "pcode": 420000, "pname": "湖北省", "citycode": 27, "cityname": "武汉市", "adcode": 420105, "adname": "汉阳区", "business_a": "鹦鹉村", "location": "114.266939,30.549409", "tel": "027-84833033;13971274319", "fetch_time": "19/1/2025 12:03:55", "大类": "体育休闲服务", "中类": "休闲场所", "小类": "游乐场|科教文化服务;培训机构;培训机构", "wgs84经ti": 114.261529, "wgs84纬ti": 30.551882}}]}