{"type": "FeatureCollection", "features": [{"type": "Feature", "id": 2137, "geometry": {"type": "Point", "coordinates": [114.31342499956418, 30.50379299984712]}, "properties": {"OBJECTID": 2137, "poiid": "B001B06075", "name": "中国电信(南湖营业厅)", "address": "恒安路55号", "type": "生活服务;电讯营业厅;中国电信营业厅|公司企业;公司;电信公司|购物服务;家电电子卖场;手机销售", "typecode": "070601|170208|060305", "pcode": 420000, "pname": "湖北省", "citycode": 27, "cityname": "武汉市", "adcode": 420106, "adname": "武昌区", "business_a": "红旗", "location": "114.313425,30.503793", "tel": " ", "fetch_time": "19/1/2025 21:06:44", "大类": "生活服务", "中类": "电讯营业厅", "小类": "中国电信营业厅|公司企业;公司;电信公司|购物服务;家电电子卖场;手机销售", "wgs84经ti": 114.307976, "wgs84纬ti": 30.506219}}, {"type": "Feature", "id": 2190, "geometry": {"type": "Point", "coordinates": [114.26824899999144, 30.617944000215516]}, "properties": {"OBJECTID": 2190, "poiid": "B0FFGA2YQ0", "name": "中国电信:", "address": " ", "type": "生活服务;电讯营业厅;中国电信营业厅|公司企业;公司;电信公司|购物服务;家电电子卖场;手机销售", "typecode": "070601|170208|060305", "pcode": 420000, "pname": "湖北省", "citycode": 27, "cityname": "武汉市", "adcode": 420103, "adname": "江汉区", "business_a": "新华", "location": "114.268249,30.617944", "tel": "027-85320189", "fetch_time": "19/1/2025 21:06:49", "大类": "生活服务", "中类": "电讯营业厅", "小类": "中国电信营业厅|公司企业;公司;电信公司|购物服务;家电电子卖场;手机销售", "wgs84经ti": 114.262833, "wgs84纬ti": 30.62039}}, {"type": "Feature", "id": 2808, "geometry": {"type": "Point", "coordinates": [114.33929800020258, 30.545754000446834]}, "properties": {"OBJECTID": 2808, "poiid": "B0FFH81LD8", "name": "中国电信(洪山广场营业厅)", "address": "洪山街道洪山路特一号", "type": "生活服务;电讯营业厅;中国电信营业厅|公司企业;公司;电信公司|购物服务;家电电子卖场;手机销售", "typecode": "070601|170208|060305", "pcode": 420000, "pname": "湖北省", "citycode": 27, "cityname": "武汉市", "adcode": 420106, "adname": "武昌区", "business_a": "水果湖", "location": "114.339298,30.545754", "tel": " ", "fetch_time": "19/1/2025 21:07:05", "大类": "生活服务", "中类": "电讯营业厅", "小类": "中国电信营业厅|公司企业;公司;电信公司|购物服务;家电电子卖场;手机销售", "wgs84经ti": 114.333804, "wgs84纬ti": 30.548118}}]}