{"type": "FeatureCollection", "features": [{"type": "Feature", "id": 101091, "geometry": {"type": "Point", "coordinates": [114.39650499970605, 30.488887000434772]}, "properties": {"OBJECTID": 101091, "poiid": "B0J3RL3V26", "name": "同学广场真功夫充换站", "address": "民族大道与宽和路交叉口东南60米", "type": "生活服务;共享设备;充电宝|汽车服务;汽车服务相关;汽车服务相关", "typecode": "072101|010000", "pcode": 420000, "pname": "湖北省", "citycode": 27, "cityname": "武汉市", "adcode": 420111, "adname": "洪山区", "business_a": "光谷", "location": "114.396505,30.488887", "tel": " ", "fetch_time": "19/1/2025 18:15:59", "大类": "生活服务", "中类": "共享设备", "小类": "充电宝|汽车服务;汽车服务相关;汽车服务相关", "wgs84经ti": 114.390965, "wgs84纬ti": 30.491198}}]}