{"type": "FeatureCollection", "features": [{"type": "Feature", "id": 11956, "geometry": {"type": "Point", "coordinates": [114.37304499972697, 31.17485400031194]}, "properties": {"OBJECTID": 11956, "poiid": "B001B1DKFC", "name": "黄家田", "address": "姚集镇仙姑寨村", "type": "地名地址信息;普通地名;村庄级地名|餐饮服务;餐饮相关场所;餐饮相关", "typecode": "190108|050000", "pcode": 420000, "pname": "湖北省", "citycode": 27, "cityname": "武汉市", "adcode": 420116, "adname": "黄陂区", "business_a": " ", "location": "114.373045,31.174854", "tel": " ", "fetch_time": "19/1/2025 20:53:18", "大类": "地名地址信息", "中类": "普通地名", "小类": "村庄级地名|餐饮服务;餐饮相关场所;餐饮相关", "wgs84经ti": 114.367452, "wgs84纬ti": 31.176838}}]}