{"type": "FeatureCollection", "features": [{"type": "Feature", "id": 1688, "geometry": {"type": "Point", "coordinates": [114.03429300022185, 30.61991899956223]}, "properties": {"OBJECTID": 1688, "poiid": "B001B1D9RE", "name": "青锋大队", "address": "惠安大道", "type": "地名地址信息;普通地名;村庄级地名|政府机构及社会团体;政府及社会团体相关;政府及社会团体相关", "typecode": "190108|130000", "pcode": 420000, "pname": "湖北省", "citycode": 27, "cityname": "武汉市", "adcode": 420112, "adname": "东西湖区", "business_a": " ", "location": "114.034293,30.619919", "tel": " ", "fetch_time": "19/1/2025 21:20:37", "大类": "地名地址信息", "中类": "普通地名", "小类": "村庄级地名|政府机构及社会团体;政府及社会团体相关;政府及社会团体相关", "wgs84经ti": 114.028603, "wgs84纬ti": 30.622276}}, {"type": "Feature", "id": 153255, "geometry": {"type": "Point", "coordinates": [114.03429300022185, 30.61991899956223]}, "properties": {"OBJECTID": 153255, "poiid": "B001B1D9RE", "name": "青锋大队", "address": "惠安大道", "type": "地名地址信息;普通地名;村庄级地名|政府机构及社会团体;政府及社会团体相关;政府及社会团体相关", "typecode": "190108|130000", "pcode": 420000, "pname": "湖北省", "citycode": 27, "cityname": "武汉市", "adcode": 420112, "adname": "东西湖区", "business_a": " ", "location": "114.034293,30.619919", "tel": " ", "fetch_time": "19/1/2025 06:20:29", "大类": "地名地址信息", "中类": "普通地名", "小类": "村庄级地名|政府机构及社会团体;政府及社会团体相关;政府及社会团体相关", "wgs84经ti": 114.028603, "wgs84纬ti": 30.622276}}]}