{"type": "FeatureCollection", "features": [{"type": "Feature", "id": 3075, "geometry": {"type": "Point", "coordinates": [114.08365400033188, 30.705893000061963]}, "properties": {"OBJECTID": 3075, "poiid": "B0FFITNY2Q", "name": "郁金香主题公园江南水乡园", "address": "郁金香主题公园内部", "type": "风景名胜;风景名胜;风景名胜|体育休闲服务;体育休闲服务场所;体育休闲服务场所", "typecode": "110200|080000", "pcode": 420000, "pname": "湖北省", "citycode": 27, "cityname": "武汉市", "adcode": 420112, "adname": "东西湖区", "business_a": " ", "location": "114.083654,30.705893", "tel": " ", "fetch_time": "19/1/2025 21:03:03", "大类": "风景名胜", "中类": "风景名胜", "小类": "风景名胜|体育休闲服务;体育休闲服务场所;体育休闲服务场所", "wgs84经ti": 114.077899, "wgs84纬ti": 30.708128}}, {"type": "Feature", "id": 5177, "geometry": {"type": "Point", "coordinates": [114.08365400033188, 30.705893000061963]}, "properties": {"OBJECTID": 5177, "poiid": "B0FFITNY2Q", "name": "郁金香主题公园江南水乡园", "address": "郁金香主题公园内部", "type": "风景名胜;风景名胜;风景名胜|体育休闲服务;体育休闲服务场所;体育休闲服务场所", "typecode": "110200|080000", "pcode": 420000, "pname": "湖北省", "citycode": 27, "cityname": "武汉市", "adcode": 420112, "adname": "东西湖区", "business_a": " ", "location": "114.083654,30.705893", "tel": " ", "fetch_time": "19/1/2025 07:17:57", "大类": "风景名胜", "中类": "风景名胜", "小类": "风景名胜|体育休闲服务;体育休闲服务场所;体育休闲服务场所", "wgs84经ti": 114.077899, "wgs84纬ti": 30.708128}}]}