{"type": "FeatureCollection", "features": [{"type": "Feature", "id": 9873, "geometry": {"type": "Point", "coordinates": [114.34677499966654, 30.547345000071743]}, "properties": {"OBJECTID": 9873, "poiid": "B001B0JZ1Q", "name": "水果湖艺术学校", "address": "水果湖路186附4号", "type": "科教文化服务;培训机构;培训机构|科教文化服务;学校;学校", "typecode": "141400|141200", "pcode": 420000, "pname": "湖北省", "citycode": 27, "cityname": "武汉市", "adcode": 420106, "adname": "武昌区", "business_a": "水果湖", "location": "114.346775,30.547345", "tel": " ", "fetch_time": "19/1/2025 21:30:07", "大类": "科教文化服务", "中类": "培训机构", "小类": "培训机构|科教文化服务;学校;学校", "wgs84经ti": 114.341269, "wgs84纬ti": 30.549694}}, {"type": "Feature", "id": 14631, "geometry": {"type": "Point", "coordinates": [114.33415300036074, 31.175601999732578]}, "properties": {"OBJECTID": 14631, "poiid": "B001B0K6OB", "name": "武汉理工大学木兰教学实践基地", "address": "梅店水库溢洪公路桥附近", "type": "科教文化服务;培训机构;培训机构|科教文化服务;学校;学校", "typecode": "141400|141200", "pcode": 420000, "pname": "湖北省", "citycode": 27, "cityname": "武汉市", "adcode": 420116, "adname": "黄陂区", "business_a": " ", "location": "114.334153,31.175602", "tel": " ", "fetch_time": "19/1/2025 20:44:21", "大类": "科教文化服务", "中类": "培训机构", "小类": "培训机构|科教文化服务;学校;学校", "wgs84经ti": 114.328612, "wgs84纬ti": 31.177648}}, {"type": "Feature", "id": 17829, "geometry": {"type": "Point", "coordinates": [114.31693599959681, 30.509856999800775]}, "properties": {"OBJECTID": 17829, "poiid": "B001B1C3PH", "name": "迈开尔学校", "address": "雅安街169-171号", "type": "科教文化服务;培训机构;培训机构|科教文化服务;学校;学校", "typecode": "141400|141200", "pcode": 420000, "pname": "湖北省", "citycode": 27, "cityname": "武汉市", "adcode": 420106, "adname": "武昌区", "business_a": "丁字桥", "location": "114.316936,30.509857", "tel": " ", "fetch_time": "19/1/2025 08:42:31", "大类": "科教文化服务", "中类": "培训机构", "小类": "培训机构|科教文化服务;学校;学校", "wgs84经ti": 114.311481, "wgs84纬ti": 30.512275}}, {"type": "Feature", "id": 34562, "geometry": {"type": "Point", "coordinates": [114.34677499966654, 30.547345000071743]}, "properties": {"OBJECTID": 34562, "poiid": "B001B0JZ1Q", "name": "水果湖艺术学校", "address": "水果湖路186附4号(洪山路地铁站D口步行370米)", "type": "科教文化服务;培训机构;培训机构|科教文化服务;学校;学校", "typecode": "141400|141200", "pcode": 420000, "pname": "湖北省", "citycode": 27, "cityname": "武汉市", "adcode": 420106, "adname": "武昌区", "business_a": "水果湖", "location": "114.346775,30.547345", "tel": " ", "fetch_time": "19/1/2025 06:51:26", "大类": "科教文化服务", "中类": "培训机构", "小类": "培训机构|科教文化服务;学校;学校", "wgs84经ti": 114.341269, "wgs84纬ti": 30.549694}}]}