{"type": "FeatureCollection", "features": [{"type": "Feature", "id": 29259, "geometry": {"type": "Point", "coordinates": [114.26687400043488, 30.57884300020436]}, "properties": {"OBJECTID": 29259, "poiid": "B0G1GLNS0X", "name": "藤门国际教育", "address": "解放大道634号新世界中心写字楼A座10层1011号", "type": "科教文化服务;培训机构;培训机构|生活服务;中介机构;中介机构", "typecode": "141400|071600", "pcode": 420000, "pname": "湖北省", "citycode": 27, "cityname": "武汉市", "adcode": 420104, "adname": "硚口区", "business_a": "武广", "location": "114.266874,30.578843", "tel": " ", "fetch_time": "19/1/2025 12:03:55", "大类": "科教文化服务", "中类": "培训机构", "小类": "培训机构|生活服务;中介机构;中介机构", "wgs84经ti": 114.261462, "wgs84纬ti": 30.581306}}]}