{"type": "FeatureCollection", "features": [{"type": "Feature", "id": 15197, "geometry": {"type": "Point", "coordinates": [114.31771100026253, 30.547968000023218]}, "properties": {"OBJECTID": 15197, "poiid": "B001B17096", "name": "湖北省影视艺术中心", "address": "中山路376号(小东门地铁站D口步行320米)", "type": "体育休闲服务;影剧院;剧场|科教文化服务;美术馆;美术馆", "typecode": "080603|140400", "pcode": 420000, "pname": "湖北省", "citycode": 27, "cityname": "武汉市", "adcode": 420106, "adname": "武昌区", "business_a": "小东门", "location": "114.317711,30.547968", "tel": " ", "fetch_time": "19/1/2025 12:03:55", "大类": "体育休闲服务", "中类": "影剧院", "小类": "剧场|科教文化服务;美术馆;美术馆", "wgs84经ti": 114.312252, "wgs84纬ti": 30.550372}}]}