{"type": "FeatureCollection", "features": [{"type": "Feature", "id": 8424, "geometry": {"type": "Point", "coordinates": [114.39189400020803, 30.589836999977592]}, "properties": {"OBJECTID": 8424, "poiid": "B0FFK1J92O", "name": "武汉欢乐谷-海盗船舞台", "address": "东湖生态旅游风景区欢乐大道196号飓风湾内", "type": "体育休闲服务;影剧院;剧场|体育休闲服务;休闲场所;游乐场", "typecode": "080603|080501", "pcode": 420000, "pname": "湖北省", "citycode": 27, "cityname": "武汉市", "adcode": 420106, "adname": "武昌区", "business_a": " ", "location": "114.391894,30.589837", "tel": "027-88518861", "fetch_time": "19/1/2025 22:40:21", "大类": "体育休闲服务", "中类": "影剧院", "小类": "剧场|体育休闲服务;休闲场所;游乐场", "wgs84经ti": 114.386345, "wgs84纬ti": 30.592116}}]}