{"type": "FeatureCollection", "features": [{"type": "Feature", "id": 4263, "geometry": {"type": "Point", "coordinates": [114.31480700034285, 30.34744299959482]}, "properties": {"OBJECTID": 4263, "poiid": "B0FFFRGOLM", "name": "武汉市江夏区博物馆", "address": "纸坊兴新街269号", "type": "科教文化服务;博物馆;博物馆|科教文化服务;文化宫;文化宫", "typecode": "140100|140800", "pcode": 420000, "pname": "湖北省", "citycode": 27, "cityname": "武汉市", "adcode": 420115, "adname": "江夏区", "business_a": "纸坊", "location": "114.314807,30.347443", "tel": "027-87015451", "fetch_time": "19/1/2025 21:17:24", "大类": "科教文化服务", "中类": "博物馆", "小类": "博物馆|科教文化服务;文化宫;文化宫", "wgs84经ti": 114.30937, "wgs84纬ti": 30.349901}}]}