{"type": "FeatureCollection", "features": [{"type": "Feature", "id": 45685, "geometry": {"type": "Point", "coordinates": [114.28410800018412, 30.575603000078445]}, "properties": {"OBJECTID": 45685, "poiid": "B0FFGAI2Z6", "name": "创新(前进一路店)", "address": "前进街办事处前进四路72号军民停车场旁巷子内2单元", "type": "购物服务;家电电子卖场;数码电子|购物服务;个人用品/化妆品店;其它个人用品店|生活服务;美容美发店;美容美发店", "typecode": "060306|061400|071100", "pcode": 420000, "pname": "湖北省", "citycode": 27, "cityname": "武汉市", "adcode": 420103, "adname": "江汉区", "business_a": "前进", "location": "114.284108,30.575603", "tel": "027-85811583;027-85891829", "fetch_time": "19/1/2025 22:09:09", "大类": "购物服务", "中类": "家电电子卖场", "小类": "数码电子|购物服务;个人用品/化妆品店;其它个人用品店|生活服务;美容美发店;美容美发店", "wgs84经ti": 114.278688, "wgs84纬ti": 30.578051}}]}