{"type": "FeatureCollection", "features": [{"type": "Feature", "id": 1929, "geometry": {"type": "Point", "coordinates": [114.09362399964789, 30.458764999904872]}, "properties": {"OBJECTID": 1929, "poiid": "B0GRJROLB4", "name": "七彩音阶", "address": "后官湖大道薛峰社区", "type": "体育休闲服务;运动场馆;溜冰场|科教文化服务;培训机构;培训机构", "typecode": "080107|141400", "pcode": 420000, "pname": "湖北省", "citycode": 27, "cityname": "武汉市", "adcode": 420114, "adname": "蔡甸区", "business_a": " ", "location": "114.093624,30.458765", "tel": " ", "fetch_time": "19/1/2025 21:16:57", "大类": "体育休闲服务", "中类": "运动场馆", "小类": "溜冰场|科教文化服务;培训机构;培训机构", "wgs84经ti": 114.087893, "wgs84纬ti": 30.461089}}]}