{"type": "FeatureCollection", "features": [{"type": "Feature", "id": 504, "geometry": {"type": "Point", "coordinates": [114.22855200037463, 30.632091999746024]}, "properties": {"OBJECTID": 504, "poiid": "B001B0I0G4", "name": "东方马城国际赛马场", "address": "金银湖金南一路1号", "type": "体育休闲服务;运动场馆;赛马场", "typecode": "080116", "pcode": 420000, "pname": "湖北省", "citycode": 27, "cityname": "武汉市", "adcode": 420112, "adname": "东西湖区", "business_a": "常青", "location": "114.228552,30.632092", "tel": "027-85880008;027-83912121", "fetch_time": "19/1/2025 21:16:22", "大类": "体育休闲服务", "中类": "运动场馆", "小类": "赛马场", "wgs84经ti": 114.223106, "wgs84纬ti": 30.634531}}, {"type": "Feature", "id": 505, "geometry": {"type": "Point", "coordinates": [114.46286400037343, 30.962979999927086]}, "properties": {"OBJECTID": 505, "poiid": "B0FFG1SX2X", "name": "骑马驿站-跑马场", "address": "王家河镇聂家岗武汉木兰草原骑马驿站内", "type": "体育休闲服务;运动场馆;赛马场", "typecode": "080116", "pcode": 420000, "pname": "湖北省", "citycode": 27, "cityname": "武汉市", "adcode": 420116, "adname": "黄陂区", "business_a": " ", "location": "114.462864,30.962980", "tel": " ", "fetch_time": "19/1/2025 21:16:22", "大类": "体育休闲服务", "中类": "运动场馆", "小类": "赛马场", "wgs84经ti": 114.457403, "wgs84纬ti": 30.965143}}, {"type": "Feature", "id": 506, "geometry": {"type": "Point", "coordinates": [114.22831200009875, 30.632335000160197]}, "properties": {"OBJECTID": 506, "poiid": "B001B0IZML", "name": "武汉东西湖东方马城", "address": "金南一路1号", "type": "体育休闲服务;运动场馆;赛马场", "typecode": "080116", "pcode": 420000, "pname": "湖北省", "citycode": 27, "cityname": "武汉市", "adcode": 420112, "adname": "东西湖区", "business_a": "常青", "location": "114.228312,30.632335", "tel": "027-85880008;027-85882572", "fetch_time": "19/1/2025 21:16:22", "大类": "体育休闲服务", "中类": "运动场馆", "小类": "赛马场", "wgs84经ti": 114.222866, "wgs84纬ti": 30.634774}}, {"type": "Feature", "id": 18115, "geometry": {"type": "Point", "coordinates": [114.3277570003853, 30.33037500030605]}, "properties": {"OBJECTID": 18115, "poiid": "B0KGXZORUK", "name": "青龙山骑马场", "address": "青龙路445号", "type": "体育休闲服务;运动场馆;赛马场", "typecode": "080116", "pcode": 420000, "pname": "湖北省", "citycode": 27, "cityname": "武汉市", "adcode": 420115, "adname": "江夏区", "business_a": " ", "location": "114.327757,30.330375", "tel": "13387632955", "fetch_time": "19/1/2025 07:55:57", "大类": "体育休闲服务", "中类": "运动场馆", "小类": "赛马场", "wgs84经ti": 114.3223, "wgs84纬ti": 30.332811}}, {"type": "Feature", "id": 21347, "geometry": {"type": "Point", "coordinates": [114.22855200037463, 30.632091999746024]}, "properties": {"OBJECTID": 21347, "poiid": "B001B0I0G4", "name": "东方马城国际赛马场", "address": "金银湖金南一路1号", "type": "体育休闲服务;运动场馆;赛马场", "typecode": "080116", "pcode": 420000, "pname": "湖北省", "citycode": 27, "cityname": "武汉市", "adcode": 420112, "adname": "东西湖区", "business_a": "常青", "location": "114.228552,30.632092", "tel": "027-83912121;027-85880008", "fetch_time": "19/1/2025 07:17:10", "大类": "体育休闲服务", "中类": "运动场馆", "小类": "赛马场", "wgs84经ti": 114.223106, "wgs84纬ti": 30.634531}}]}