{"type": "FeatureCollection", "features": [{"type": "Feature", "id": 1, "geometry": {"type": "Point", "coordinates": [114.34735899961822, 30.515253000425673]}, "properties": {"OBJECTID": 1, "poiid": "B0L6TUDAO4", "name": "武汉宠物市场猫舍犬舍购宠基地优宠", "address": "珞狮路210号博文花园3栋11层1109", "type": "虚拟数据;虚拟店铺;虚拟店铺", "typecode": "980200", "pcode": 420000, "pname": "湖北省", "citycode": 27, "cityname": "武汉市", "adcode": 420111, "adname": "洪山区", "business_a": "石牌岭", "location": "114.347359,30.515253", "tel": "17728448095", "fetch_time": "19/1/2025 00:49:36", "大类": "虚拟数据", "中类": "虚拟店铺", "小类": "虚拟店铺", "wgs84经ti": 114.341855, "wgs84纬ti": 30.517612}}, {"type": "Feature", "id": 2, "geometry": {"type": "Point", "coordinates": [114.29870499973606, 30.634263000037492]}, "properties": {"OBJECTID": 2, "poiid": "B0L6CMCV5N", "name": "电脑售后维修服务中心(武汉)", "address": "新地东方华府9号楼1层4室", "type": "虚拟数据;虚拟店铺;虚拟店铺", "typecode": "980200", "pcode": 420000, "pname": "湖北省", "citycode": 27, "cityname": "武汉市", "adcode": 420102, "adname": "江岸区", "business_a": "二七", "location": "114.298705,30.634263", "tel": "027-61524641", "fetch_time": "19/1/2025 04:02:56", "大类": "虚拟数据", "中类": "虚拟店铺", "小类": "虚拟店铺", "wgs84经ti": 114.293265, "wgs84纬ti": 30.636667}}, {"type": "Feature", "id": 3, "geometry": {"type": "Point", "coordinates": [114.38362900037816, 30.721898999839027]}, "properties": {"OBJECTID": 3, "poiid": "B0K0S5SH8A", "name": "全都修电脑维修售后服务中心-武汉店", "address": "江夏区纸坊街西交路商业街长宏楼9号1-2层51", "type": "虚拟数据;虚拟店铺;虚拟店铺", "typecode": "980200", "pcode": 420000, "pname": "湖北省", "citycode": 27, "cityname": "武汉市", "adcode": 420116, "adname": "黄陂区", "business_a": "长江新区", "location": "114.383629,30.721899", "tel": "4006838658", "fetch_time": "19/1/2025 04:56:25", "大类": "虚拟数据", "中类": "虚拟店铺", "小类": "虚拟店铺", "wgs84经ti": 114.37807, "wgs84纬ti": 30.724125}}, {"type": "Feature", "id": 4, "geometry": {"type": "Point", "coordinates": [114.34318899977256, 30.555063999903723]}, "properties": {"OBJECTID": 4, "poiid": "B0LBZRLGKX", "name": "武昌大型猫舍犬舍宠物基地市场", "address": "中北路86号汉街总部国际A座2702室", "type": "虚拟数据;虚拟店铺;虚拟店铺", "typecode": "980200", "pcode": 420000, "pname": "湖北省", "citycode": 27, "cityname": "武汉市", "adcode": 420106, "adname": "武昌区", "business_a": "水果湖", "location": "114.343189,30.555064", "tel": "13114363329", "fetch_time": "19/1/2025 07:18:37", "大类": "虚拟数据", "中类": "虚拟店铺", "小类": "虚拟店铺", "wgs84经ti": 114.337688, "wgs84纬ti": 30.557417}}]}