{"type": "FeatureCollection", "features": [{"type": "Feature", "id": 28495, "geometry": {"type": "Point", "coordinates": [114.4877369998627, 30.51353200020168]}, "properties": {"OBJECTID": 28495, "poiid": "B0FFGH8SFR", "name": "石门峰纪念公园", "address": "石门峰路9号", "type": "生活服务;丧葬设施;陵园|风景名胜;风景名胜;风景名胜", "typecode": "071901|110200", "pcode": 420000, "pname": "湖北省", "citycode": 27, "cityname": "武汉市", "adcode": 420111, "adname": "洪山区", "business_a": " ", "location": "114.487737,30.513532", "tel": "027-87635632", "fetch_time": "19/1/2025 21:13:34", "大类": "生活服务", "中类": "丧葬设施", "小类": "陵园|风景名胜;风景名胜;风景名胜", "wgs84经ti": 114.482403, "wgs84纬ti": 30.515982}}, {"type": "Feature", "id": 30051, "geometry": {"type": "Point", "coordinates": [114.36168300007046, 30.0333369999027]}, "properties": {"OBJECTID": 30051, "poiid": "B001B0K4XZ", "name": "贺胜桥北伐阵亡将士陵园", "address": "贺胜桥街45号", "type": "生活服务;丧葬设施;陵园|风景名胜;风景名胜;风景名胜", "typecode": "071901|110200", "pcode": 420000, "pname": "湖北省", "citycode": 27, "cityname": "武汉市", "adcode": 420115, "adname": "江夏区", "business_a": " ", "location": "114.361683,30.033337", "tel": " ", "fetch_time": "19/1/2025 21:35:04", "大类": "生活服务", "中类": "丧葬设施", "小类": "陵园|风景名胜;风景名胜;风景名胜", "wgs84经ti": 114.356202, "wgs84纬ti": 30.035727}}, {"type": "Feature", "id": 41246, "geometry": {"type": "Point", "coordinates": [114.36555499966357, 30.51289300041168]}, "properties": {"OBJECTID": 41246, "poiid": "B0FFF3OMUJ", "name": "黎元洪墓", "address": "华中师范大学(东门)", "type": "生活服务;丧葬设施;陵园|风景名胜;风景名胜;风景名胜", "typecode": "071901|110200", "pcode": 420000, "pname": "湖北省", "citycode": 27, "cityname": "武汉市", "adcode": 420111, "adname": "洪山区", "business_a": "陈家湾", "location": "114.365555,30.512893", "tel": " ", "fetch_time": "19/1/2025 22:58:21", "大类": "生活服务", "中类": "丧葬设施", "小类": "陵园|风景名胜;风景名胜;风景名胜", "wgs84经ti": 114.360028, "wgs84纬ti": 30.515224}}, {"type": "Feature", "id": 102703, "geometry": {"type": "Point", "coordinates": [114.33680500035052, 30.53269900005887]}, "properties": {"OBJECTID": 102703, "poiid": "B0FFHFV5HT", "name": "施洋烈士纪念馆(装修中)", "address": "武珞路509附1号(宝通寺地铁站D口步行330米)", "type": "生活服务;丧葬设施;陵园|风景名胜;风景名胜;风景名胜", "typecode": "071901|110200", "pcode": 420000, "pname": "湖北省", "citycode": 27, "cityname": "武汉市", "adcode": 420106, "adname": "武昌区", "business_a": "中南路/中南", "location": "114.336805,30.532699", "tel": "027-87641163", "fetch_time": "19/1/2025 06:52:47", "大类": "生活服务", "中类": "丧葬设施", "小类": "陵园|风景名胜;风景名胜;风景名胜", "wgs84经ti": 114.331316, "wgs84纬ti": 30.535072}}, {"type": "Feature", "id": 103140, "geometry": {"type": "Point", "coordinates": [114.36168300007046, 30.0333369999027]}, "properties": {"OBJECTID": 103140, "poiid": "B001B0K4XZ", "name": "贺胜桥北伐阵亡将士陵园", "address": "贺胜桥街45号", "type": "生活服务;丧葬设施;陵园|风景名胜;风景名胜;风景名胜", "typecode": "071901|110200", "pcode": 420000, "pname": "湖北省", "citycode": 27, "cityname": "武汉市", "adcode": 420115, "adname": "江夏区", "business_a": " ", "location": "114.361683,30.033337", "tel": " ", "fetch_time": "19/1/2025 06:41:14", "大类": "生活服务", "中类": "丧葬设施", "小类": "陵园|风景名胜;风景名胜;风景名胜", "wgs84经ti": 114.356202, "wgs84纬ti": 30.035727}}]}