{"type": "FeatureCollection", "features": [{"type": "Feature", "id": 15128, "geometry": {"type": "Point", "coordinates": [114.33680500035052, 30.53269900005887]}, "properties": {"OBJECTID": 15128, "poiid": "B0FFHFV5HT", "name": "施洋烈士纪念馆", "address": "武珞路509附1号", "type": "生活服务;丧葬设施;陵园|风景名胜;风景名胜;红色景区|风景名胜;风景名胜;纪念馆", "typecode": "071901|110210|110204", "pcode": 420000, "pname": "湖北省", "citycode": 27, "cityname": "武汉市", "adcode": 420106, "adname": "武昌区", "business_a": "中南路/中南", "location": "114.336805,30.532699", "tel": "027-87641163", "fetch_time": "19/1/2025 21:17:27", "大类": "生活服务", "中类": "丧葬设施", "小类": "陵园|风景名胜;风景名胜;红色景区|风景名胜;风景名胜;纪念馆", "wgs84经ti": 114.331316, "wgs84纬ti": 30.535072}}]}