{"type": "FeatureCollection", "features": [{"type": "Feature", "id": 48150, "geometry": {"type": "Point", "coordinates": [114.15105999981915, 30.64873300002796]}, "properties": {"OBJECTID": 48150, "poiid": "B0FFINNULN", "name": "幸福驿站", "address": "吴家山翡丽公馆12栋物业服务中心", "type": "生活服务;中介机构;中介机构|住宿服务;旅馆招待所;旅馆招待所", "typecode": "071600|100200", "pcode": 420000, "pname": "湖北省", "citycode": 27, "cityname": "武汉市", "adcode": 420112, "adname": "东西湖区", "business_a": "三店", "location": "114.151060,30.648733", "tel": " ", "fetch_time": "19/1/2025 08:36:25", "大类": "生活服务", "中类": "中介机构", "小类": "中介机构|住宿服务;旅馆招待所;旅馆招待所", "wgs84经ti": 114.145415, "wgs84纬ti": 30.651042}}]}