{"type": "FeatureCollection", "features": [{"type": "Feature", "id": 14664, "geometry": {"type": "Point", "coordinates": [114.29897799973492, 30.64009400003812]}, "properties": {"OBJECTID": 14664, "poiid": "B0FFL82MJE", "name": "爱享家", "address": "后湖街街道兴业路165号东方世家2栋1楼", "type": "生活服务;中介机构;中介机构|购物服务;专卖店;专营店", "typecode": "071600|061200", "pcode": 420000, "pname": "湖北省", "citycode": 27, "cityname": "武汉市", "adcode": 420102, "adname": "江岸区", "business_a": "后湖", "location": "114.298978,30.640094", "tel": " ", "fetch_time": "19/1/2025 21:04:39", "大类": "生活服务", "中类": "中介机构", "小类": "中介机构|购物服务;专卖店;专营店", "wgs84经ti": 114.293538, "wgs84纬ti": 30.642495}}]}