{"type": "FeatureCollection", "features": [{"type": "Feature", "id": 92888, "geometry": {"type": "Point", "coordinates": [114.29254399980584, 30.476372999814146]}, "properties": {"OBJECTID": 92888, "poiid": "B0J0FUKP5D", "name": "夏威驿意式餐厅(龙湖武汉白沙天街A馆店)", "address": "张家湾白沙三路龙湖天街A馆4楼", "type": "餐饮服务;外国餐厅;意式菜品餐厅|餐饮服务;外国餐厅;牛扒店(扒房)", "typecode": "050205|050211", "pcode": 420000, "pname": "湖北省", "citycode": 27, "cityname": "武汉市", "adcode": 420111, "adname": "洪山区", "business_a": "张家湾", "location": "114.292544,30.476373", "tel": "027-86781697;17689395194", "fetch_time": "19/1/2025 06:53:49", "大类": "餐饮服务", "中类": "外国餐厅", "小类": "意式菜品餐厅|餐饮服务;外国餐厅;牛扒店(扒房)", "wgs84经ti": 114.287125, "wgs84纬ti": 30.478841}}]}