{"type": "FeatureCollection", "features": [{"type": "Feature", "id": 364, "geometry": {"type": "Point", "coordinates": [114.1659759996927, 30.56773299957831]}, "properties": {"OBJECTID": 364, "poiid": "B0FFFFP4GT", "name": "武汉市建银经贸有限公司", "address": "汉阳大道黄金口工业园金色环路18-5号建银汽贸园", "type": "汽车销售;海马汽车销售;海马汽车销售|汽车维修;海马汽车维修;海马汽车维修", "typecode": "023100|033200", "pcode": 420000, "pname": "湖北省", "citycode": 27, "cityname": "武汉市", "adcode": 420105, "adname": "汉阳区", "business_a": " ", "location": "114.165976,30.567733", "tel": " ", "fetch_time": "19/1/2025 20:54:06", "大类": "汽车销售", "中类": "海马汽车销售", "小类": "海马汽车销售|汽车维修;海马汽车维修;海马汽车维修", "wgs84经ti": 114.160381, "wgs84纬ti": 30.570101}}]}