{"type": "FeatureCollection", "features": [{"type": "Feature", "id": 10029, "geometry": {"type": "Point", "coordinates": [114.29772500040849, 30.578133999884244]}, "properties": {"OBJECTID": 10029, "poiid": "B0FFF0F1DX", "name": "中山颐养园", "address": "上海路1附1号", "type": "体育休闲服务;度假疗养场所;疗养院|生活服务;洗浴推拿场所;洗浴推拿场所", "typecode": "080402|071400", "pcode": 420000, "pname": "湖北省", "citycode": 27, "cityname": "武汉市", "adcode": 420102, "adname": "江岸区", "business_a": "江滩", "location": "114.297725,30.578134", "tel": " ", "fetch_time": "19/1/2025 09:08:51", "大类": "体育休闲服务", "中类": "度假疗养场所", "小类": "疗养院|生活服务;洗浴推拿场所;洗浴推拿场所", "wgs84经ti": 114.292291, "wgs84纬ti": 30.580562}}]}