{"type": "FeatureCollection", "features": [{"type": "Feature", "id": 971, "geometry": {"type": "Point", "coordinates": [114.19237400025997, 30.5311830002953]}, "properties": {"OBJECTID": 971, "poiid": "B0HA6CC2WO", "name": "RENAULT", "address": "龙阳大道与龙阳大道高架交叉口东北140米", "type": "汽车销售;雷诺特约销售;雷诺销售", "typecode": "020800", "pcode": 420000, "pname": "湖北省", "citycode": 27, "cityname": "武汉市", "adcode": 420114, "adname": "蔡甸区", "business_a": "升官渡", "location": "114.192374,30.531183", "tel": " ", "fetch_time": "19/1/2025 20:43:56", "大类": "汽车销售", "中类": "雷诺特约销售", "小类": "雷诺销售", "wgs84经ti": 114.186857, "wgs84纬ti": 30.533612}}, {"type": "Feature", "id": 973, "geometry": {"type": "Point", "coordinates": [114.19209900016881, 30.530733000227826]}, "properties": {"OBJECTID": 973, "poiid": "B0G13G0N9H", "name": "东风雷诺品牌汽车(武汉鸿泰沌阳专营店)", "address": "四新地区管委会武汉市经济技术开发区东风大道3号", "type": "汽车销售;雷诺特约销售;雷诺销售", "typecode": "020800", "pcode": 420000, "pname": "湖北省", "citycode": 27, "cityname": "武汉市", "adcode": 420114, "adname": "蔡甸区", "business_a": "升官渡", "location": "114.192099,30.530733", "tel": "027-84555728", "fetch_time": "19/1/2025 20:43:56", "大类": "汽车销售", "中类": "雷诺特约销售", "小类": "雷诺销售", "wgs84经ti": 114.186582, "wgs84纬ti": 30.533162}}, {"type": "Feature", "id": 2135, "geometry": {"type": "Point", "coordinates": [114.14728700029491, 30.560280000321825]}, "properties": {"OBJECTID": 2135, "poiid": "B0FFLFEBNC", "name": "东风雷诺", "address": "汉阳大道董家店地铁四号线黄金口站", "type": "汽车销售;雷诺特约销售;雷诺销售", "typecode": "020800", "pcode": 420000, "pname": "湖北省", "citycode": 27, "cityname": "武汉市", "adcode": 420105, "adname": "汉阳区", "business_a": " ", "location": "114.147287,30.560280", "tel": " ", "fetch_time": "19/1/2025 08:58:36", "大类": "汽车销售", "中类": "雷诺特约销售", "小类": "雷诺销售", "wgs84经ti": 114.14164, "wgs84纬ti": 30.562618}}, {"type": "Feature", "id": 3942, "geometry": {"type": "Point", "coordinates": [114.19209900016881, 30.530733000227826]}, "properties": {"OBJECTID": 3942, "poiid": "B0G13G0N9H", "name": "东风雷诺品牌汽车(武汉鸿泰沌阳专营店)", "address": "四新地区管委会武汉市经济技术开发区东风大道3号", "type": "汽车销售;雷诺特约销售;雷诺销售", "typecode": "020800", "pcode": 420000, "pname": "湖北省", "citycode": 27, "cityname": "武汉市", "adcode": 420114, "adname": "蔡甸区", "business_a": "升官渡", "location": "114.192099,30.530733", "tel": "027-84555728", "fetch_time": "19/1/2025 06:27:10", "大类": "汽车销售", "中类": "雷诺特约销售", "小类": "雷诺销售", "wgs84经ti": 114.186582, "wgs84纬ti": 30.533162}}]}