{"type": "FeatureCollection", "features": [{"type": "Feature", "id": 62734, "geometry": {"type": "Point", "coordinates": [114.24621300003002, 30.70164100003217]}, "properties": {"OBJECTID": 62734, "poiid": "B0FFHQOVJS", "name": "旅游百事通(巢上城门市)", "address": "湖北省武汉市黄陂区盘龙城经济开发区巢上城商业街11-1", "type": "生活服务;旅行社;旅行社|购物服务;购物相关场所;购物相关场所", "typecode": "070100|060000", "pcode": 420000, "pname": "湖北省", "citycode": 27, "cityname": "武汉市", "adcode": 420116, "adname": "黄陂区", "business_a": " ", "location": "114.246213,30.701641", "tel": "15907190570", "fetch_time": "19/1/2025 12:03:55", "大类": "生活服务", "中类": "旅行社", "小类": "旅行社|购物服务;购物相关场所;购物相关场所", "wgs84经ti": 114.240783, "wgs84纬ti": 30.704056}}, {"type": "Feature", "id": 96502, "geometry": {"type": "Point", "coordinates": [114.38219199976106, 30.63032199996036]}, "properties": {"OBJECTID": 96502, "poiid": "B0G3VBA9IY", "name": "李八姑", "address": "建设四路江南春城-南区", "type": "生活服务;旅行社;旅行社|购物服务;购物相关场所;购物相关场所", "typecode": "070100|060000", "pcode": 420000, "pname": "湖北省", "citycode": 27, "cityname": "武汉市", "adcode": 420107, "adname": "青山区", "business_a": "八大家", "location": "114.382192,30.630322", "tel": " ", "fetch_time": "19/1/2025 23:01:41", "大类": "生活服务", "中类": "旅行社", "小类": "旅行社|购物服务;购物相关场所;购物相关场所", "wgs84经ti": 114.376642, "wgs84纬ti": 30.632591}}]}