{"type": "FeatureCollection", "features": [{"type": "Feature", "id": 1048, "geometry": {"type": "Point", "coordinates": [114.25805600028423, 30.426059999869153]}, "properties": {"OBJECTID": 1048, "poiid": "B0FFJWWOUE", "name": "湖北骏马志恒贸易有限公司", "address": "白沙洲大道华中动力汽车产业园9号", "type": "汽车销售;长城汽车销售;长城汽车销售|汽车维修;汽车维修;汽车维修", "typecode": "023300|030000", "pcode": 420000, "pname": "湖北省", "citycode": 27, "cityname": "武汉市", "adcode": 420111, "adname": "洪山区", "business_a": " ", "location": "114.258056,30.42606", "tel": "027-88028033;027-88030188", "fetch_time": "19/1/2025 20:53:16", "大类": "汽车销售", "中类": "长城汽车销售", "小类": "长城汽车销售|汽车维修;汽车维修;汽车维修", "wgs84经ti": 114.252656, "wgs84纬ti": 30.428572}}, {"type": "Feature", "id": 3687, "geometry": {"type": "Point", "coordinates": [114.25805600028423, 30.426059999869153]}, "properties": {"OBJECTID": 3687, "poiid": "B0FFJWWOUE", "name": "湖北骏马志恒贸易有限公司", "address": "白沙洲大道9号东瑞华中汽车城内", "type": "汽车销售;长城汽车销售;长城汽车销售|汽车维修;汽车维修;汽车维修", "typecode": "023300|030000", "pcode": 420000, "pname": "湖北省", "citycode": 27, "cityname": "武汉市", "adcode": 420111, "adname": "洪山区", "business_a": " ", "location": "114.258056,30.426060", "tel": "027-88028033;027-88030188", "fetch_time": "19/1/2025 07:04:13", "大类": "汽车销售", "中类": "长城汽车销售", "小类": "长城汽车销售|汽车维修;汽车维修;汽车维修", "wgs84经ti": 114.252656, "wgs84纬ti": 30.428572}}]}