{"type": "FeatureCollection", "features": [{"type": "Feature", "id": 31346, "geometry": {"type": "Point", "coordinates": [114.30055899979811, 30.334275000291086]}, "properties": {"OBJECTID": 31346, "poiid": "B0FFHHDXZ9", "name": "关山口铁路桥", "address": "江夏区", "type": "地名地址信息;交通地名;桥|地名地址信息;交通地名;立交桥", "typecode": "190307|190306", "pcode": 420000, "pname": "湖北省", "citycode": 27, "cityname": "武汉市", "adcode": 420115, "adname": "江夏区", "business_a": " ", "location": "114.300559,30.334275", "tel": " ", "fetch_time": "19/1/2025 20:41:12", "大类": "地名地址信息", "中类": "交通地名", "小类": "桥|地名地址信息;交通地名;立交桥", "wgs84经ti": 114.295143, "wgs84纬ti": 30.33676}}, {"type": "Feature", "id": 38185, "geometry": {"type": "Point", "coordinates": [114.43316300037225, 30.58984000011594]}, "properties": {"OBJECTID": 38185, "poiid": "B0G0MSMTAV", "name": "青化-鲁磨跨铁路桥", "address": "洪山区", "type": "地名地址信息;交通地名;桥|地名地址信息;交通地名;立交桥", "typecode": "190307|190306", "pcode": 420000, "pname": "湖北省", "citycode": 27, "cityname": "武汉市", "adcode": 420111, "adname": "洪山区", "business_a": " ", "location": "114.433163,30.589840", "tel": " ", "fetch_time": "19/1/2025 21:33:14", "大类": "地名地址信息", "中类": "交通地名", "小类": "桥|地名地址信息;交通地名;立交桥", "wgs84经ti": 114.427655, "wgs84纬ti": 30.592138}}, {"type": "Feature", "id": 57452, "geometry": {"type": "Point", "coordinates": [114.26259199992091, 30.26377100003168]}, "properties": {"OBJECTID": 57452, "poiid": "B0FFJ9T558", "name": "京珠立交桥", "address": "江夏区", "type": "地名地址信息;交通地名;桥|地名地址信息;交通地名;立交桥", "typecode": "190307|190306", "pcode": 420000, "pname": "湖北省", "citycode": 27, "cityname": "武汉市", "adcode": 420115, "adname": "江夏区", "business_a": " ", "location": "114.262592,30.263771", "tel": " ", "fetch_time": "19/1/2025 09:00:52", "大类": "地名地址信息", "中类": "交通地名", "小类": "桥|地名地址信息;交通地名;立交桥", "wgs84经ti": 114.257207, "wgs84纬ti": 30.266306}}, {"type": "Feature", "id": 152578, "geometry": {"type": "Point", "coordinates": [114.23594100027697, 30.84028400030644]}, "properties": {"OBJECTID": 152578, "poiid": "BY0001MAGQ", "name": "汉十立交桥", "address": "黄陂区", "type": "地名地址信息;交通地名;桥|地名地址信息;交通地名;立交桥", "typecode": "190307|190306", "pcode": 420000, "pname": "湖北省", "citycode": 27, "cityname": "武汉市", "adcode": 420116, "adname": "黄陂区", "business_a": " ", "location": "114.235941,30.840284", "tel": " ", "fetch_time": "19/1/2025 04:44:24", "大类": "地名地址信息", "中类": "交通地名", "小类": "桥|地名地址信息;交通地名;立交桥", "wgs84经ti": 114.230488, "wgs84纬ti": 30.842623}}]}