{"type": "FeatureCollection", "features": [{"type": "Feature", "id": 44044, "geometry": {"type": "Point", "coordinates": [114.28227700028344, 30.606142000053296]}, "properties": {"OBJECTID": 44044, "poiid": "B0GRJSMSY6", "name": "湖北云朵出行服务有限公司", "address": "香港路中华城b2栋2205室", "type": "生活服务;生活服务场所;生活服务场所|公司企业;公司;公司", "typecode": "070000|170200", "pcode": 420000, "pname": "湖北省", "citycode": 27, "cityname": "武汉市", "adcode": 420103, "adname": "江汉区", "business_a": "新华", "location": "114.282277,30.606142", "tel": "4000279928", "fetch_time": "19/1/2025 09:20:01", "大类": "生活服务", "中类": "生活服务场所", "小类": "生活服务场所|公司企业;公司;公司", "wgs84经ti": 114.276856, "wgs84纬ti": 30.60858}}, {"type": "Feature", "id": 102523, "geometry": {"type": "Point", "coordinates": [114.28227700028344, 30.606142000053296]}, "properties": {"OBJECTID": 102523, "poiid": "B0GRJSMSY6", "name": "湖北云朵出行服务有限公司", "address": "香港路中华城b2栋2205室", "type": "生活服务;生活服务场所;生活服务场所|公司企业;公司;公司", "typecode": "070000|170200", "pcode": 420000, "pname": "湖北省", "citycode": 27, "cityname": "武汉市", "adcode": 420103, "adname": "江汉区", "business_a": "建设大道", "location": "114.282277,30.606142", "tel": "4000279928", "fetch_time": "19/1/2025 06:29:49", "大类": "生活服务", "中类": "生活服务场所", "小类": "生活服务场所|公司企业;公司;公司", "wgs84经ti": 114.276856, "wgs84纬ti": 30.60858}}]}