{"type": "FeatureCollection", "features": [{"type": "Feature", "id": 14937, "geometry": {"type": "Point", "coordinates": [114.24893999988115, 30.59836200010625]}, "properties": {"OBJECTID": 14937, "poiid": "B0FFJ2U6IY", "name": "完美网络", "address": "万松街街道淮海路泛海国际SOHO城5栋4楼608", "type": "生活服务;生活服务场所;生活服务场所|公司企业;公司企业;公司企业|体育休闲服务;体育休闲服务场所;体育休闲服务场所", "typecode": "070000|170000|080000", "pcode": 420000, "pname": "湖北省", "citycode": 27, "cityname": "武汉市", "adcode": 420103, "adname": "江汉区", "business_a": " ", "location": "114.248940,30.598362", "tel": "027-59760001", "fetch_time": "19/1/2025 21:15:08", "大类": "生活服务", "中类": "生活服务场所", "小类": "生活服务场所|公司企业;公司企业;公司企业|体育休闲服务;体育休闲服务场所;体育休闲服务场所", "wgs84经ti": 114.243521, "wgs84纬ti": 30.600823}}]}