{"type": "FeatureCollection", "features": [{"type": "Feature", "id": 18798, "geometry": {"type": "Point", "coordinates": [114.35931999991817, 30.542081000138126]}, "properties": {"OBJECTID": 18798, "poiid": "B001B1DB1C", "name": "武汉大学社区卫生中心夜间急诊", "address": "八一路299号武汉大学", "type": "医疗保健服务;诊所;诊所|医疗保健服务;急救中心;急救中心", "typecode": "090300|090400", "pcode": 420000, "pname": "湖北省", "citycode": 27, "cityname": "武汉市", "adcode": 420106, "adname": "武昌区", "business_a": "珞珈山", "location": "114.359320,30.542081", "tel": "027-68772155", "fetch_time": "19/1/2025 12:03:55", "大类": "医疗保健服务", "中类": "诊所", "小类": "诊所|医疗保健服务;急救中心;急救中心", "wgs84经ti": 114.353797, "wgs84纬ti": 30.544411}}]}