{"type": "FeatureCollection", "features": [{"type": "Feature", "id": 1285, "geometry": {"type": "Point", "coordinates": [114.26288399989676, 30.61464199992838]}, "properties": {"OBJECTID": 1285, "poiid": "B0FFHVTMNN", "name": "华夏银行24小时自助银行(新华支行)", "address": "新华路589号大武汉19111F层", "type": "金融保险服务;自动提款机;华夏银行ATM|金融保险服务;银行相关;银行相关", "typecode": "160307|160200", "pcode": 420000, "pname": "湖北省", "citycode": 27, "cityname": "武汉市", "adcode": 420103, "adname": "江汉区", "business_a": "新华", "location": "114.262884,30.614642", "tel": " ", "fetch_time": "19/1/2025 21:00:52", "大类": "金融保险服务", "中类": "自动提款机", "小类": "华夏银行ATM|金融保险服务;银行相关;银行相关", "wgs84经ti": 114.257469, "wgs84纬ti": 30.617093}}]}