{"type": "FeatureCollection", "features": [{"type": "Feature", "id": 998, "geometry": {"type": "Point", "coordinates": [114.26972399966292, 30.57992999996958]}, "properties": {"OBJECTID": 998, "poiid": "B0FFHH3DIF", "name": "招商银行24小时自助银行(武商广场自助银行)", "address": "解放大道690号武汉国际广场购物中心b座2层", "type": "金融保险服务;自动提款机;招商银行ATM|金融保险服务;银行相关;银行相关", "typecode": "160306|160200", "pcode": 420000, "pname": "湖北省", "citycode": 27, "cityname": "武汉市", "adcode": 420103, "adname": "江汉区", "business_a": "万松", "location": "114.269724,30.579930", "tel": " ", "fetch_time": "19/1/2025 21:00:42", "大类": "金融保险服务", "中类": "自动提款机", "小类": "招商银行ATM|金融保险服务;银行相关;银行相关", "wgs84经ti": 114.264311, "wgs84纬ti": 30.58239}}, {"type": "Feature", "id": 7306, "geometry": {"type": "Point", "coordinates": [114.26975300010099, 30.57997800038447]}, "properties": {"OBJECTID": 7306, "poiid": "B0FFJ68GGV", "name": "招商银行24小时自助服务(武商广场自助银行)(武商MALL·武广A1座)", "address": "解放大道688号武商MALL·武广A1座L1层", "type": "金融保险服务;自动提款机;招商银行ATM|金融保险服务;银行相关;银行相关", "typecode": "160306|160200", "pcode": 420000, "pname": "湖北省", "citycode": 27, "cityname": "武汉市", "adcode": 420103, "adname": "江汉区", "business_a": "万松", "location": "114.269753,30.579978", "tel": " ", "fetch_time": "19/1/2025 04:02:07", "大类": "金融保险服务", "中类": "自动提款机", "小类": "招商银行ATM|金融保险服务;银行相关;银行相关", "wgs84经ti": 114.26434, "wgs84纬ti": 30.582438}}]}