{"type": "FeatureCollection", "features": [{"type": "Feature", "id": 1896, "geometry": {"type": "Point", "coordinates": [114.19037599985256, 30.480212999730213]}, "properties": {"OBJECTID": 1896, "poiid": "B0FFHKZ8NN", "name": "鸿海名车", "address": "江城大道538号一号车市A-28", "type": "汽车销售;汽车销售;汽车销售|汽车服务;二手车交易;二手车交易", "typecode": "020000|011000", "pcode": 420000, "pname": "湖北省", "citycode": 27, "cityname": "武汉市", "adcode": 420114, "adname": "蔡甸区", "business_a": "沌口", "location": "114.190376,30.480213", "tel": "13349875678", "fetch_time": "19/1/2025 21:20:59", "大类": "汽车销售", "中类": "汽车销售", "小类": "汽车销售|汽车服务;二手车交易;二手车交易", "wgs84经ti": 114.184858, "wgs84纬ti": 30.482654}}, {"type": "Feature", "id": 3991, "geometry": {"type": "Point", "coordinates": [114.19037599985256, 30.480212999730213]}, "properties": {"OBJECTID": 3991, "poiid": "B0FFHKZ8NN", "name": "鸿海名车", "address": "江城大道538号一号车市A-28", "type": "汽车销售;汽车销售;汽车销售|汽车服务;二手车交易;二手车交易", "typecode": "020000|011000", "pcode": 420000, "pname": "湖北省", "citycode": 27, "cityname": "武汉市", "adcode": 420114, "adname": "蔡甸区", "business_a": "沌口", "location": "114.190376,30.480213", "tel": "13349875678", "fetch_time": "19/1/2025 06:27:13", "大类": "汽车销售", "中类": "汽车销售", "小类": "汽车销售|汽车服务;二手车交易;二手车交易", "wgs84经ti": 114.184858, "wgs84纬ti": 30.482654}}]}