{"type": "FeatureCollection", "features": [{"type": "Feature", "id": 1835, "geometry": {"type": "Point", "coordinates": [114.25696999966578, 30.42002200021517]}, "properties": {"OBJECTID": 1835, "poiid": "B0FFG3GU5V", "name": "三福顺达", "address": "青菱街道白沙洲大道红霞村绅宝二手车交易市场", "type": "汽车销售;汽车销售;汽车销售|购物服务;购物相关场所;购物相关场所", "typecode": "020000|060000", "pcode": 420000, "pname": "湖北省", "citycode": 27, "cityname": "武汉市", "adcode": 420111, "adname": "洪山区", "business_a": " ", "location": "114.256970,30.420022", "tel": "13006358132", "fetch_time": "19/1/2025 20:45:50", "大类": "汽车销售", "中类": "汽车销售", "小类": "汽车销售|购物服务;购物相关场所;购物相关场所", "wgs84经ti": 114.25157, "wgs84纬ti": 30.422536}}, {"type": "Feature", "id": 2064, "geometry": {"type": "Point", "coordinates": [114.15039799986789, 30.62072199972056]}, "properties": {"OBJECTID": 2064, "poiid": "B0G2T74MRV", "name": "广汽菲克", "address": "二雅路明珠小区东侧约30米", "type": "汽车销售;汽车销售;汽车销售|购物服务;购物相关场所;购物相关场所", "typecode": "020000|060000", "pcode": 420000, "pname": "湖北省", "citycode": 27, "cityname": "武汉市", "adcode": 420112, "adname": "东西湖区", "business_a": "吴家山", "location": "114.150398,30.620722", "tel": " ", "fetch_time": "19/1/2025 09:04:48", "大类": "汽车销售", "中类": "汽车销售", "小类": "汽车销售|购物服务;购物相关场所;购物相关场所", "wgs84经ti": 114.144754, "wgs84纬ti": 30.623042}}, {"type": "Feature", "id": 2281, "geometry": {"type": "Point", "coordinates": [114.1542490002912, 30.6103109998528]}, "properties": {"OBJECTID": 2281, "poiid": "B0FFI1090J", "name": "雷丁电动汽车", "address": "舵落口大市场18区", "type": "汽车销售;汽车销售;汽车销售|购物服务;购物相关场所;购物相关场所", "typecode": "020000|060000", "pcode": 420000, "pname": "湖北省", "citycode": 27, "cityname": "武汉市", "adcode": 420112, "adname": "东西湖区", "business_a": " ", "location": "114.154249,30.610311", "tel": "15342270583", "fetch_time": "19/1/2025 12:03:55", "大类": "汽车销售", "中类": "汽车销售", "小类": "汽车销售|购物服务;购物相关场所;购物相关场所", "wgs84经ti": 114.148617, "wgs84纬ti": 30.612641}}, {"type": "Feature", "id": 2656, "geometry": {"type": "Point", "coordinates": [114.32510200025717, 30.58451099988281]}, "properties": {"OBJECTID": 2656, "poiid": "B0KDZ6JDTB", "name": "理想汽车武昌万象城零售中心", "address": "和平大道619号武昌万象城F1层", "type": "汽车销售;汽车销售;汽车销售|购物服务;购物相关场所;购物相关场所", "typecode": "020000|060000", "pcode": 420000, "pname": "湖北省", "citycode": 27, "cityname": "武汉市", "adcode": 420106, "adname": "武昌区", "business_a": "徐家棚", "location": "114.325102,30.584511", "tel": "18107093330", "fetch_time": "19/1/2025 04:03:26", "大类": "汽车销售", "中类": "汽车销售", "小类": "汽车销售|购物服务;购物相关场所;购物相关场所", "wgs84经ti": 114.319628, "wgs84纬ti": 30.586888}}]}