{"type": "FeatureCollection", "features": [{"type": "Feature", "id": 32964, "geometry": {"type": "Point", "coordinates": [114.19657000040525, 30.597926999831202]}, "properties": {"OBJECTID": 32964, "poiid": "B0FFH0IEL0", "name": "武汉铁路局旅行服务公司铁路客票代售(解放大道)", "address": "古田二路轻轨C出口", "type": "生活服务;售票处;火车票代售点|生活服务;售票处;长途汽车票代售点", "typecode": "070302|070303", "pcode": 420000, "pname": "湖北省", "citycode": 27, "cityname": "武汉市", "adcode": 420104, "adname": "硚口区", "business_a": "古田", "location": "114.196570,30.597927", "tel": " ", "fetch_time": "19/1/2025 21:25:50", "大类": "生活服务", "中类": "售票处", "小类": "火车票代售点|生活服务;售票处;长途汽车票代售点", "wgs84经ti": 114.191059, "wgs84纬ti": 30.600339}}]}