{"type": "FeatureCollection", "features": [{"type": "Feature", "id": 586, "geometry": {"type": "Point", "coordinates": [114.309167000157, 30.419344999572104]}, "properties": {"OBJECTID": 586, "poiid": "B0FFGE0TGC", "name": "超威电池", "address": "金樱街88号附近", "type": "摩托车服务;摩托车维修;摩托车维修|购物服务;专卖店;专营店", "typecode": "040200|061200", "pcode": 420000, "pname": "湖北省", "citycode": 27, "cityname": "武汉市", "adcode": 420115, "adname": "江夏区", "business_a": "大花岭", "location": "114.309167,30.419345", "tel": " ", "fetch_time": "19/1/2025 21:26:22", "大类": "摩托车服务", "中类": "摩托车维修", "小类": "摩托车维修|购物服务;专卖店;专营店", "wgs84经ti": 114.303732, "wgs84纬ti": 30.4218}}]}