{"type": "FeatureCollection", "features": [{"type": "Feature", "id": 8387, "geometry": {"type": "Point", "coordinates": [114.30219000036823, 30.58929300007196]}, "properties": {"OBJECTID": 8387, "poiid": "B001B1C0ND", "name": "同兴房产(洞庭街店)", "address": "一元街办事处胜利街164号一元街", "type": "政府机构及社会团体;政府机关;乡镇以下级政府及事业单位|生活服务;中介机构;中介机构", "typecode": "130106|071600", "pcode": 420000, "pname": "湖北省", "citycode": 27, "cityname": "武汉市", "adcode": 420102, "adname": "江岸区", "business_a": "大智路", "location": "114.302190,30.589293", "tel": " ", "fetch_time": "19/1/2025 21:04:26", "大类": "政府机构及社会团体", "中类": "政府机关", "小类": "乡镇以下级政府及事业单位|生活服务;中介机构;中介机构", "wgs84经ti": 114.29675, "wgs84纬ti": 30.591709}}]}