{"type": "FeatureCollection", "features": [{"type": "Feature", "id": 3649, "geometry": {"type": "Point", "coordinates": [114.30808199958472, 30.52959599995546]}, "properties": {"OBJECTID": 3649, "poiid": "B001B16Z49", "name": "武昌区教育局体育卫生艺术教育中心", "address": "首义路街办事处首义路252号", "type": "政府机构及社会团体;政府机关;区县级政府及事业单位|科教文化服务;培训机构;培训机构", "typecode": "130104|141400", "pcode": 420000, "pname": "湖北省", "citycode": 27, "cityname": "武汉市", "adcode": 420106, "adname": "武昌区", "business_a": "紫阳路", "location": "114.308082,30.529596", "tel": "027-88700000", "fetch_time": "19/1/2025 20:42:11", "大类": "政府机构及社会团体", "中类": "政府机关", "小类": "区县级政府及事业单位|科教文化服务;培训机构;培训机构", "wgs84经ti": 114.302639, "wgs84纬ti": 30.532023}}, {"type": "Feature", "id": 14928, "geometry": {"type": "Point", "coordinates": [114.38111899974206, 30.88511400011106]}, "properties": {"OBJECTID": 14928, "poiid": "B0FFGH5E2N", "name": "黄陂区反腐倡廉教育基地", "address": "百乐街与百泰路交叉口西北70米", "type": "政府机构及社会团体;政府机关;区县级政府及事业单位|科教文化服务;培训机构;培训机构", "typecode": "130104|141400", "pcode": 420000, "pname": "湖北省", "citycode": 27, "cityname": "武汉市", "adcode": 420116, "adname": "黄陂区", "business_a": "前川", "location": "114.381119,30.885114", "tel": " ", "fetch_time": "19/1/2025 20:46:27", "大类": "政府机构及社会团体", "中类": "政府机关", "小类": "区县级政府及事业单位|科教文化服务;培训机构;培训机构", "wgs84经ti": 114.375547, "wgs84纬ti": 30.887253}}, {"type": "Feature", "id": 29967, "geometry": {"type": "Point", "coordinates": [114.3810609997654, 30.885140999557507]}, "properties": {"OBJECTID": 29967, "poiid": "B0FFGH5E2N", "name": "黄陂区反腐倡廉教育基地", "address": "百乐街与百泰路交叉口西北70米", "type": "政府机构及社会团体;政府机关;区县级政府及事业单位|科教文化服务;培训机构;培训机构", "typecode": "130104|141400", "pcode": 420000, "pname": "湖北省", "citycode": 27, "cityname": "武汉市", "adcode": 420116, "adname": "黄陂区", "business_a": "前川", "location": "114.381061,30.885141", "tel": " ", "fetch_time": "19/1/2025 06:49:54", "大类": "政府机构及社会团体", "中类": "政府机关", "小类": "区县级政府及事业单位|科教文化服务;培训机构;培训机构", "wgs84经ti": 114.375489, "wgs84纬ti": 30.88728}}]}