{"type": "FeatureCollection", "features": [{"type": "Feature", "id": 4063, "geometry": {"type": "Point", "coordinates": [114.80009699997663, 30.84299100013459]}, "properties": {"OBJECTID": 4063, "poiid": "B001B064CE", "name": "武汉市新洲区档案馆", "address": "邾城街解放路4号", "type": "政府机构及社会团体;政府机关;区县级政府及事业单位|科教文化服务;档案馆;档案馆|生活服务;生活服务场所;生活服务场所", "typecode": "130104|140900|070000", "pcode": 420000, "pname": "湖北省", "citycode": 27, "cityname": "武汉市", "adcode": 420117, "adname": "新洲区", "business_a": "邾城", "location": "114.800097,30.842991", "tel": "027-86921515", "fetch_time": "19/1/2025 20:56:42", "大类": "政府机构及社会团体", "中类": "政府机关", "小类": "区县级政府及事业单位|科教文化服务;档案馆;档案馆|生活服务;生活服务场所;生活服务场所", "wgs84经ti": 114.794867, "wgs84纬ti": 30.845368}}, {"type": "Feature", "id": 30130, "geometry": {"type": "Point", "coordinates": [114.80009699997663, 30.84299100013459]}, "properties": {"OBJECTID": 30130, "poiid": "B001B064CE", "name": "武汉市新洲区档案馆", "address": "邾城街解放路4号", "type": "政府机构及社会团体;政府机关;区县级政府及事业单位|科教文化服务;档案馆;档案馆|生活服务;生活服务场所;生活服务场所", "typecode": "130104|140900|070000", "pcode": 420000, "pname": "湖北省", "citycode": 27, "cityname": "武汉市", "adcode": 420117, "adname": "新洲区", "business_a": "邾城", "location": "114.800097,30.842991", "tel": "027-86921515", "fetch_time": "19/1/2025 06:57:15", "大类": "政府机构及社会团体", "中类": "政府机关", "小类": "区县级政府及事业单位|科教文化服务;档案馆;档案馆|生活服务;生活服务场所;生活服务场所", "wgs84经ti": 114.794867, "wgs84纬ti": 30.845368}}]}