{"type": "FeatureCollection", "features": [{"type": "Feature", "id": 6661, "geometry": {"type": "Point", "coordinates": [114.3160940003379, 30.354208000398955]}, "properties": {"OBJECTID": 6661, "poiid": "B0FFLG5RZV", "name": "江夏区民主党派大楼", "address": "沙羡街与四贤路交叉口西北40米", "type": "政府机构及社会团体;政府机关;区县级政府及事业单位|商务住宅;楼宇;商务写字楼", "typecode": "130104|120201", "pcode": 420000, "pname": "湖北省", "citycode": 27, "cityname": "武汉市", "adcode": 420115, "adname": "江夏区", "business_a": "纸坊", "location": "114.316094,30.354208", "tel": " ", "fetch_time": "19/1/2025 20:37:01", "大类": "政府机构及社会团体", "中类": "政府机关", "小类": "区县级政府及事业单位|商务住宅;楼宇;商务写字楼", "wgs84经ti": 114.310654, "wgs84纬ti": 30.356663}}, {"type": "Feature", "id": 8350, "geometry": {"type": "Point", "coordinates": [114.80405800007668, 30.84216199967659]}, "properties": {"OBJECTID": 8350, "poiid": "B001B1C9LF", "name": "新洲区民政局社区服务大楼", "address": "齐安大道326号", "type": "政府机构及社会团体;政府机关;区县级政府及事业单位|商务住宅;楼宇;商务写字楼", "typecode": "130104|120201", "pcode": 420000, "pname": "湖北省", "citycode": 27, "cityname": "武汉市", "adcode": 420117, "adname": "新洲区", "business_a": "邾城", "location": "114.804058,30.842162", "tel": " ", "fetch_time": "19/1/2025 21:03:26", "大类": "政府机构及社会团体", "中类": "政府机关", "小类": "区县级政府及事业单位|商务住宅;楼宇;商务写字楼", "wgs84经ti": 114.798835, "wgs84纬ti": 30.844546}}, {"type": "Feature", "id": 29675, "geometry": {"type": "Point", "coordinates": [114.31622800022205, 30.354150999569015]}, "properties": {"OBJECTID": 29675, "poiid": "B0FFLG5RZV", "name": "江夏区民主党派大楼", "address": "民主党派办公楼", "type": "政府机构及社会团体;政府机关;区县级政府及事业单位|商务住宅;楼宇;商务写字楼", "typecode": "130104|120201", "pcode": 420000, "pname": "湖北省", "citycode": 27, "cityname": "武汉市", "adcode": 420115, "adname": "江夏区", "business_a": "纸坊", "location": "114.316228,30.354151", "tel": " ", "fetch_time": "19/1/2025 06:41:22", "大类": "政府机构及社会团体", "中类": "政府机关", "小类": "区县级政府及事业单位|商务住宅;楼宇;商务写字楼", "wgs84经ti": 114.310788, "wgs84纬ti": 30.356606}}, {"type": "Feature", "id": 30056, "geometry": {"type": "Point", "coordinates": [114.80405800007668, 30.84216199967659]}, "properties": {"OBJECTID": 30056, "poiid": "B001B1C9LF", "name": "新洲区民政局社区服务大楼", "address": "齐安大道326号", "type": "政府机构及社会团体;政府机关;区县级政府及事业单位|商务住宅;楼宇;商务写字楼", "typecode": "130104|120201", "pcode": 420000, "pname": "湖北省", "citycode": 27, "cityname": "武汉市", "adcode": 420117, "adname": "新洲区", "business_a": "邾城", "location": "114.804058,30.842162", "tel": " ", "fetch_time": "19/1/2025 06:57:07", "大类": "政府机构及社会团体", "中类": "政府机关", "小类": "区县级政府及事业单位|商务住宅;楼宇;商务写字楼", "wgs84经ti": 114.798835, "wgs84纬ti": 30.844546}}]}