{"type": "FeatureCollection", "features": [{"type": "Feature", "id": 3195, "geometry": {"type": "Point", "coordinates": [114.3109790000808, 30.545526999871186]}, "properties": {"OBJECTID": 3195, "poiid": "B001B1D5FB", "name": "武昌区司法局", "address": "荆南街14号", "type": "政府机构及社会团体;政府机关;区县级政府及事业单位|政府机构及社会团体;公检法机构;公检法机关", "typecode": "130104|130500", "pcode": 420000, "pname": "湖北省", "citycode": 27, "cityname": "武汉市", "adcode": 420106, "adname": "武昌区", "business_a": "小东门", "location": "114.310979,30.545527", "tel": "027-88936159", "fetch_time": "19/1/2025 21:32:22", "大类": "政府机构及社会团体", "中类": "政府机关", "小类": "区县级政府及事业单位|政府机构及社会团体;公检法机构;公检法机关", "wgs84经ti": 114.30553, "wgs84纬ti": 30.547944}}, {"type": "Feature", "id": 7459, "geometry": {"type": "Point", "coordinates": [114.79856899965966, 30.833013000449682]}, "properties": {"OBJECTID": 7459, "poiid": "B001B1CBHQ", "name": "武汉市新洲区劳动人事争议仲裁院", "address": "古城大道156号", "type": "政府机构及社会团体;政府机关;区县级政府及事业单位|政府机构及社会团体;公检法机构;公检法机关", "typecode": "130104|130500", "pcode": 420000, "pname": "湖北省", "citycode": 27, "cityname": "武汉市", "adcode": 420117, "adname": "新洲区", "business_a": "邾城", "location": "114.798569,30.833013", "tel": " ", "fetch_time": "19/1/2025 20:58:57", "大类": "政府机构及社会团体", "中类": "政府机关", "小类": "区县级政府及事业单位|政府机构及社会团体;公检法机构;公检法机关", "wgs84经ti": 114.793337, "wgs84纬ti": 30.835393}}, {"type": "Feature", "id": 11058, "geometry": {"type": "Point", "coordinates": [114.37696499973504, 30.86755399971736]}, "properties": {"OBJECTID": 11058, "poiid": "B0FFGOAX6O", "name": "黄陂区城市管理执法督察大队", "address": "前川街道民安街36号附1号", "type": "政府机构及社会团体;政府机关;区县级政府及事业单位|政府机构及社会团体;公检法机构;公检法机关", "typecode": "130104|130500", "pcode": 420000, "pname": "湖北省", "citycode": 27, "cityname": "武汉市", "adcode": 420116, "adname": "黄陂区", "business_a": "前川", "location": "114.376965,30.867554", "tel": " ", "fetch_time": "19/1/2025 21:03:46", "大类": "政府机构及社会团体", "中类": "政府机关", "小类": "区县级政府及事业单位|政府机构及社会团体;公检法机构;公检法机关", "wgs84经ti": 114.371397, "wgs84纬ti": 30.869707}}, {"type": "Feature", "id": 16735, "geometry": {"type": "Point", "coordinates": [114.31031600008339, 30.35091399958145]}, "properties": {"OBJECTID": 16735, "poiid": "B001B09VQ0", "name": "武汉仲裁委员会江夏分会", "address": "熊廷弼路154号", "type": "政府机构及社会团体;政府机关;区县级政府及事业单位|政府机构及社会团体;公检法机构;公检法机关", "typecode": "130104|130500", "pcode": 420000, "pname": "湖北省", "citycode": 27, "cityname": "武汉市", "adcode": 420115, "adname": "江夏区", "business_a": "纸坊", "location": "114.310316,30.350914", "tel": "027-87959784", "fetch_time": "19/1/2025 21:29:45", "大类": "政府机构及社会团体", "中类": "政府机关", "小类": "区县级政府及事业单位|政府机构及社会团体;公检法机构;公检法机关", "wgs84经ti": 114.304885, "wgs84纬ti": 30.35338}}]}