{"type": "FeatureCollection", "features": [{"type": "Feature", "id": 21054, "geometry": {"type": "Point", "coordinates": [114.30722999986472, 30.417992000130766]}, "properties": {"OBJECTID": 21054, "poiid": "B0FFLC72R3", "name": "中国中铁七局", "address": "武昌大道福地家园西侧约80米", "type": "政府机构及社会团体;政府机关;国家级机关及事业单位|公司企业;公司;建筑公司", "typecode": "130101|170202", "pcode": 420000, "pname": "湖北省", "citycode": 27, "cityname": "武汉市", "adcode": 420115, "adname": "江夏区", "business_a": "大花岭", "location": "114.307230,30.417992", "tel": " ", "fetch_time": "19/1/2025 08:56:27", "大类": "政府机构及社会团体", "中类": "政府机关", "小类": "国家级机关及事业单位|公司企业;公司;建筑公司", "wgs84经ti": 114.301798, "wgs84纬ti": 30.420451}}]}