{"type": "FeatureCollection", "features": [{"type": "Feature", "id": 667, "geometry": {"type": "Point", "coordinates": [114.28596200024617, 30.613837999723955]}, "properties": {"OBJECTID": 667, "poiid": "B0FFGCBGR8", "name": "武汉市发展和改革委员会(花桥工作区)", "address": "花桥街办事处黄孝河路17号", "type": "政府机构及社会团体;政府机关;地市级政府及事业单位|政府机构及社会团体;政府机关;乡镇级政府及事业单位", "typecode": "130103|130105", "pcode": 420000, "pname": "湖北省", "citycode": 27, "cityname": "武汉市", "adcode": 420102, "adname": "江岸区", "business_a": "花桥", "location": "114.285962,30.613838", "tel": " ", "fetch_time": "19/1/2025 20:58:18", "大类": "政府机构及社会团体", "中类": "政府机关", "小类": "地市级政府及事业单位|政府机构及社会团体;政府机关;乡镇级政府及事业单位", "wgs84经ti": 114.280537, "wgs84纬ti": 30.616269}}]}