{"type": "FeatureCollection", "features": [{"type": "Feature", "id": 12847, "geometry": {"type": "Point", "coordinates": [114.39146200007133, 30.626588999582737]}, "properties": {"OBJECTID": 12847, "poiid": "B0FFGPT72X", "name": "武汉市青山区南干渠游园管理处", "address": "工业一路18附17号附近", "type": "政府机构及社会团体;政府机关;政府机关相关|风景名胜;公园广场;公园广场", "typecode": "130100|110100", "pcode": 420000, "pname": "湖北省", "citycode": 27, "cityname": "武汉市", "adcode": 420107, "adname": "青山区", "business_a": "南干渠", "location": "114.391462,30.626589", "tel": " ", "fetch_time": "19/1/2025 20:39:58", "大类": "政府机构及社会团体", "中类": "政府机关", "小类": "政府机关相关|风景名胜;公园广场;公园广场", "wgs84经ti": 114.38591, "wgs84纬ti": 30.628854}}]}