{"type": "FeatureCollection", "features": [{"type": "Feature", "id": 28974, "geometry": {"type": "Point", "coordinates": [114.34552100029396, 30.50402999998454]}, "properties": {"OBJECTID": 28974, "poiid": "B0FFM10DEE", "name": "湖北省水利水电规划勘测设计院", "address": "珞狮路290号", "type": "政府机构及社会团体;政府机关;省直辖市级政府及事业单位|科教文化服务;科研机构;科研机构", "typecode": "130102|141300", "pcode": 420000, "pname": "湖北省", "citycode": 27, "cityname": "武汉市", "adcode": 420111, "adname": "洪山区", "business_a": "珞南", "location": "114.345521,30.504030", "tel": " ", "fetch_time": "19/1/2025 07:09:53", "大类": "政府机构及社会团体", "中类": "政府机关", "小类": "省直辖市级政府及事业单位|科教文化服务;科研机构;科研机构", "wgs84经ti": 114.340021, "wgs84纬ti": 30.506395}}]}