{"type": "FeatureCollection", "features": [{"type": "Feature", "id": 8230, "geometry": {"type": "Point", "coordinates": [114.30905400034192, 30.379327999587588]}, "properties": {"OBJECTID": 8230, "poiid": "B0FFLKLEZZ", "name": "和平农庄文体中心", "address": "武昌大道特8号", "type": "科教文化服务;文化宫;文化宫|体育休闲服务;休闲场所;休闲场所", "typecode": "140800|080500", "pcode": 420000, "pname": "湖北省", "citycode": 27, "cityname": "武汉市", "adcode": 420115, "adname": "江夏区", "business_a": " ", "location": "114.309054,30.379328", "tel": "17507135818", "fetch_time": "19/1/2025 21:35:18", "大类": "科教文化服务", "中类": "文化宫", "小类": "文化宫|体育休闲服务;休闲场所;休闲场所", "wgs84经ti": 114.303622, "wgs84纬ti": 30.381791}}]}