{"type": "FeatureCollection", "features": [{"type": "Feature", "id": 60711, "geometry": {"type": "Point", "coordinates": [114.31200599977717, 30.35003699960788]}, "properties": {"OBJECTID": 60711, "poiid": "B0FFGXY7G4", "name": "童萌会儿童剪发乐园", "address": "纸坊街道纸坊街新北路20号", "type": "生活服务;美容美发店;美容美发店|体育休闲服务;运动场馆;运动场所", "typecode": "071100|080100", "pcode": 420000, "pname": "湖北省", "citycode": 27, "cityname": "武汉市", "adcode": 420115, "adname": "江夏区", "business_a": "纸坊", "location": "114.312006,30.350037", "tel": " ", "fetch_time": "19/1/2025 12:03:55", "大类": "生活服务", "中类": "美容美发店", "小类": "美容美发店|体育休闲服务;运动场馆;运动场所", "wgs84经ti": 114.306573, "wgs84纬ti": 30.3525}}]}