{"type": "FeatureCollection", "features": [{"type": "Feature", "id": 132653, "geometry": {"type": "Point", "coordinates": [114.36537200021769, 30.40406099981533]}, "properties": {"OBJECTID": 132653, "poiid": "B0FFICMV4Q", "name": "上庸堂", "address": "阳光大道与阳光一路交叉口西100米", "type": "购物服务;专卖店;专营店|风景名胜;风景名胜相关;旅游景点", "typecode": "061200|110000", "pcode": 420000, "pname": "湖北省", "citycode": 27, "cityname": "武汉市", "adcode": 420115, "adname": "江夏区", "business_a": "庙山", "location": "114.365372,30.404061", "tel": "17786560888", "fetch_time": "19/1/2025 12:03:55", "大类": "购物服务", "中类": "专卖店", "小类": "专营店|风景名胜;风景名胜相关;旅游景点", "wgs84经ti": 114.359855, "wgs84纬ti": 30.40642}}, {"type": "Feature", "id": 181387, "geometry": {"type": "Point", "coordinates": [114.34035799962203, 30.667986000253734]}, "properties": {"OBJECTID": 181387, "poiid": "B0L6VDOO7H", "name": "中华唐犬汇", "address": "解放大道下延线辅路与堤边路交叉口东北140米", "type": "购物服务;专卖店;专营店|风景名胜;风景名胜相关;旅游景点", "typecode": "061200|110000", "pcode": 420000, "pname": "湖北省", "citycode": 27, "cityname": "武汉市", "adcode": 420102, "adname": "江岸区", "business_a": "长江新区", "location": "114.340358,30.667986", "tel": " ", "fetch_time": "19/1/2025 02:27:31", "大类": "购物服务", "中类": "专卖店", "小类": "专营店|风景名胜;风景名胜相关;旅游景点", "wgs84经ti": 114.334852, "wgs84纬ti": 30.670299}}]}