{"type": "FeatureCollection", "features": [{"type": "Feature", "id": 178931, "geometry": {"type": "Point", "coordinates": [114.37787100014657, 30.627775000316035]}, "properties": {"OBJECTID": 178931, "poiid": "B0J0ZH3S9S", "name": "西西弗书店(武商城市奥莱C潮品馆店)", "address": "和平大道959号武商城市奥莱1楼1017C-1", "type": "购物服务;专卖店;书店|购物服务;专卖店;珠宝首饰工艺品", "typecode": "061205|061202", "pcode": 420000, "pname": "湖北省", "citycode": 27, "cityname": "武汉市", "adcode": 420107, "adname": "青山区", "business_a": "建二", "location": "114.377871,30.627775", "tel": "027-86438818", "fetch_time": "19/1/2025 09:26:56", "大类": "购物服务", "中类": "专卖店", "小类": "书店|购物服务;专卖店;珠宝首饰工艺品", "wgs84经ti": 114.372323, "wgs84纬ti": 30.630049}}]}