{"type": "FeatureCollection", "features": [{"type": "Feature", "id": 110836, "geometry": {"type": "Point", "coordinates": [114.37548299974071, 30.873413000109906]}, "properties": {"OBJECTID": 110836, "poiid": "B0FFFQR2F4", "name": "果果爱童装童鞋", "address": "民安街311号", "type": "购物服务;专卖店;儿童用品店|餐饮服务;冷饮店;冷饮店", "typecode": "061207|050700", "pcode": 420000, "pname": "湖北省", "citycode": 27, "cityname": "武汉市", "adcode": 420116, "adname": "黄陂区", "business_a": "前川", "location": "114.375483,30.873413", "tel": " ", "fetch_time": "19/1/2025 12:03:55", "大类": "购物服务", "中类": "专卖店", "小类": "儿童用品店|餐饮服务;冷饮店;冷饮店", "wgs84经ti": 114.369915, "wgs84纬ti": 30.875564}}]}