{"type": "FeatureCollection", "features": [{"type": "Feature", "id": 37317, "geometry": {"type": "Point", "coordinates": [114.32019899988404, 30.352283999806787]}, "properties": {"OBJECTID": 37317, "poiid": "B0FFI0W8D1", "name": "小阿福(江夏店)", "address": "纸坊街古驿道花之都创业街一楼五街5-24号", "type": "购物服务;专卖店;儿童用品店|生活服务;摄影冲印店;摄影冲印", "typecode": "061207|071300", "pcode": 420000, "pname": "湖北省", "citycode": 27, "cityname": "武汉市", "adcode": 420115, "adname": "江夏区", "business_a": "纸坊", "location": "114.320199,30.352284", "tel": "027-81816870;15072333663;027-87955568", "fetch_time": "19/1/2025 21:32:55", "大类": "购物服务", "中类": "专卖店", "小类": "儿童用品店|生活服务;摄影冲印店;摄影冲印", "wgs84经ti": 114.314753, "wgs84纬ti": 30.354731}}, {"type": "Feature", "id": 163336, "geometry": {"type": "Point", "coordinates": [114.37722700012603, 30.867027999742447]}, "properties": {"OBJECTID": 163336, "poiid": "B0FFKCZSMR", "name": "黄陂大西瓜儿童摄影", "address": "前川街民安街16号", "type": "购物服务;专卖店;儿童用品店|生活服务;摄影冲印店;摄影冲印", "typecode": "061207|071300", "pcode": 420000, "pname": "湖北省", "citycode": 27, "cityname": "武汉市", "adcode": 420116, "adname": "黄陂区", "business_a": "前川", "location": "114.377227,30.867028", "tel": "027-85955990", "fetch_time": "19/1/2025 12:03:55", "大类": "购物服务", "中类": "专卖店", "小类": "儿童用品店|生活服务;摄影冲印店;摄影冲印", "wgs84经ti": 114.371659, "wgs84纬ti": 30.869181}}]}