{"type": "FeatureCollection", "features": [{"type": "Feature", "id": 51334, "geometry": {"type": "Point", "coordinates": [114.34299099963494, 30.588449999867635]}, "properties": {"OBJECTID": 51334, "poiid": "B001B1IOED", "name": "护童健康学习桌(销品茂店)", "address": "徐东大街18号销品茂4楼(西瓜庄园摄影对面)", "type": "购物服务;专卖店;儿童用品店|购物服务;家居建材市场;家居建材市场", "typecode": "061207|060600", "pcode": 420000, "pname": "湖北省", "citycode": 27, "cityname": "武汉市", "adcode": 420106, "adname": "武昌区", "business_a": "徐东大街", "location": "114.342991,30.588450", "tel": "18995549266", "fetch_time": "19/1/2025 22:38:33", "大类": "购物服务", "中类": "专卖店", "小类": "儿童用品店|购物服务;家居建材市场;家居建材市场", "wgs84经ti": 114.337488, "wgs84纬ti": 30.590791}}]}