{"type": "FeatureCollection", "features": [{"type": "Feature", "id": 90249, "geometry": {"type": "Point", "coordinates": [114.57635199984497, 30.65151000038628]}, "properties": {"OBJECTID": 90249, "poiid": "B0FFLGW2XS", "name": "宏光", "address": "平江东路与中份路交叉口西100米", "type": "购物服务;专卖店;古玩字画店|公司企业;公司;公司", "typecode": "061201|170200", "pcode": 420000, "pname": "湖北省", "citycode": 27, "cityname": "武汉市", "adcode": 420117, "adname": "新洲区", "business_a": "阳逻", "location": "114.576352,30.651510", "tel": " ", "fetch_time": "19/1/2025 09:27:33", "大类": "购物服务", "中类": "专卖店", "小类": "古玩字画店|公司企业;公司;公司", "wgs84经ti": 114.571275, "wgs84纬ti": 30.654119}}]}