{"type": "FeatureCollection", "features": [{"type": "Feature", "id": 41093, "geometry": {"type": "Point", "coordinates": [114.4078250001237, 30.49235800042146]}, "properties": {"OBJECTID": 41093, "poiid": "B0FFKTMYFR", "name": "团宠宠物酒店", "address": "关山大道保利时代北门15-S02商铺", "type": "购物服务;专卖店;宠物用品店|住宿服务;宾馆酒店;宾馆酒店", "typecode": "061211|100100", "pcode": 420000, "pname": "湖北省", "citycode": 27, "cityname": "武汉市", "adcode": 420111, "adname": "洪山区", "business_a": "关山", "location": "114.407825,30.492358", "tel": "13207145221", "fetch_time": "19/1/2025 21:21:40", "大类": "购物服务", "中类": "专卖店", "小类": "宠物用品店|住宿服务;宾馆酒店;宾馆酒店", "wgs84经ti": 114.40229, "wgs84纬ti": 30.494668}}, {"type": "Feature", "id": 147634, "geometry": {"type": "Point", "coordinates": [114.26298600010387, 30.615122999626806]}, "properties": {"OBJECTID": 147634, "poiid": "B0FFKVAENQ", "name": "猫先生猫咪酒店", "address": "新华西路三金大武汉1911B栋一层(24号)", "type": "购物服务;专卖店;宠物用品店|住宿服务;宾馆酒店;宾馆酒店", "typecode": "061211|100100", "pcode": 420000, "pname": "湖北省", "citycode": 27, "cityname": "武汉市", "adcode": 420103, "adname": "江汉区", "business_a": "新华", "location": "114.262986,30.615123", "tel": "13971091017", "fetch_time": "19/1/2025 12:03:55", "大类": "购物服务", "中类": "专卖店", "小类": "宠物用品店|住宿服务;宾馆酒店;宾馆酒店", "wgs84经ti": 114.257571, "wgs84纬ti": 30.617574}}]}