{"type": "FeatureCollection", "features": [{"type": "Feature", "id": 22390, "geometry": {"type": "Point", "coordinates": [114.25962499979391, 30.569034000219006]}, "properties": {"OBJECTID": 22390, "poiid": "B0FFKRJMI4", "name": "鱼乐园水族馆", "address": "武胜路(地铁站)Q口步行637米", "type": "购物服务;专卖店;宠物用品店|购物服务;花鸟鱼虫市场;宠物市场", "typecode": "061211|060502", "pcode": 420000, "pname": "湖北省", "citycode": 27, "cityname": "武汉市", "adcode": 420104, "adname": "硚口区", "business_a": "崇仁路", "location": "114.259625,30.569034", "tel": "15827064236", "fetch_time": "19/1/2025 21:28:42", "大类": "购物服务", "中类": "专卖店", "小类": "宠物用品店|购物服务;花鸟鱼虫市场;宠物市场", "wgs84经ti": 114.254213, "wgs84纬ti": 30.571504}}]}