{"type": "FeatureCollection", "features": [{"type": "Feature", "id": 1252, "geometry": {"type": "Point", "coordinates": [114.31416000018396, 30.64886499981992]}, "properties": {"OBJECTID": 1252, "poiid": "B0FFJ4BSY1", "name": "小角落宠物", "address": "万锦江城商铺8-12", "type": "购物服务;专卖店;宠物用品店|生活服务;生活服务场所;生活服务场所", "typecode": "061211|070000", "pcode": 420000, "pname": "湖北省", "citycode": 27, "cityname": "武汉市", "adcode": 420102, "adname": "江岸区", "business_a": "后湖", "location": "114.314160,30.648865", "tel": "18665904310", "fetch_time": "19/1/2025 20:57:43", "大类": "购物服务", "中类": "专卖店", "小类": "宠物用品店|生活服务;生活服务场所;生活服务场所", "wgs84经ti": 114.308698, "wgs84纬ti": 30.651236}}, {"type": "Feature", "id": 3384, "geometry": {"type": "Point", "coordinates": [114.25376500025459, 30.623943999915696]}, "properties": {"OBJECTID": 3384, "poiid": "B0FFI1NRXO", "name": "C&D宠物SPA会馆(顶琇店)", "address": "常青街办事处红旗渠路顶琇国际公馆商4", "type": "购物服务;专卖店;宠物用品店|生活服务;生活服务场所;生活服务场所", "typecode": "061211|070000", "pcode": 420000, "pname": "湖北省", "citycode": 27, "cityname": "武汉市", "adcode": 420103, "adname": "江汉区", "business_a": "常青", "location": "114.253765,30.623944", "tel": " ", "fetch_time": "19/1/2025 21:06:59", "大类": "购物服务", "中类": "专卖店", "小类": "宠物用品店|生活服务;生活服务场所;生活服务场所", "wgs84经ti": 114.248346, "wgs84纬ti": 30.626394}}, {"type": "Feature", "id": 27422, "geometry": {"type": "Point", "coordinates": [114.32685700025047, 30.34761799957107]}, "properties": {"OBJECTID": 27422, "poiid": "B0G1VA8ZSX", "name": "Angel pet爱宠工作室", "address": "兴新街东路44号", "type": "购物服务;专卖店;宠物用品店|生活服务;生活服务场所;生活服务场所", "typecode": "061211|070000", "pcode": 420000, "pname": "湖北省", "citycode": 27, "cityname": "武汉市", "adcode": 420115, "adname": "江夏区", "business_a": "纸坊", "location": "114.326857,30.347618", "tel": "13972830139", "fetch_time": "19/1/2025 21:34:52", "大类": "购物服务", "中类": "专卖店", "小类": "宠物用品店|生活服务;生活服务场所;生活服务场所", "wgs84经ti": 114.3214, "wgs84纬ti": 30.350053}}, {"type": "Feature", "id": 38894, "geometry": {"type": "Point", "coordinates": [114.29240299959883, 30.64016499971501]}, "properties": {"OBJECTID": 38894, "poiid": "B0FFF369TU", "name": "老友狗狗宠物店", "address": "后湖南路3-9号(近世纪家园)", "type": "购物服务;专卖店;宠物用品店|生活服务;生活服务场所;生活服务场所", "typecode": "061211|070000", "pcode": 420000, "pname": "湖北省", "citycode": 27, "cityname": "武汉市", "adcode": 420102, "adname": "江岸区", "business_a": "后湖", "location": "114.292403,30.640165", "tel": "13871478380;15827422274", "fetch_time": "19/1/2025 20:56:55", "大类": "购物服务", "中类": "专卖店", "小类": "宠物用品店|生活服务;生活服务场所;生活服务场所", "wgs84经ti": 114.28697, "wgs84纬ti": 30.642576}}]}