{"type": "FeatureCollection", "features": [{"type": "Feature", "id": 7124, "geometry": {"type": "Point", "coordinates": [114.80469799991283, 30.842019000276707]}, "properties": {"OBJECTID": 7124, "poiid": "B0FFGBPCIG", "name": "印刷", "address": "邾城街方坪里131号", "type": "购物服务;专卖店;摄影器材店|生活服务;摄影冲印店;摄影冲印", "typecode": "061212|071300", "pcode": 420000, "pname": "湖北省", "citycode": 27, "cityname": "武汉市", "adcode": 420117, "adname": "新洲区", "business_a": "邾城", "location": "114.804698,30.842019", "tel": " ", "fetch_time": "19/1/2025 21:25:43", "大类": "购物服务", "中类": "专卖店", "小类": "摄影器材店|生活服务;摄影冲印店;摄影冲印", "wgs84经ti": 114.799476, "wgs84纬ti": 30.844404}}]}