{"type": "FeatureCollection", "features": [{"type": "Feature", "id": 162315, "geometry": {"type": "Point", "coordinates": [114.57546000007903, 30.657088999557743]}, "properties": {"OBJECTID": 162315, "poiid": "B0FFGFWLTD", "name": "研究天下", "address": "军安路28号", "type": "购物服务;专卖店;烟酒专卖店|科教文化服务;科教文化场所;科教文化场所", "typecode": "061210|140000", "pcode": 420000, "pname": "湖北省", "citycode": 27, "cityname": "武汉市", "adcode": 420117, "adname": "新洲区", "business_a": "阳逻", "location": "114.575460,30.657089", "tel": "15377655556", "fetch_time": "19/1/2025 12:03:55", "大类": "购物服务", "中类": "专卖店", "小类": "烟酒专卖店|科教文化服务;科教文化场所;科教文化场所", "wgs84经ti": 114.570382, "wgs84纬ti": 30.659694}}]}