{"type": "FeatureCollection", "features": [{"type": "Feature", "id": 52555, "geometry": {"type": "Point", "coordinates": [114.33185000027731, 30.54413400038385]}, "properties": {"OBJECTID": 52555, "poiid": "B0FFK5QWYU", "name": "巴山夜雨茶馆(洪山体育馆店)", "address": "民主路786号", "type": "购物服务;专卖店;烟酒专卖店|餐饮服务;茶艺馆;茶艺馆", "typecode": "061210|050600", "pcode": 420000, "pname": "湖北省", "citycode": 27, "cityname": "武汉市", "adcode": 420106, "adname": "武昌区", "business_a": "中南路/中南", "location": "114.331850,30.544134", "tel": "027-87832173;027-87121918;027-87303868", "fetch_time": "19/1/2025 22:40:13", "大类": "购物服务", "中类": "专卖店", "小类": "烟酒专卖店|餐饮服务;茶艺馆;茶艺馆", "wgs84经ti": 114.326368, "wgs84纬ti": 30.546512}}, {"type": "Feature", "id": 73252, "geometry": {"type": "Point", "coordinates": [114.34878199958962, 30.08506300025732]}, "properties": {"OBJECTID": 73252, "poiid": "B0HB25WAJO", "name": "烟酒", "address": "星明街江夏区碧云小学西侧约240米", "type": "购物服务;专卖店;烟酒专卖店|餐饮服务;茶艺馆;茶艺馆", "typecode": "061210|050600", "pcode": 420000, "pname": "湖北省", "citycode": 27, "cityname": "武汉市", "adcode": 420115, "adname": "江夏区", "business_a": " ", "location": "114.348782,30.085063", "tel": " ", "fetch_time": "19/1/2025 09:27:37", "大类": "购物服务", "中类": "专卖店", "小类": "烟酒专卖店|餐饮服务;茶艺馆;茶艺馆", "wgs84经ti": 114.343313, "wgs84纬ti": 30.087474}}]}