{"type": "FeatureCollection", "features": [{"type": "Feature", "id": 21055, "geometry": {"type": "Point", "coordinates": [114.25856999970574, 30.6176670000321]}, "properties": {"OBJECTID": 21055, "poiid": "B001B1BZNW", "name": "武汉廷怀汝瓷艺术馆", "address": "新华街办事处金墩街财神广场", "type": "购物服务;专卖店;珠宝首饰工艺品|科教文化服务;展览馆;展览馆", "typecode": "061202|140200", "pcode": 420000, "pname": "湖北省", "citycode": 27, "cityname": "武汉市", "adcode": 420103, "adname": "江汉区", "business_a": "常青", "location": "114.258570,30.617667", "tel": " ", "fetch_time": "19/1/2025 21:14:36", "大类": "购物服务", "中类": "专卖店", "小类": "珠宝首饰工艺品|科教文化服务;展览馆;展览馆", "wgs84经ti": 114.253154, "wgs84纬ti": 30.620119}}]}