{"type": "FeatureCollection", "features": [{"type": "Feature", "id": 4361, "geometry": {"type": "Point", "coordinates": [114.26979200010078, 30.58027199955319]}, "properties": {"OBJECTID": 4361, "poiid": "B001B1C8Q8", "name": "宝格丽(武汉国际广场店)", "address": "解放大道688号武汉广场一楼", "type": "购物服务;专卖店;珠宝首饰工艺品|购物服务;个人用品/化妆品店;其它个人用品店", "typecode": "061202|061400", "pcode": 420000, "pname": "湖北省", "citycode": 27, "cityname": "武汉市", "adcode": 420103, "adname": "江汉区", "business_a": "新华", "location": "114.269792,30.580272", "tel": " ", "fetch_time": "19/1/2025 21:12:45", "大类": "购物服务", "中类": "专卖店", "小类": "珠宝首饰工艺品|购物服务;个人用品/化妆品店;其它个人用品店", "wgs84经ti": 114.264379, "wgs84纬ti": 30.582732}}]}