{"type": "FeatureCollection", "features": [{"type": "Feature", "id": 180184, "geometry": {"type": "Point", "coordinates": [114.27081899979703, 30.5805630003822]}, "properties": {"OBJECTID": 180184, "poiid": "B0FFGNKEC5", "name": "3D·JP(武商MALL店)", "address": "解放大道690号武商MALL·AB座B1层N-020", "type": "购物服务;专卖店;礼品饰品店|购物服务;专卖店;儿童用品店", "typecode": "061209|061207", "pcode": 420000, "pname": "湖北省", "citycode": 27, "cityname": "武汉市", "adcode": 420103, "adname": "江汉区", "business_a": "江滩", "location": "114.270819,30.580563", "tel": "027-85588126", "fetch_time": "19/1/2025 00:48:38", "大类": "购物服务", "中类": "专卖店", "小类": "礼品饰品店|购物服务;专卖店;儿童用品店", "wgs84经ti": 114.265406, "wgs84纬ti": 30.583022}}]}