{"type": "FeatureCollection", "features": [{"type": "Feature", "id": 81683, "geometry": {"type": "Point", "coordinates": [114.0313330004177, 30.583478999955958]}, "properties": {"OBJECTID": 81683, "poiid": "B0FFFFYTLK", "name": "祈福园", "address": "文昌街与正街南路交叉口西北40米", "type": "购物服务;专卖店;礼品饰品店|生活服务;丧葬设施;丧葬设施", "typecode": "061209|071900", "pcode": 420000, "pname": "湖北省", "citycode": 27, "cityname": "武汉市", "adcode": 420114, "adname": "蔡甸区", "business_a": " ", "location": "114.031333,30.583479", "tel": " ", "fetch_time": "19/1/2025 08:51:09", "大类": "购物服务", "中类": "专卖店", "小类": "礼品饰品店|生活服务;丧葬设施;丧葬设施", "wgs84经ti": 114.025653, "wgs84纬ti": 30.585858}}]}