{"type": "FeatureCollection", "features": [{"type": "Feature", "id": 110812, "geometry": {"type": "Point", "coordinates": [114.31942400011758, 30.519946000107893]}, "properties": {"OBJECTID": 110812, "poiid": "B0FFGCBDXX", "name": "自由客(武汉003店)", "address": "平安路与雄楚大道交叉口南50米", "type": "购物服务;专卖店;自行车专卖店|住宿服务;旅馆招待所;旅馆招待所", "typecode": "061208|100200", "pcode": 420000, "pname": "湖北省", "citycode": 27, "cityname": "武汉市", "adcode": 420106, "adname": "武昌区", "business_a": "丁字桥", "location": "114.319424,30.519946", "tel": " ", "fetch_time": "19/1/2025 12:03:55", "大类": "购物服务", "中类": "专卖店", "小类": "自行车专卖店|住宿服务;旅馆招待所;旅馆招待所", "wgs84经ti": 114.313965, "wgs84纬ti": 30.522356}}]}