{"type": "FeatureCollection", "features": [{"type": "Feature", "id": 292, "geometry": {"type": "Point", "coordinates": [114.01687400003516, 30.44940800007919]}, "properties": {"OBJECTID": 292, "poiid": "B0HG05ZFEN", "name": "小刘车行(联富街店)", "address": "车站南路星月花园西南侧约140米", "type": "购物服务;专卖店;自行车专卖店|生活服务;维修站点;维修站点|摩托车服务;摩托车维修;摩托车维修", "typecode": "061208|071200|040200", "pcode": 420000, "pname": "湖北省", "citycode": 27, "cityname": "武汉市", "adcode": 420114, "adname": "蔡甸区", "business_a": " ", "location": "114.016874,30.449408", "tel": " ", "fetch_time": "19/1/2025 20:54:19", "大类": "购物服务", "中类": "专卖店", "小类": "自行车专卖店|生活服务;维修站点;维修站点|摩托车服务;摩托车维修;摩托车维修", "wgs84经ti": 114.011241, "wgs84纬ti": 30.451869}}, {"type": "Feature", "id": 183978, "geometry": {"type": "Point", "coordinates": [114.01707600035718, 30.44930099964148]}, "properties": {"OBJECTID": 183978, "poiid": "B0HG05ZFEN", "name": "小刘车行(联富街店)", "address": "车站南路与云龙三路交叉口东80米", "type": "购物服务;专卖店;自行车专卖店|生活服务;维修站点;维修站点|摩托车服务;摩托车维修;摩托车维修", "typecode": "061208|071200|040200", "pcode": 420000, "pname": "湖北省", "citycode": 27, "cityname": "武汉市", "adcode": 420114, "adname": "蔡甸区", "business_a": " ", "location": "114.017076,30.449301", "tel": " ", "fetch_time": "19/1/2025 06:35:46", "大类": "购物服务", "中类": "专卖店", "小类": "自行车专卖店|生活服务;维修站点;维修站点|摩托车服务;摩托车维修;摩托车维修", "wgs84经ti": 114.011442, "wgs84纬ti": 30.451762}}]}