{"type": "FeatureCollection", "features": [{"type": "Feature", "id": 177283, "geometry": {"type": "Point", "coordinates": [114.418910999643, 30.326612000343573]}, "properties": {"OBJECTID": 177283, "poiid": "B0G2CG6XFT", "name": "湖北康帅园艺", "address": " ", "type": "购物服务;花鸟鱼虫市场;花卉市场|公司企业;公司企业;公司企业", "typecode": "060501|170000", "pcode": 420000, "pname": "湖北省", "citycode": 27, "cityname": "武汉市", "adcode": 420115, "adname": "江夏区", "business_a": " ", "location": "114.418911,30.326612", "tel": " ", "fetch_time": "19/1/2025 23:02:16", "大类": "购物服务", "中类": "花鸟鱼虫市场", "小类": "花卉市场|公司企业;公司企业;公司企业", "wgs84经ti": 114.413402, "wgs84纬ti": 30.328962}}]}