{"type": "FeatureCollection", "features": [{"type": "Feature", "id": 9292, "geometry": {"type": "Point", "coordinates": [114.26372800014713, 30.415105000095707]}, "properties": {"OBJECTID": 9292, "poiid": "B0FFIPTWGW", "name": "铭创定制", "address": "白沙洲特2号华中城建材市场7栋18号", "type": "公司企业;公司企业;公司企业|购物服务;家居建材市场;家居建材市场", "typecode": "170000|060600", "pcode": 420000, "pname": "湖北省", "citycode": 27, "cityname": "武汉市", "adcode": 420111, "adname": "洪山区", "business_a": " ", "location": "114.263728,30.415105", "tel": "15972400330;18971800177", "fetch_time": "19/1/2025 20:49:10", "大类": "公司企业", "中类": "公司企业", "小类": "公司企业|购物服务;家居建材市场;家居建材市场", "wgs84经ti": 114.25833, "wgs84纬ti": 30.417617}}]}