{"type": "FeatureCollection", "features": [{"type": "Feature", "id": 2562, "geometry": {"type": "Point", "coordinates": [114.37957100030144, 30.619456999840736]}, "properties": {"OBJECTID": 2562, "poiid": "B0FFFNOTEL", "name": "中国工商银行(青山钢花支行)", "address": "辽宁街9附4号", "type": "金融保险服务;银行;中国工商银行|金融保险服务;自动提款机;中国工商银行ATM", "typecode": "160105|160302", "pcode": 420000, "pname": "湖北省", "citycode": 27, "cityname": "武汉市", "adcode": 420107, "adname": "青山区", "business_a": "建二", "location": "114.379571,30.619457", "tel": "027-82215107;027-82218666", "fetch_time": "19/1/2025 20:48:57", "大类": "金融保险服务", "中类": "银行", "小类": "中国工商银行|金融保险服务;自动提款机;中国工商银行ATM", "wgs84经ti": 114.374023, "wgs84纬ti": 30.621733}}, {"type": "Feature", "id": 2756, "geometry": {"type": "Point", "coordinates": [114.3475539996175, 30.60455899989796]}, "properties": {"OBJECTID": 2756, "poiid": "B0FFHBMD99", "name": "中国工商银行(杨园支行)", "address": "和平大道980号馨都雅园1栋1-2号商铺", "type": "金融保险服务;银行;中国工商银行|金融保险服务;自动提款机;中国工商银行ATM", "typecode": "160105|160302", "pcode": 420000, "pname": "湖北省", "citycode": 27, "cityname": "武汉市", "adcode": 420106, "adname": "武昌区", "business_a": "杨园", "location": "114.347554,30.604559", "tel": "027-82216043", "fetch_time": "19/1/2025 20:51:36", "大类": "金融保险服务", "中类": "银行", "小类": "中国工商银行|金融保险服务;自动提款机;中国工商银行ATM", "wgs84经ti": 114.342042, "wgs84纬ti": 30.606886}}]}