{"type": "FeatureCollection", "features": [{"type": "Feature", "id": 3454, "geometry": {"type": "Point", "coordinates": [114.25578299978565, 30.523039999796197]}, "properties": {"OBJECTID": 3454, "poiid": "B0FFGCZ5KF", "name": "中国工商银行(武汉鹦鹉洲支行)", "address": "鹦鹉大道504附1号", "type": "金融保险服务;银行;中国工商银行|生活服务;生活服务场所;生活服务场所", "typecode": "160105|070000", "pcode": 420000, "pname": "湖北省", "citycode": 27, "cityname": "武汉市", "adcode": 420105, "adname": "汉阳区", "business_a": "洲头", "location": "114.255783,30.523040", "tel": "027-82216771;027-95588;027-82216772", "fetch_time": "19/1/2025 21:19:59", "大类": "金融保险服务", "中类": "银行", "小类": "中国工商银行|生活服务;生活服务场所;生活服务场所", "wgs84经ti": 114.250374, "wgs84纬ti": 30.525527}}]}