{"type": "FeatureCollection", "features": [{"type": "Feature", "id": 7903, "geometry": {"type": "Point", "coordinates": [114.2923829995758, 30.581512000078817]}, "properties": {"OBJECTID": 7903, "poiid": "B001B1ASL4", "name": "浙江实业银行(汉口分行)", "address": "中山大道910号浙江大楼F1层", "type": "金融保险服务;银行;银行|风景名胜;风景名胜;风景名胜", "typecode": "160100|110200", "pcode": 420000, "pname": "湖北省", "citycode": 27, "cityname": "武汉市", "adcode": 420102, "adname": "江岸区", "business_a": "大智路", "location": "114.292383,30.581512", "tel": " ", "fetch_time": "19/1/2025 07:18:46", "大类": "金融保险服务", "中类": "银行", "小类": "银行|风景名胜;风景名胜;风景名胜", "wgs84经ti": 114.286955, "wgs84纬ti": 30.583947}}]}