{"type": "FeatureCollection", "features": [{"type": "Feature", "id": 20697, "geometry": {"type": "Point", "coordinates": [114.28429199967616, 30.567070999626992]}, "properties": {"OBJECTID": 20697, "poiid": "B0FFFFWSSV", "name": "三利毛巾睡衣", "address": "汉正街855附3", "type": "购物服务;家居建材市场;布艺市场|购物服务;专卖店;专营店", "typecode": "060605|061200", "pcode": 420000, "pname": "湖北省", "citycode": 27, "cityname": "武汉市", "adcode": 420103, "adname": "江汉区", "business_a": "江滩", "location": "114.284292,30.567071", "tel": "027-85668039;027-59316018", "fetch_time": "19/1/2025 21:14:12", "大类": "购物服务", "中类": "家居建材市场", "小类": "布艺市场|购物服务;专卖店;专营店", "wgs84经ti": 114.278873, "wgs84纬ti": 30.569522}}]}