{"type": "FeatureCollection", "features": [{"type": "Feature", "id": 16337, "geometry": {"type": "Point", "coordinates": [114.39722499963409, 30.336471999982848]}, "properties": {"OBJECTID": 16337, "poiid": "B0FFFZ39U7", "name": "温馨家纺复印照相", "address": "界兴路201号附4", "type": "购物服务;家居建材市场;布艺市场|生活服务;摄影冲印店;摄影冲印", "typecode": "060605|071300", "pcode": 420000, "pname": "湖北省", "citycode": 27, "cityname": "武汉市", "adcode": 420115, "adname": "江夏区", "business_a": " ", "location": "114.397225,30.336472", "tel": "15926379668", "fetch_time": "19/1/2025 21:35:30", "大类": "购物服务", "中类": "家居建材市场", "小类": "布艺市场|生活服务;摄影冲印店;摄影冲印", "wgs84经ti": 114.391699, "wgs84纬ti": 30.338815}}, {"type": "Feature", "id": 71712, "geometry": {"type": "Point", "coordinates": [114.34390599956225, 30.60127100025653]}, "properties": {"OBJECTID": 71712, "poiid": "B001B0JUUQ", "name": "美好阳光摄影", "address": "和平大道743附15号", "type": "购物服务;家居建材市场;布艺市场|生活服务;摄影冲印店;摄影冲印", "typecode": "060605|071300", "pcode": 420000, "pname": "湖北省", "citycode": 27, "cityname": "武汉市", "adcode": 420106, "adname": "武昌区", "business_a": "杨园", "location": "114.343906,30.601271", "tel": "027-51157398", "fetch_time": "19/1/2025 09:17:11", "大类": "购物服务", "中类": "家居建材市场", "小类": "布艺市场|生活服务;摄影冲印店;摄影冲印", "wgs84经ti": 114.3384, "wgs84纬ti": 30.603606}}]}