{"type": "FeatureCollection", "features": [{"type": "Feature", "id": 23252, "geometry": {"type": "Point", "coordinates": [114.32038500036754, 30.543944999762004]}, "properties": {"OBJECTID": 23252, "poiid": "B0FFFDCRLP", "name": "欧景壁纸布艺(民主路店)", "address": "中南路街办事处民主路531号", "type": "购物服务;家居建材市场;建材五金市场|购物服务;家居建材市场;布艺市场", "typecode": "060603|060605", "pcode": 420000, "pname": "湖北省", "citycode": 27, "cityname": "武汉市", "adcode": 420106, "adname": "武昌区", "business_a": "中南路/中南", "location": "114.320385,30.543945", "tel": " ", "fetch_time": "19/1/2025 20:53:29", "大类": "购物服务", "中类": "家居建材市场", "小类": "建材五金市场|购物服务;家居建材市场;布艺市场", "wgs84经ti": 114.314922, "wgs84纬ti": 30.546345}}, {"type": "Feature", "id": 39497, "geometry": {"type": "Point", "coordinates": [114.22436699983723, 30.588276999983634]}, "properties": {"OBJECTID": 39497, "poiid": "B0FFGODVQU", "name": "郁金香软装(总部)", "address": "解放大道387号南国大家装H座1-3层", "type": "购物服务;家居建材市场;建材五金市场|购物服务;家居建材市场;布艺市场", "typecode": "060603|060605", "pcode": 420000, "pname": "湖北省", "citycode": 27, "cityname": "武汉市", "adcode": 420104, "adname": "硚口区", "business_a": "宗关", "location": "114.224367,30.588277", "tel": "027-85811678;027-83877593", "fetch_time": "19/1/2025 21:25:11", "大类": "购物服务", "中类": "家居建材市场", "小类": "建材五金市场|购物服务;家居建材市场;布艺市场", "wgs84经ti": 114.218918, "wgs84纬ti": 30.59073}}, {"type": "Feature", "id": 71997, "geometry": {"type": "Point", "coordinates": [114.03093400000421, 30.583536999932676]}, "properties": {"OBJECTID": 71997, "poiid": "B0FFG704OY", "name": "佳美乐(文昌街店)", "address": "蔡后街4号", "type": "购物服务;家居建材市场;建材五金市场|购物服务;家居建材市场;布艺市场", "typecode": "060603|060605", "pcode": 420000, "pname": "湖北省", "citycode": 27, "cityname": "武汉市", "adcode": 420114, "adname": "蔡甸区", "business_a": " ", "location": "114.030934,30.583537", "tel": "18971535155;13545163851", "fetch_time": "19/1/2025 09:20:29", "大类": "购物服务", "中类": "家居建材市场", "小类": "建材五金市场|购物服务;家居建材市场;布艺市场", "wgs84经ti": 114.025255, "wgs84纬ti": 30.585917}}, {"type": "Feature", "id": 154765, "geometry": {"type": "Point", "coordinates": [114.27222199974551, 30.575892999962036]}, "properties": {"OBJECTID": 154765, "poiid": "B0FFHEGW2I", "name": "金典墙纸软包布艺", "address": "顺道街46号", "type": "购物服务;家居建材市场;建材五金市场|购物服务;家居建材市场;布艺市场", "typecode": "060603|060605", "pcode": 420000, "pname": "湖北省", "citycode": 27, "cityname": "武汉市", "adcode": 420104, "adname": "硚口区", "business_a": "江滩", "location": "114.272222,30.575893", "tel": " ", "fetch_time": "19/1/2025 12:03:55", "大类": "购物服务", "中类": "家居建材市场", "小类": "建材五金市场|购物服务;家居建材市场;布艺市场", "wgs84经ti": 114.266809, "wgs84纬ti": 30.578353}}]}