{"type": "FeatureCollection", "features": [{"type": "Feature", "id": 3488, "geometry": {"type": "Point", "coordinates": [114.358184999738, 30.043567999563606]}, "properties": {"OBJECTID": 3488, "poiid": "B001B17GDL", "name": "武汉市贺站林产品交易大市场", "address": "京港线与纸贺路交叉路口往西约220米", "type": "购物服务;家居建材市场;建材五金市场|购物服务;综合市场;综合市场", "typecode": "060603|060700", "pcode": 420000, "pname": "湖北省", "citycode": 27, "cityname": "武汉市", "adcode": 420115, "adname": "江夏区", "business_a": " ", "location": "114.358185,30.043568", "tel": " ", "fetch_time": "19/1/2025 21:07:05", "大类": "购物服务", "中类": "家居建材市场", "小类": "建材五金市场|购物服务;综合市场;综合市场", "wgs84经ti": 114.352707, "wgs84纬ti": 30.045963}}]}