{"type": "FeatureCollection", "features": [{"type": "Feature", "id": 82171, "geometry": {"type": "Point", "coordinates": [114.29261899966718, 30.802582000059317]}, "properties": {"OBJECTID": 82171, "poiid": "B0FFKAVQTD", "name": "线条之家", "address": "横店中兴街56", "type": "购物服务;家居建材市场;建材五金市场|地名地址信息;地名地址信息;地名地址信息", "typecode": "060603|190000", "pcode": 420000, "pname": "湖北省", "citycode": 27, "cityname": "武汉市", "adcode": 420116, "adname": "黄陂区", "business_a": "横店", "location": "114.292619,30.802582", "tel": "15872433440", "fetch_time": "19/1/2025 09:11:19", "大类": "购物服务", "中类": "家居建材市场", "小类": "建材五金市场|地名地址信息;地名地址信息;地名地址信息", "wgs84经ti": 114.287172, "wgs84纬ti": 30.804912}}]}