{"type": "FeatureCollection", "features": [{"type": "Feature", "id": 84489, "geometry": {"type": "Point", "coordinates": [114.22127500024112, 30.60696100005015]}, "properties": {"OBJECTID": 84489, "poiid": "B0FFL4D89K", "name": "星辰手缝方向盘套", "address": "常码头汽配用品市场南三门旁", "type": "购物服务;家居建材市场;建材五金市场|汽车服务;汽车养护/装饰;汽车养护|公司企业;公司;公司", "typecode": "060603|010400|170200", "pcode": 420000, "pname": "湖北省", "citycode": 27, "cityname": "武汉市", "adcode": 420104, "adname": "硚口区", "business_a": "古田", "location": "114.221275,30.606961", "tel": "13212792258", "fetch_time": "19/1/2025 09:09:03", "大类": "购物服务", "中类": "家居建材市场", "小类": "建材五金市场|汽车服务;汽车养护/装饰;汽车养护|公司企业;公司;公司", "wgs84经ti": 114.215819, "wgs84纬ti": 30.609404}}]}