{"type": "FeatureCollection", "features": [{"type": "Feature", "id": 16664, "geometry": {"type": "Point", "coordinates": [114.26310100001115, 30.32947099998671]}, "properties": {"OBJECTID": 16664, "poiid": "B0FFL5UID7", "name": "邓禄普轮胎", "address": "郑店金东路18号菜场旁", "type": "购物服务;家居建材市场;建材五金市场|汽车服务;汽车配件销售;汽车配件销售", "typecode": "060603|010800", "pcode": 420000, "pname": "湖北省", "citycode": 27, "cityname": "武汉市", "adcode": 420115, "adname": "江夏区", "business_a": "郑店", "location": "114.263101,30.329471", "tel": "13659850172;13429894833", "fetch_time": "19/1/2025 20:42:56", "大类": "购物服务", "中类": "家居建材市场", "小类": "建材五金市场|汽车服务;汽车配件销售;汽车配件销售", "wgs84经ti": 114.25771, "wgs84纬ti": 30.331999}}, {"type": "Feature", "id": 18916, "geometry": {"type": "Point", "coordinates": [114.80837500040604, 30.828819000396606]}, "properties": {"OBJECTID": 18916, "poiid": "B0FFFFNSHU", "name": "二毛朝阳轮胎", "address": "龙腾大道幸福时代对面", "type": "购物服务;家居建材市场;建材五金市场|汽车服务;汽车配件销售;汽车配件销售", "typecode": "060603|010800", "pcode": 420000, "pname": "湖北省", "citycode": 27, "cityname": "武汉市", "adcode": 420117, "adname": "新洲区", "business_a": "邾城", "location": "114.808375,30.828819", "tel": "13018095718;027-86912803;027-86926205", "fetch_time": "19/1/2025 20:56:12", "大类": "购物服务", "中类": "家居建材市场", "小类": "建材五金市场|汽车服务;汽车配件销售;汽车配件销售", "wgs84经ti": 114.803161, "wgs84纬ti": 30.831218}}, {"type": "Feature", "id": 112073, "geometry": {"type": "Point", "coordinates": [114.42591299968524, 30.62662600038965]}, "properties": {"OBJECTID": 112073, "poiid": "B0FFGQ1D2G", "name": "三元汽车玻璃", "address": "冶金大道与工人村路交叉口西南20米", "type": "购物服务;家居建材市场;建材五金市场|汽车服务;汽车配件销售;汽车配件销售", "typecode": "060603|010800", "pcode": 420000, "pname": "湖北省", "citycode": 27, "cityname": "武汉市", "adcode": 420107, "adname": "青山区", "business_a": "厂前", "location": "114.425913,30.626626", "tel": "13808670471;13871395328", "fetch_time": "19/1/2025 12:03:55", "大类": "购物服务", "中类": "家居建材市场", "小类": "建材五金市场|汽车服务;汽车配件销售;汽车配件销售", "wgs84经ti": 114.420388, "wgs84纬ti": 30.6289}}]}