{"type": "FeatureCollection", "features": [{"type": "Feature", "id": 4, "geometry": {"type": "Point", "coordinates": [114.42046800039793, 30.535996000115347]}, "properties": {"OBJECTID": 4, "poiid": "B001B0I8R5", "name": "易东高尔夫练习场", "address": "鲁磨路东湖钓鱼台", "type": "体育休闲服务;高尔夫相关;高尔夫练习场|体育休闲服务;高尔夫相关;高尔夫球场", "typecode": "080202|080201", "pcode": 420000, "pname": "湖北省", "citycode": 27, "cityname": "武汉市", "adcode": 420111, "adname": "洪山区", "business_a": " ", "location": "114.420468,30.535996", "tel": "15071390333", "fetch_time": "19/1/2025 11:43:03", "大类": "体育休闲服务", "中类": "高尔夫相关", "小类": "高尔夫练习场|体育休闲服务;高尔夫相关;高尔夫球场", "wgs84经ti": 114.414943, "wgs84纬ti": 30.538299}}, {"type": "Feature", "id": 12, "geometry": {"type": "Point", "coordinates": [114.42046800039793, 30.535996000115347]}, "properties": {"OBJECTID": 12, "poiid": "B001B0I8R5", "name": "易东高尔夫练习场", "address": "鲁磨路东湖钓鱼台", "type": "体育休闲服务;高尔夫相关;高尔夫练习场|体育休闲服务;高尔夫相关;高尔夫球场", "typecode": "080202|080201", "pcode": 420000, "pname": "湖北省", "citycode": 27, "cityname": "武汉市", "adcode": 420111, "adname": "洪山区", "business_a": " ", "location": "114.420468,30.535996", "tel": "15071390333", "fetch_time": "19/1/2025 07:55:03", "大类": "体育休闲服务", "中类": "高尔夫相关", "小类": "高尔夫练习场|体育休闲服务;高尔夫相关;高尔夫球场", "wgs84经ti": 114.414943, "wgs84纬ti": 30.538299}}, {"type": "Feature", "id": 72, "geometry": {"type": "Point", "coordinates": [114.42046800039793, 30.535996000115347]}, "properties": {"OBJECTID": 72, "poiid": "B001B0I8R5", "name": "易东高尔夫练习场", "address": "鲁磨路东湖钓鱼台", "type": "体育休闲服务;高尔夫相关;高尔夫练习场|体育休闲服务;高尔夫相关;高尔夫球场", "typecode": "080202|080201", "pcode": 420000, "pname": "湖北省", "citycode": 27, "cityname": "武汉市", "adcode": 420111, "adname": "洪山区", "business_a": " ", "location": "114.420468,30.535996", "tel": "15071390333", "fetch_time": "19/1/2025 07:34:25", "大类": "体育休闲服务", "中类": "高尔夫相关", "小类": "高尔夫练习场|体育休闲服务;高尔夫相关;高尔夫球场", "wgs84经ti": 114.414943, "wgs84纬ti": 30.538299}}, {"type": "Feature", "id": 3777, "geometry": {"type": "Point", "coordinates": [114.42046800039793, 30.535996000115347]}, "properties": {"OBJECTID": 3777, "poiid": "B001B0I8R5", "name": "易东高尔夫练习场", "address": "鲁磨路东湖钓鱼台", "type": "体育休闲服务;高尔夫相关;高尔夫练习场|体育休闲服务;高尔夫相关;高尔夫球场", "typecode": "080202|080201", "pcode": 420000, "pname": "湖北省", "citycode": 27, "cityname": "武汉市", "adcode": 420111, "adname": "洪山区", "business_a": " ", "location": "114.420468,30.535996", "tel": " ", "fetch_time": "19/1/2025 21:13:10", "大类": "体育休闲服务", "中类": "高尔夫相关", "小类": "高尔夫练习场|体育休闲服务;高尔夫相关;高尔夫球场", "wgs84经ti": 114.414943, "wgs84纬ti": 30.538299}}, {"type": "Feature", "id": 20056, "geometry": {"type": "Point", "coordinates": [114.42046800039793, 30.535996000115347]}, "properties": {"OBJECTID": 20056, "poiid": "B001B0I8R5", "name": "易东高尔夫练习场", "address": "鲁磨路东湖钓鱼台", "type": "体育休闲服务;高尔夫相关;高尔夫练习场|体育休闲服务;高尔夫相关;高尔夫球场", "typecode": "080202|080201", "pcode": 420000, "pname": "湖北省", "citycode": 27, "cityname": "武汉市", "adcode": 420111, "adname": "洪山区", "business_a": " ", "location": "114.420468,30.535996", "tel": "15071390333", "fetch_time": "19/1/2025 07:36:22", "大类": "体育休闲服务", "中类": "高尔夫相关", "小类": "高尔夫练习场|体育休闲服务;高尔夫相关;高尔夫球场", "wgs84经ti": 114.414943, "wgs84纬ti": 30.538299}}, {"type": "Feature", "id": 22365, "geometry": {"type": "Point", "coordinates": [114.42046800039793, 30.535996000115347]}, "properties": {"OBJECTID": 22365, "poiid": "B001B0I8R5", "name": "易东高尔夫练习场", "address": "鲁磨路东湖钓鱼台", "type": "体育休闲服务;高尔夫相关;高尔夫练习场|体育休闲服务;高尔夫相关;高尔夫球场", "typecode": "080202|080201", "pcode": 420000, "pname": "湖北省", "citycode": 27, "cityname": "武汉市", "adcode": 420111, "adname": "洪山区", "business_a": " ", "location": "114.420468,30.535996", "tel": "15071390333", "fetch_time": "19/1/2025 07:57:24", "大类": "体育休闲服务", "中类": "高尔夫相关", "小类": "高尔夫练习场|体育休闲服务;高尔夫相关;高尔夫球场", "wgs84经ti": 114.414943, "wgs84纬ti": 30.538299}}]}