{"type": "FeatureCollection", "features": [{"type": "Feature", "id": 945, "geometry": {"type": "Point", "coordinates": [114.25683199959713, 30.41907000038026]}, "properties": {"OBJECTID": 945, "poiid": "B0G2U611AI", "name": "东风商用车专营店", "address": "白沙洲大道绅宝新车交易市场", "type": "汽车销售;东风特约销售;东风销售|汽车销售;福特特约销售;福特销售", "typecode": "022200|021800", "pcode": 420000, "pname": "湖北省", "citycode": 27, "cityname": "武汉市", "adcode": 420111, "adname": "洪山区", "business_a": " ", "location": "114.256832,30.419070", "tel": " ", "fetch_time": "19/1/2025 21:34:15", "大类": "汽车销售", "中类": "东风特约销售", "小类": "东风销售|汽车销售;福特特约销售;福特销售", "wgs84经ti": 114.251432, "wgs84纬ti": 30.421584}}]}