{"type": "FeatureCollection", "features": [{"type": "Feature", "id": 5891, "geometry": {"type": "Point", "coordinates": [114.15103300037276, 30.558609999751752]}, "properties": {"OBJECTID": 5891, "poiid": "B0HRNAVCAM", "name": "武汉宝丰世纪汽车服务有限公司", "address": "汉阳大道董家店汽车交易中心特9号", "type": "汽车维修;通用特约维修;别克维修|汽车销售;通用特约销售;别克销售", "typecode": "030502|020402", "pcode": 420000, "pname": "湖北省", "citycode": 27, "cityname": "武汉市", "adcode": 420105, "adname": "汉阳区", "business_a": " ", "location": "114.151033,30.558610", "tel": "027-83846188;15927169584", "fetch_time": "19/1/2025 06:39:31", "大类": "汽车维修", "中类": "通用特约维修", "小类": "别克维修|汽车销售;通用特约销售;别克销售", "wgs84经ti": 114.145396, "wgs84纬ti": 30.560954}}]}